Workbook

Sheet Start
E6: MM HOLDING GMBH · UNTERNEHMERISCHE BETEILIGUNGEN · WEINGARTEN | G6: ERSTELLT FÜR
E7: =Obj_Name -> Beispiel: 3-Zimmer-Eigentumswohnung | G7: Max Mustermann
E9: Immobilien-Kalkulation
E11: Kauf · Finanzierung · Cashflow · Steuern · Exit — für vermietete Immobilien im Privatvermögen oder in der GmbH
E12: ="Stand "&TEXT(DAY(TODAY()),"00")&"."&TEXT(MONTH(TODAY()),"00")&"."&YEAR(TODAY())&" · Rechtsstand September 2026 · Kauf als: "&CHOOSE(Rechtsform_Idx,"Privatperson","vv-GmbH","GmbH / Holding") -> Stand 24.09.2026 · Rechtsstand September 2026 · Kauf als: Privatperson
E14: GESAMTINVESTITION | F14: KAUFPREIS | G14: HALTEDAUER
E15: =Gesamtinvestition -> 328974.5 | F15: =Kaufpreis -> 285000 | G15: =Haltedauer -> 12
E17: Zuerst: Kauf als wählen ↓ | F17: Leitfaden starten ›
C21: Kauf als – Privatperson oder Gesellschaft | G21: Pflichtauswahl
C23: KAUF ALS ▾ Auswahlliste | D23: Privatperson – Einkünfte aus Vermietung und Verpachtung (§ 21 EStG) | G23: Auswahl ändern ▾
D24: ▾ Klicken und aus der Liste wählen: Privatperson · vv-GmbH · gewerbliche GmbH/Holding · wirkt auf S09 Steuern, S11 Exit, Dashboard und Bankgespräch
C26: Aktuelle Kalkulation im Überblick | G26: Details im Dashboard ›
C27: CASHFLOW N. ST. / MONAT (JAHR 1) | E27: BRUTTOMIETRENDITE | F27: DSCR | G27: =UPPER("IRR n. St. ("&Haltedauer&" J.)") -> IRR N. ST. (12 J.)
C28: =CF_nSt_Monat_J1 -> 256.53305 | E28: =Bruttomietrendite -> 0.04 | F28: =DSCR_J1 -> 0.612 | G28: =EK_IRR -> 0.053273956
C29: ="Jahr 2: "&SUBSTITUTE(FIXED(INDEX(Projektion!$D$37:$AQ$37,2),0),"-","−")&" €" -> Jahr 2: −274 € | D29: =IF(CF_nSt_Monat_J1<0,"● kritisch",IF(INDEX(Projektion!$D$37:$AQ$37,2)<0,"● prüfen",IF(ISNUMBER(CF_nSt_Monat_J1),"● erfüllt",""))) -> ● prüfen | E29: ="Ziel ≥ "&FIXED(Ampel_BMR_gruen*100,1)&" %" -> Ziel ≥ 5.0 % | F29: ="Jahr 1 · "&"Ziel ≥ "&FIXED(Ampel_DSCR_gruen,2)&"×" -> Jahr 1 · Ziel ≥ 1.20× | G29: ="Ziel ≥ "&FIXED(Ampel_IRR_gruen*100,1)&" %" -> Ziel ≥ 6.0 %
C30: Cashflow nach Steuern pro Monat (Jahr 1) | E30: DSCR (Jahr 1) | F30: ="IRR n. St. – Verkauf nach "&Haltedauer&" J." -> IRR n. St. – Verkauf nach 12 J. | G30: Rechtsform | AfA
C31: =CF_nSt_Monat_J1 -> 256.53305 | E31: =DSCR_J1 -> 0.612 | F31: =EK_IRR -> 0.053273956 | G31: =CHOOSE(Rechtsform_Idx,"Privat","vv-GmbH","GmbH")&" | "&CHOOSE(Methode_eff,"nach Baujahr","linear 2 %","linear 2,5 %","linear 3 %","degressiv","Gutachten") -> Privat | nach Baujahr
C34: Ihr Weg durch das Tool | G34: 6 Etappen · A–F
C35: A Kauf als wählen › | E35: Privatperson oder Gesellschaft – die Auswahl oben steuert Steuern, Exit und Bankunterlagen.
C36: B Leitfaden: Schritte 01–12 › | E36: Vom Objekt bis zum Ergebnis – jede Seite mit Eingaben, Zwischenergebnis und Einordnung.
C37: C Dashboard › | E37: Die Gesamtbewertung auf einer Seite: Kennzahlen mit Status, Cashflow und Vermögen.
C38: D Cockpit & Diagramme › | E38: Detailkennzahlen und Prüfhinweise im Cockpit, alle Auswertungen als Diagramm.
C39: E Sensitivität › | E39: Break-even-Miete und -Zins, Miete × Zins und IRR-Matrix – wie robust ist die Rechnung?
C40: F Bankunterlagen › | E40: Bankgespräch als A4-Übersicht, dazu Haushaltsrechnung und Vermögensaufstellung.
C46: Legende | F46: Alle Blätter | G46: Schritte S01–S12: siehe Leitfaden
C48: Eingabe | D48: Gelb hinterlegt – hier eingeben, Beispielwerte überschreiben | F48: Leitfaden › | G48: Zwölf Schritte vom Objekt zum Ergebnis
C49: Verknüpfung | D49: Blau – übernommen aus einer Eingabe an anderer Stelle | F49: Dashboard › | G49: Gesamtbewertung auf einer Seite
C50: Berechnung | D50: Schwarz – berechnet, bitte nicht ändern | F50: Cockpit › | G50: Detailkennzahlen und Prüfhinweise
C51: Ergebnis | D51: Hervorgehoben – Summe bzw. Blockergebnis | F51: Diagramme › | G51: 13 Diagramme zur Kalkulation
C52: −1.234 € | D52: Rot – negative Ergebnis- und Kumulwerte | F52: Eingaben › | G52: Alle Eingaben und Profi-Felder
C53: Status | D53: ● erfüllt · ● prüfen · ● kritisch | F53: Projektion › | G53: Miete, Kosten, Vermögen – 40 Jahre
C54: Prüfhinweis | D54: ▲ Warnung ⓘ Information | F54: Steuern › | G54: Steuerparameter, AfA, Ergebnis, Exit
C55: Blattschutz | D55: ohne Passwort – bei Bedarf aufheben | F55: AfA-Vergleich › | G55: Abschreibungsvarianten im Vergleich
C56: Navigation | D56: Reiter oben · „Weiter ›“ führt zum nächsten Schritt | F56: Finanzierung › | G56: Tilgungspläne Darlehen I und II
F57: Sensitivität › | G57: Break-even, Miete × Zins, IRR-Matrix
C58: Tipp & Support | F58: Bankgespräch › | G58: Investitionsübersicht für die Bank
C59: Beispielwerte in den gelben Feldern einfach überschreiben – alle Blätter rechnen sofort mit. Hilfe zu jedem Eingabefeld: Zelle markieren – der Eingabehinweis erscheint. Jedes Blatt ist für den Druck auf A4 eingerichtet. Blattwechsel per Tastatur: Strg + Bild ↓ / Bild ↑. Version Pro · Rechtsstand September 2026 · MM Holding GmbH, Weingarten | F59: Haushaltsrechnung › | G59: Selbstauskunft Einnahmen/Ausgaben
F60: Vermögensaufstellung › | G60: Selbstauskunft Vermögen
F61: Hinweise › | G61: Rechtsgrundlagen und Modellannahmen
F62: Konfiguration › | G62: Stammdaten, Tarif 2026, Ampel-Schwellen
C64: Keine Gewähr für die Richtigkeit der Angaben · ersetzt keine Rechts-, Steuer- oder Finanzberatung · Rechtsstand September 2026
C65: MM Holding GmbH · Kornhausgasse 4 · 88250 Weingarten · Amtsgericht Ulm HRB 750729

Sheet Leitfaden
C5: EINSTIEG › IN ZWÖLF SCHRITTEN ZUR INVESTITIONSENTSCHEIDUNG | I5: ‹ Start
C6: Leitfaden | H6: Schritt 01 starten ›
C7: Hinweis Gelbe Felder enthalten Beispielwerte – einfach überschreiben. „Kauf als“ wählen Sie auf der Startseite. | F7: Kauf als wählen ›
C9: GESAMTINVESTITION | E9: EIGENKAPITALBEDARF INKL. RESERVE | F9: RATE AN DIE BANK / MONAT | H9: CASHFLOW N. ST. / MONAT (JAHR 1)
C10: =Gesamtinvestition -> 328974.5 | E10: =EK_Bedarf_gesamt -> 83974.5 | F10: =Kapitaldienst_Monat_J1 -> 1166.6667 | H10: =CF_nSt_Monat_J1 -> 256.53305
C11: ="Kaufpreis "&FIXED(Kaufpreis,0)&" € · NK "&FIXED(NK_Quote*100,1)&" %" -> Kaufpreis 285,000 € · NK 10.6 % | E11: ="Quote "&FIXED(EK_Quote*100,1)&" % · Beleihung "&FIXED(Beleihung*100,1)&" %" -> Quote 24.0 % · Beleihung 87.7 % | F11: ="Volltilgung "&Volltilgung_Txt -> Volltilgung Jahr 32 (2057) | H11: ="Jahr 2: "&SUBSTITUTE(FIXED(INDEX(Projektion!$D$37:$AQ$37,2),0),"-","−")&" €" -> Jahr 2: −274 € | I11: =IF(CF_nSt_Monat_J1<0,"● kritisch",IF(INDEX(Projektion!$D$37:$AQ$37,2)<0,"● prüfen",IF(ISNUMBER(CF_nSt_Monat_J1),"● erfüllt",""))) -> ● prüfen
C12: Cashflow vor Steuern pro Monat (Jahr 1) | E12: Bruttomietrendite | F12: DSCR (Jahr 1) | H12: ="Eigenkapitalrendite p. a. (IRR) – Verkauf nach "&Haltedauer&" J." -> Eigenkapitalrendite p. a. (IRR) – Verkauf nach 12 J.
C13: =CF_vSt_J1/12 -> -452.66667 | E13: =Bruttomietrendite -> 0.04 | F13: =DSCR_J1 -> 0.612 | H13: =EK_IRR -> 0.053273956
C16: Die zwölf Schritte | F16: ✓ vollständig ○ Angaben fehlen
C17: STATUS | D17: SCHRITT | E17: INHALT
C18: =IF(AND(Wohnflaeche>0,Baujahr>0),"✓","○") -> ✓ | D18: 01 Objekt › | E18: Objektdaten, Baujahr, Kaufdatum und Bundesland – die Basis für Grunderwerbsteuer und AfA.
C19: =IF(AND(Kaufpreis>0,Miete_Monat>0),"✓","○") -> ✓ | D19: 02 Kaufpreis & Miete › | E19: Kaufpreis und Nettokaltmiete ergeben die erste Kennzahl: die Bruttomietrendite.
C20: =IF(NK_Summe>0,"✓","○") -> ✓ | D20: 03 Kaufnebenkosten › | E20: Grunderwerbsteuer, Notar, Grundbuch und Makler – sie erhöhen die AfA-Basis.
C21: =IF(AK_Gebaeude>0,"✓","○") -> ✓ | D21: 04 Kaufpreisaufteilung › | E21: Nur der Gebäudeanteil ist abschreibbar – Aufteilung in Grund und Boden und Gebäude.
C22: optional | D22: 05 Maßnahmen & Reserve › | E22: Renovierung, Sonderumlagen und Liquiditätsreserve – inklusive Prüfung der 15 %-Grenze.
C23: =IF(Hausgeld+Verwaltung_Monat+IH_Ruecklage_qm>0,"✓","○") -> ✓ | D23: 06 Bewirtschaftung › | E23: Hausgeld, Verwaltung, Rücklagen und Mietausfall – was von der Miete monatlich übrig bleibt.
C24: =IF(Darlehen_Summe>0,"✓","○") -> ✓ | D24: 07 Finanzierung › | E24: Darlehen, Zins, Tilgung und Zinsbindung – Rate, Eigenkapital und Restschuld.
C25: =IF(Darlehen_Summe>0,"✓","○") -> ✓ | D25: 08 Zwischenergebnis › | E25: Cashflow vor Steuern: Miete abzüglich Bewirtschaftung, Zinsen und Tilgung.
C26: =IF(OR(Rechtsform_Idx>1,zvE>0),"✓","○") -> ✓ | D26: 09 Steuern › | E26: Kauf als, Einkommen, Soli und Kirchensteuer – daraus folgt der angewendete Steuersatz.
C27: =IF(AfA_J1>0,"✓","○") -> ✓ | D27: 10 Abschreibung › | E27: AfA-Methode, Sonder-AfA § 7b und erhöhte Absetzungen § 7h/7i – der steuerliche Hebel.
C28: =IF(Haltedauer>0,"✓","○") -> ✓ | D28: 11 Prognose & Exit › | E28: Miet-, Kosten- und Wertsteigerung, Haltedauer und Verkauf – inklusive 10-Jahres-Frist.
C29: =IF(COUNTIF(C18:C28,"○")>0,"○","✓") -> ✓ | D29: 12 Ergebnis › | E29: Cashflow nach Steuern, Eigenkapitalrendite, Vermögensaufbau und Rente nach Volltilgung.
C31: Zum Dashboard › | H31: Schritt 01 starten ›
C33: Keine Gewähr für die Richtigkeit der Angaben · ersetzt keine Rechts-, Steuer- oder Finanzberatung · Rechtsstand September 2026
C34: MM Holding GmbH · Kornhausgasse 4 · 88250 Weingarten · Amtsgericht Ulm HRB 750729

Sheet S01 Objekt
C5: SCHRITT 01 / 12 · OBJEKT | I5: ‹ Leitfaden
C6: Objekt | H6: =Obj_Name -> Beispiel: 3-Zimmer-Eigentumswohnung
C7: Was wird gekauft? Objektdaten, Baujahr, Kaufdatum und Bundesland – die Basis für Grunderwerbsteuer und Abschreibung. | H7: =Obj_Adresse&IFERROR(IF(Erstellt_fuer="",""," · Erstellt für "&Erstellt_fuer),"") -> Musterstraße 1, 88250 Weingarten · Erstellt für Max Mustermann
C10: Eingaben | H10: Ergebnis dieses Schritts | I10: beim Kauf
C11: POSITION | D11: EINGABE | E11: EINHEIT | F11: HINWEIS | H11: Grunderwerbsteuersatz (Bundesland) | I11: =GrESt_Satz -> 0.05
C12: Objektbezeichnung | D12: Beispiel: 3-Zimmer-Eigentumswohnung | F12: Freitext – erscheint im Cockpit und im Bankgespräch | H12: Regulärer AfA-Satz nach Baujahr | I12: =AfA_Satz_auto -> 0.02
C13: Adresse | D13: Musterstraße 1, 88250 Weingarten | H13: Erstes Kalkulationsjahr | I13: =YEAR(Kaufdatum) -> 2026
C14: Objektart | D14: Eigentumswohnung | F14: Gewerbe: keine § 7b-Sonder-AfA, keine degressive AfA | H14: Wohngebäude (steuerlich) | I14: =IF(Wohngebaeude=1,"Ja","Nein (Gewerbe)") -> Ja
C15: Wohn-/Nutzfläche | D15: 75 | F15: Basis für Miete/m², Rücklage und § 7b-Grenzen
C16: Grundstücksfläche bzw. -anteil | D16: 120 | F16: ETW: Miteigentumsanteil × Fläche (Teilungserklärung) | H16: AfA nach Baujahr
C17: Baujahr (Fertigstellung) | D17: 1996 | F17: steuert den AfA-Satz und die Prüfung von § 7b | H17: =IF(Baujahr>=2023,"Neubau (Fertigstellung ab 2023): 3 % lineare AfA. Degressive AfA (5 % vom Restwert) und die Sonder-AfA § 7b (5 % p. a., 4 Jahre) stehen in Schritt 10 zur Wahl – sofern Baubeginn, Effizienzstandard und Baukostengrenze passen.",IF(Baujahr<1925,"Altbau (vor 1925): 2,5 % lineare AfA. Bei Baudenkmalen oder Sanierungsgebieten können erhöhte Absetzungen nach § 7h/7i EStG hinzukommen (Schritt 10).","Bestandsobjekt: 2 % lineare AfA. Eine kürzere Restnutzungsdauer lässt sich nur mit einem Sachverständigengutachten durchsetzen (Schritt 10).")) -> Bestandsobjekt: 2 % lineare AfA. Eine kürzere Restnutzungsdauer lässt sich nur mit einem Sachverständigengutachten durchsetzen (Schritt 10).
C18: Kaufdatum (Nutzen und Lasten) | D18: 46357 | F18: Jahr 1 = die ersten 12 Monate ab Kauf
C19: Bundesland (Belegenheit) | D19: Baden-Württemberg | F19: steuert den Grunderwerbsteuersatz
H20: ALS NÄCHSTES | I20: Schritt 02 / 12
C21: Hinweis Alle gelben Felder enthalten Beispielwerte – einfach überschreiben. | F21: Kauf als auf der Startseite wählen › | H21: Kaufpreis & Miete · Kaufpreis und Nettokaltmiete ergeben die erste Kennzahl: die Bruttomietrendite.
C25: ‹ Zurück: Start (Kauf als) | E25: Übersicht: Leitfaden | H25: Weiter: Kaufpreis & Miete ›
C27: Keine Gewähr für die Richtigkeit der Angaben · ersetzt keine Rechts-, Steuer- oder Finanzberatung · Rechtsstand September 2026
C28: MM Holding GmbH · Kornhausgasse 4 · 88250 Weingarten · Amtsgericht Ulm HRB 750729

Sheet S02 Kaufpreis & Miete
C5: SCHRITT 02 / 12 · KAUFPREIS & MIETE | I5: ‹ Leitfaden
C6: Kaufpreis & Miete | H6: =Obj_Name -> Beispiel: 3-Zimmer-Eigentumswohnung
C7: Kaufpreis und Nettokaltmiete ergeben die erste Kennzahl: die Bruttomietrendite. | H7: =Obj_Adresse&IFERROR(IF(Erstellt_fuer="",""," · Erstellt für "&Erstellt_fuer),"") -> Musterstraße 1, 88250 Weingarten · Erstellt für Max Mustermann
C10: Eingaben | H10: Ergebnis dieses Schritts | I10: Kauf · Jahr 1
C11: POSITION | D11: EINGABE | E11: EINHEIT | F11: HINWEIS | H11: Kaufpreis ohne Inventar/Rücklage | I11: =KP_Immobilie -> 274000
C12: Kaufpreis (gesamt lt. Kaufvertrag) | D12: 285000 | F12: inkl. beweglicher Gegenstände und Rücklagenanteil | H12: Kaufpreis je m² | I12: =IF(Wohnflaeche>0,KP_Immobilie/Wohnflaeche,0) -> 3653.3333
C13: davon bewegliche Gegenstände | D13: 8000 | F13: Küche, Möbel · grunderwerbsteuerfrei (§ 2 GrEStG) | H13: Nettokaltmiete je m² | I13: =Miete_qm -> 12.666667
C14: Nutzungsdauer der Gegenstände | D14: 10 | F14: Küche i. d. R. 10 Jahre, Möbel 8–13 (AfA-Tabelle) | H14: Kaufpreisfaktor | I14: =Kaufpreisfaktor -> 25
C15: davon Anteil Erhaltungsrücklage | D15: 3000 | F15: nicht abschreibbar, aber grunderwerbsteuerpflichtig | H15: = Bruttomietrendite | I15: =Bruttomietrendite -> 0.04
C16: Nettokaltmiete | D16: 950 | E16: pro Monat | F16: Soll-Miete lt. Mietvertrag bzw. Marktmiete | H16: nachrichtlich: Warmmiete pro Monat | I16: =Miete_Monat+NK_umlagefaehig -> 1170
C17: Umlagefähige Betriebskosten | D17: 220 | E17: pro Monat | F17: Vorauszahlung des Mieters · Durchlaufposten
H18: Bruttomietrendite | I18: =IF(AND(ISNUMBER(Bruttomietrendite),Bruttomietrendite<Ampel_BMR_gelb),"● kritisch"&" · "&FIXED(Bruttomietrendite*100,1)&" %",IF(AND(ISNUMBER(Bruttomietrendite),Bruttomietrendite<Ampel_BMR_gruen),"● prüfen"&" · "&FIXED(Bruttomietrendite*100,1)&" %",IF(ISNUMBER(Bruttomietrendite),"● erfüllt"&" · "&FIXED(Bruttomietrendite*100,1)&" %",""))) -> ● prüfen · 4.0 %
H19: =IF(Bruttomietrendite<Ampel_BMR_gelb,"Unter "&FIXED(Ampel_BMR_gelb*100,1)&" % trägt sich das Objekt aus der Miete allein meist nicht – bei üblicher Finanzierung wird der Cashflow vor Steuern negativ. Es rechnet sich dann nur über Tilgung, Wertentwicklung und Steuereffekte.",IF(Bruttomietrendite<Ampel_BMR_gruen,"Ausbaufähig: Solide ist eine Bruttomietrendite ab "&FIXED(Ampel_BMR_gruen*100,1)&" %, zwischen "&FIXED(Ampel_BMR_gelb*100,1)&" und "&FIXED(Ampel_BMR_gruen*100,1)&" % trägt sich die Finanzierung meist nur mit mehr Eigenkapital. Ob der Cashflow reicht, zeigen die Schritte 6 bis 10.","Solide: Das Ziel von "&FIXED(Ampel_BMR_gruen*100,1)&" % ist erreicht. Ob der Cashflow nach Kapitaldienst und Steuern positiv ist, entscheidet sich in den Schritten 6 bis 10.")) -> Ausbaufähig: Solide ist eine Bruttomietrendite ab 5.0 %, zwischen 4.0 und 5.0 % trägt sich die Finanzierung meist nur mit mehr Eigenkapital. Ob der Cashflow reicht, zeigen die Schritte 6 bis 10.
H21: ALS NÄCHSTES | I21: Schritt 03 / 12
H22: Kaufnebenkosten · Grunderwerbsteuer, Notar, Grundbuch und Makler – sie erhöhen die Anschaffungskosten und damit die AfA-Basis.
C25: ‹ Zurück: Objekt | E25: Übersicht: Leitfaden | H25: Weiter: Kaufnebenkosten ›
C27: Keine Gewähr für die Richtigkeit der Angaben · ersetzt keine Rechts-, Steuer- oder Finanzberatung · Rechtsstand September 2026
C28: MM Holding GmbH · Kornhausgasse 4 · 88250 Weingarten · Amtsgericht Ulm HRB 750729

Sheet S03 Kaufnebenkosten
C5: SCHRITT 03 / 12 · KAUFNEBENKOSTEN | I5: ‹ Leitfaden
C6: Kaufnebenkosten | H6: =Obj_Name -> Beispiel: 3-Zimmer-Eigentumswohnung
C7: Grunderwerbsteuer, Notar, Grundbuch und Makler – sie erhöhen die Anschaffungskosten und damit die AfA-Basis. | H7: =Obj_Adresse&IFERROR(IF(Erstellt_fuer="",""," · Erstellt für "&Erstellt_fuer),"") -> Musterstraße 1, 88250 Weingarten · Erstellt für Max Mustermann
C10: Eingaben | H10: Ergebnis dieses Schritts | I10: beim Kauf
C11: POSITION | D11: EINGABE | E11: EINHEIT | F11: HINWEIS | H11: Grunderwerbsteuer | I11: =GrESt_Betrag -> 13850
C12: Grunderwerbsteuer abweichend | F12: optional · leer = Satz des Bundeslands (siehe Ergebnis) | H12: Notar | I12: =Notar_Betrag -> 4275
C13: Notar (Kaufvertrag, Auflassung) | D13: 0.015 | F13: üblich 1,0 – 1,5 % des Kaufpreises | H13: Grundbuch | I13: =Grundbuch_Betrag -> 1425
C14: Grundbuchamt (Umschreibung) | D14: 0.005 | F14: üblich ca. 0,5 % | H14: Makler | I14: =Makler_Betrag -> 10174.5
C15: Maklerprovision (inkl. USt) | D15: 0.0357 | F15: z. B. 3,57 % (3 % zzgl. 19 % USt) | H15: Sonstige | I15: =NK_Sonst -> 500
C16: Sonstige Erwerbsnebenkosten | D16: 500 | F16: Gutachten, Fahrten – sofern objektbezogen | H16: = Summe Kaufnebenkosten | I16: =NK_Summe -> 30224.5
H17: Kaufnebenkostenquote | I17: =NK_Quote -> 0.10605088
C18: ZUSAMMENSETZUNG DER KAUFNEBENKOSTEN | F18: Anteile in % | H18: = Anschaffungskosten gesamt | I18: =AK_Gesamt -> 315224.5
H20: Steuerliche Behandlung
H21: Kaufnebenkosten sind Anschaffungsnebenkosten: kein Sofortabzug, sondern Verteilung über die AfA – anteilig nach dem Gebäudeanteil (Schritt 4). Gesondert ausgewiesene bewegliche Gegenstände mindern die Bemessungsgrundlage der Grunderwerbsteuer.
H23: KAUFNEBENKOSTEN GESAMT
H24: =NK_Summe -> 30224.5
H25: =IFERROR("je m² Wohnfläche: "&FIXED(NK_Summe/Wohnflaeche,0)&" €","") -> je m² Wohnfläche: 403 €
H27: ALS NÄCHSTES | I27: Schritt 04 / 12
H28: Kaufpreisaufteilung · Nur der Gebäudeanteil ist abschreibbar – die Aufteilung zwischen Grund und Boden und Gebäude.
C31: ‹ Zurück: Kaufpreis & Miete | E31: Übersicht: Leitfaden | H31: Weiter: Kaufpreisaufteilung ›
C33: Keine Gewähr für die Richtigkeit der Angaben · ersetzt keine Rechts-, Steuer- oder Finanzberatung · Rechtsstand September 2026
C34: MM Holding GmbH · Kornhausgasse 4 · 88250 Weingarten · Amtsgericht Ulm HRB 750729
C60: DIAGRAMMDATEN (AUTOMATISCH)
C61: Grunderwerbsteuer | D61: =GrESt_Betrag -> 13850
C62: Notar | D62: =Notar_Betrag -> 4275
C63: Grundbuch | D63: =Grundbuch_Betrag -> 1425
C64: Makler | D64: =Makler_Betrag -> 10174.5
C65: Sonstige | D65: =NK_Sonst -> 500

Sheet S04 Kaufpreisaufteilung
C5: SCHRITT 04 / 12 · KAUFPREISAUFTEILUNG | I5: ‹ Leitfaden
C6: Kaufpreisaufteilung | H6: =Obj_Name -> Beispiel: 3-Zimmer-Eigentumswohnung
C7: Nur der Gebäudeanteil ist abschreibbar – die Aufteilung zwischen Grund und Boden und Gebäude. | H7: =Obj_Adresse&IFERROR(IF(Erstellt_fuer="",""," · Erstellt für "&Erstellt_fuer),"") -> Musterstraße 1, 88250 Weingarten · Erstellt für Max Mustermann
C10: Eingaben | H10: Ergebnis dieses Schritts | I10: beim Kauf
C11: POSITION | D11: EINGABE | E11: EINHEIT | F11: HINWEIS | H11: Kaufpreis ohne Inventar/Rücklage | I11: =KP_Immobilie -> 274000
C12: Methode der Kaufpreisaufteilung | D12: Bodenrichtwert × Grundstücks-/Miteigentumsanteil | F12: Standard: BMF-Arbeitshilfe · Gutachten möglich | H12: Bodenwert (nicht abschreibbar) | I12: =Bodenwert -> 54000
C13: Bodenrichtwert | D13: 450 | E13: je m² | F13: lt. Gutachterausschuss / BORIS (Methode 1) | H13: Gebäudeanteil am Kaufpreis | I13: =Gebaeudeanteil_Pct -> 0.80291971
C14: Bodenanteil in % des Kaufpreises | D14: 0.2 | F14: nur Methode „Bodenanteil in %“ | H14: AK Grund und Boden (inkl. NK) | I14: =AK_Boden -> 59956.653
C15: Gebäudewert (Gutachten / Vertrag) | F15: nur Methode „Gebäudewert“ (ohne Inventar) | H15: = AfA-Basis Gebäude (inkl. NK) | I15: =AK_Gebaeude -> 244267.85
H16: nachrichtlich: bewegliche Gegenstände | I16: =KP_bewegl -> 8000
C17: AUFTEILUNG DES KAUFPREISES | F17: inkl. Inventar und Rücklage · Anteile in %
H18: Gebäudeanteil und AfA
H19: Nur der Gebäudeanteil wird abgeschrieben – ein hoher Bodenanteil senkt die jährliche AfA. Das Finanzamt rechnet mit der BMF-Arbeitshilfe; eine im Kaufvertrag vereinbarte Aufteilung ist maßgeblich, wenn sie den realen Wertverhältnissen entspricht (BFH IX R 26/19). Ein Gutachten ersetzt die Arbeitshilfe.
H21: AfA-BASIS GEBÄUDE
H22: =AK_Gebaeude -> 244267.85
H23: ="Reguläre Gebäude-AfA Jahr 1: "&FIXED(INDEX(Steuern!$D$49:$AQ$49,1),0)&" €" -> Reguläre Gebäude-AfA Jahr 1: 4,885 €
H25: ALS NÄCHSTES | I25: Schritt 05 / 12
H26: Maßnahmen & Reserve · Renovierung, Sonderumlagen und Liquiditätsreserve – inklusive Prüfung der 15 %-Grenze.
C29: ‹ Zurück: Kaufnebenkosten | E29: Übersicht: Leitfaden | H29: Weiter: Maßnahmen & Reserve ›
C31: Keine Gewähr für die Richtigkeit der Angaben · ersetzt keine Rechts-, Steuer- oder Finanzberatung · Rechtsstand September 2026
C32: MM Holding GmbH · Kornhausgasse 4 · 88250 Weingarten · Amtsgericht Ulm HRB 750729

Sheet S05 Maßnahmen & Reserve
C5: SCHRITT 05 / 12 · MASSNAHMEN & RESERVE | I5: ‹ Leitfaden
C6: Maßnahmen & Reserve | H6: =Obj_Name -> Beispiel: 3-Zimmer-Eigentumswohnung
C7: Renovierung, Sonderumlagen und Liquiditätsreserve – inklusive Prüfung der 15 %-Grenze. | H7: =Obj_Adresse&IFERROR(IF(Erstellt_fuer="",""," · Erstellt für "&Erstellt_fuer),"") -> Musterstraße 1, 88250 Weingarten · Erstellt für Max Mustermann
C10: Eingaben | H10: Ergebnis dieses Schritts | I10: Jahre 1–3
C11: POSITION | D11: EINGABE | E11: EINHEIT | F11: HINWEIS | H11: Maßnahmen Jahre 1–3 (netto) | I11: =Reno_Netto -> 10084.034
C12: Renovierung Jahr 1 (brutto) | D12: 12000 | F12: Teil des anfänglichen Kapitalbedarfs | H12: 15 %-Grenze (Gebäude-AK × 15 %) | I12: =Grenze_15 -> 36640.177
C13: Renovierung Jahr 2 (brutto) | D13: 0 | F13: aus laufendem Cashflow / Eigenkapital | H13: Steuerliche Behandlung | I13: =IF(HK_Flag=1,"Aktiviert (AfA)",IF(Verteilung_eff>1,"Verteilt (§ 82b)","Sofortabzug")) -> Sofortabzug
C14: Renovierung Jahr 3 (brutto) | D14: 0 | F14: Jahre 1–3 zählen für die 15 %-Grenze | H14: Maßnahmen + Sonderumlage Jahr 1 | I14: =Investition_J1 -> 12000
C15: Sonderumlagen der WEG (Jahr 1) | D15: 0 | F15: Erhaltungsaufwand · zählt zur 15 %-Grenze | H15: = Gesamtinvestition | I15: =Gesamtinvestition -> 328974.5
C16: Steuerliche Behandlung | D16: Automatisch – 15 %-Grenze prüfen (§ 6 Abs. 1 Nr. 1a EStG) | F16: § 6 Abs. 1 Nr. 1a EStG · über 15 % → AfA | H16: = Eigenkapitalbedarf inkl. Reserve | I16: =EK_Bedarf_gesamt -> 83974.5
C17: Verteilung Erhaltungsaufwand | D17: 1 | F17: § 82b EStDV · 1 = sofort, 2–5 = verteilt (Privat)
C18: Wertsteigernder Anteil | D18: 1 | F18: Anteil der Maßnahmen, der den Objektwert erhöht | H18: Die 15 %-Grenze
C19: Einmalige Liquiditätsreserve | D19: 5000 | F19: z. B. Mieterwechsel · erhöht nur das Eigenkapital | H19: =IF(Reno_Netto>Grenze_15,"Achtung: Die Maßnahmen (netto "&FIXED(Reno_Netto,0)&" €) übersteigen 15 % der Gebäude-Anschaffungskosten ("&FIXED(Grenze_15,0)&" €). Damit liegen anschaffungsnahe Herstellungskosten vor (§ 6 Abs. 1 Nr. 1a EStG): kein Sofortabzug, sondern AfA – auch wenn einzelne Maßnahmen für sich Erhaltungsaufwand wären.","Die Maßnahmen (netto "&FIXED(Reno_Netto,0)&" €) bleiben unter der 15 %-Grenze von "&FIXED(Grenze_15,0)&" € – Sofortabzug als Erhaltungsaufwand ist möglich. Bei hoher Progression kann eine Verteilung auf 2 bis 5 Jahre (§ 82b EStDV) sinnvoll sein. Weitere Instandsetzungen in den ersten drei Jahren zählen mit.") -> Die Maßnahmen (netto 10,084 €) bleiben unter der 15 %-Grenze von 36,640 € – Sofortabzug als Erhaltungsaufwand ist möglich. Bei hoher Progression kann eine Verteilung auf 2 bis 5 Jahre (§ 82b EStDV) sinnvoll sein. Weitere Instandsetzungen in den ersten drei Jahren zählen mit.
C21: ZUSAMMENSETZUNG DER GESAMTINVESTITION | F21: Anteile in %
H23: EIGENKAPITALBEDARF INKL. RESERVE
H24: =EK_Bedarf_gesamt -> 83974.5
H25: =IFERROR("Anteil an der Gesamtinvestition "&FIXED(EK_Bedarf_gesamt/Gesamtinvestition*100,1)&" %","") -> Anteil an der Gesamtinvestition 25.5 %
H27: ALS NÄCHSTES | I27: Schritt 06 / 12
H28: Bewirtschaftung · Hausgeld, Verwaltung, Rücklagen und Mietausfall – was von der Miete monatlich übrig bleibt.
C31: ‹ Zurück: Kaufpreisaufteilung | E31: Übersicht: Leitfaden | H31: Weiter: Bewirtschaftung ›
C33: Keine Gewähr für die Richtigkeit der Angaben · ersetzt keine Rechts-, Steuer- oder Finanzberatung · Rechtsstand September 2026
C34: MM Holding GmbH · Kornhausgasse 4 · 88250 Weingarten · Amtsgericht Ulm HRB 750729

Sheet S06 Bewirtschaftung
C5: SCHRITT 06 / 12 · BEWIRTSCHAFTUNG | I5: ‹ Leitfaden
C6: Bewirtschaftung | H6: =Obj_Name -> Beispiel: 3-Zimmer-Eigentumswohnung
C7: Hausgeld, Verwaltung, Rücklagen und Mietausfall – was von der Miete monatlich übrig bleibt. | H7: =Obj_Adresse&IFERROR(IF(Erstellt_fuer="",""," · Erstellt für "&Erstellt_fuer),"") -> Musterstraße 1, 88250 Weingarten · Erstellt für Max Mustermann
C10: Eingaben | H10: Ergebnis dieses Schritts | I10: Jahr 1 · pro Monat
C11: POSITION | D11: EINGABE | E11: EINHEIT | F11: HINWEIS | H11: Nettokaltmiete Ist (nach Ausfall) | I11: =INDEX(Projektion!$D$15:$AQ$15,1)/12 -> 921.5
C12: Hausgeld gesamt (WEG) | D12: 310 | E12: pro Monat | F12: lt. Wirtschaftsplan | H12: – Bewirtschaftung inkl. Rücklagen | I12: =INDEX(Projektion!$D$26:$AQ$26,1)/12 -> 207.5
C13: davon nicht umlagefähig | D13: 95 | E13: pro Monat | F13: Verwaltung WEG, Rücklage, Sonstiges – trägt der Eigentümer | H13: in % der Nettokaltmiete | I13: =IF(INDEX(Projektion!$D$15:$AQ$15,1)>0,INDEX(Projektion!$D$26:$AQ$26,1)/INDEX(Projektion!$D$15:$AQ$15,1),0) -> 0.22517634
C14: davon Erhaltungsrücklage | D14: 60 | E14: pro Monat | F14: Teil von „nicht umlagefähig“ · Abzug erst bei Verausgabung | H14: = Einnahmenüberschuss (NOI) | I14: =INDEX(Projektion!$D$29:$AQ$29,1)/12 -> 714
C15: Miet-/SE-Verwaltung | D15: 25 | E15: pro Monat | F15: Werbungskosten | H15: = Nettomietrendite | I15: =IF(Gesamtinvestition>0,INDEX(Projektion!$D$29:$AQ$29,1)/Gesamtinvestition,0) -> 0.026044572
C16: Eigene Instandhaltungsrücklage | D16: 10 | E16: je m² p. a. | F16: kalkulatorisch, Faustwert 8–15 €/m² · nicht steuerwirksam
C17: Mietausfallwagnis | D17: 0.03 | E17: der Miete | F17: kalkulatorisch 2–4 % | H17: Nettomietrendite | I17: =IF(AND(ISNUMBER(S06_NMR),S06_NMR<Ampel_NMR_gelb),"● kritisch"&" · "&FIXED(S06_NMR*100,1)&" %",IF(AND(ISNUMBER(S06_NMR),S06_NMR<Ampel_NMR_gruen),"● prüfen"&" · "&FIXED(S06_NMR*100,1)&" %",IF(ISNUMBER(S06_NMR),"● erfüllt"&" · "&FIXED(S06_NMR*100,1)&" %",""))) -> ● prüfen · 2.6 %
C18: Leerstand zu Beginn | D18: 0 | F18: Renovierung / Neuvermietung · mindert die Miete Jahr 1 | H18: =IF(S06_NMR<Ampel_NMR_gruen,"Die Nettomietrendite liegt unter dem Ziel von "&FIXED(Ampel_NMR_gruen*100,1)&" %.","Die Nettomietrendite erreicht das Ziel von "&FIXED(Ampel_NMR_gruen*100,1)&" %.")&" "&"Nicht umlagefähige Kosten trägt der Eigentümer. Zuführungen zur WEG-Erhaltungsrücklage und die eigene Instandhaltungsrücklage sind Liquiditätsabflüsse, steuerlich aber erst bei tatsächlicher Verausgab"&"ung abziehbar. Mietausfallwagnis und Leerstand mindern die Ist-Miete." -> Die Nettomietrendite liegt unter dem Ziel von 3.5 %. Nicht umlagefähige Kosten trägt der Eigentümer. Zuführungen zur WEG-Erhaltungsrücklage und die eigene Instandhaltungsrücklage sind Liquiditätsabflüsse, steuerlich aber erst bei tatsächlicher Verausgabung abziehbar. Mietausfallwagnis und Leerstand mindern die Ist-Miete.
C19: Sonstige Werbungskosten | D19: 300 | E19: pro Jahr | F19: Steuerberatung, Kontoführung, Fahrten
C21: BEWIRTSCHAFTUNGSKOSTEN JAHR 1 | F21: € p. a. · Anteile
H22: EINNAHMENÜBERSCHUSS (NOI) / MONAT
H23: =INDEX(Projektion!$D$29:$AQ$29,1)/12 -> 714
H24: ="Jahr 1 · "&FIXED(INDEX(Projektion!$D$29:$AQ$29,1),0)&" € p. a." -> Jahr 1 · 8,568 € p. a.
H26: ALS NÄCHSTES | I26: Schritt 07 / 12
H27: Finanzierung · Darlehen, Zins, Tilgung und Zinsbindung – Rate, Eigenkapital und Restschuld nach der Zinsbindung.
C30: ‹ Zurück: Maßnahmen & Reserve | E30: Übersicht: Leitfaden | H30: Weiter: Finanzierung ›
C32: Keine Gewähr für die Richtigkeit der Angaben · ersetzt keine Rechts-, Steuer- oder Finanzberatung · Rechtsstand September 2026
C33: MM Holding GmbH · Kornhausgasse 4 · 88250 Weingarten · Amtsgericht Ulm HRB 750729
C60: DIAGRAMMDATEN (AUTOMATISCH)
C61: Hausgeld n. umlagefähig (ohne Rücklage) | D61: =INDEX(Projektion!$D$20:$AQ$20,1) -> 420
C62: Zuführung Erhaltungsrücklage | D62: =INDEX(Projektion!$D$21:$AQ$21,1) -> 720
C63: Verwaltung | D63: =INDEX(Projektion!$D$22:$AQ$22,1) -> 300
C64: Eigene Instandhaltungsrücklage | D64: =INDEX(Projektion!$D$24:$AQ$24,1) -> 750
C65: Mietausfall | D65: =INDEX(Projektion!$D$14:$AQ$14,1) -> 342
C66: Sonstige Werbungskosten | D66: =INDEX(Projektion!$D$23:$AQ$23,1) -> 300

Sheet S07 Finanzierung
C5: SCHRITT 07 / 12 · FINANZIERUNG | I5: ‹ Leitfaden
C6: Finanzierung | H6: =Obj_Name -> Beispiel: 3-Zimmer-Eigentumswohnung
C7: Darlehen, Zins, Tilgung und Zinsbindung – Rate, Eigenkapital und Restschuld nach der Zinsbindung. | H7: =Obj_Adresse&IFERROR(IF(Erstellt_fuer="",""," · Erstellt für "&Erstellt_fuer),"") -> Musterstraße 1, 88250 Weingarten · Erstellt für Max Mustermann
C10: Eingaben | H10: Ergebnis dieses Schritts | I10: Kauf · Rate Jahr 1
C11: POSITION | D11: EINGABE | E11: EINHEIT | F11: HINWEIS | H11: Darlehen gesamt (inkl. Darlehen II) | I11: =Darlehen_Summe -> 250000
C12: Darlehen I – Betrag | D12: 250000 | F12: Bankdarlehen (Annuität) | H12: Finanzierungsnebenkosten | I12: =FinNK_Summe -> 1750
C13: Darlehen I – Sollzins p. a. | D13: 0.036 | H13: = Eigenkapital (ohne Reserve) | I13: =Eigenkapital -> 78974.5
C14: Darlehen I – anfängliche Tilgung p. a. | D14: 0.02 | F14: Annuität = (Zins + Tilgung) × Darlehen, konstant | H14: Eigenkapitalquote | I14: =EK_Quote -> 0.24006268
C15: Darlehen I – Zinsbindung | D15: 10 | H15: Beleihungsauslauf | I15: =Beleihung -> 0.87719298
C16: Darlehen I – Anschlusszins | D16: 0.045 | F16: nach der Zinsbindung · Annahme, die Annuität bleibt | H16: Restschuld nach Zinsbindung | I16: =Restschuld_ZB_I -> 191071.23
C17: Darlehen I – Sondertilgung p. a. | D17: 0 | E17: pro Jahr | H17: Volltilgung | I17: =Volltilgung_Txt -> Jahr 32 (2057)
C18: Darlehen I – tilgungsfreie Jahre | D18: 0 | H18: = Rate an die Bank / Monat | I18: =Kapitaldienst_Monat_J1 -> 1166.6667
C19: Grundschuldbestellung | D19: 0.005 | F19: Notar + Grundbuch, ca. 0,4–0,6 % des Darlehens
C20: Bearbeitungs-/Vermittlungsgebühr | D20: 500 | F20: Bank, Wertermittlung · sofort abziehbar | H20: Kapitaldienstdeckung (DSCR) | I20: =IF(AND(ISNUMBER(DSCR_J1),DSCR_J1<Ampel_DSCR_gelb),"● kritisch"&" · "&FIXED(DSCR_J1,2)&"×",IF(AND(ISNUMBER(DSCR_J1),DSCR_J1<Ampel_DSCR_gruen),"● prüfen"&" · "&FIXED(DSCR_J1,2)&"×",IF(ISNUMBER(DSCR_J1),"● erfüllt"&" · "&FIXED(DSCR_J1,2)&"×",""))) -> ● kritisch · 0.61×
C21: Disagio Darlehen I | D21: 0 | F21: bis 5 % bei ≥ 5 Jahren Zinsbindung sofort abziehbar | H21: =IF(NOT(ISNUMBER(DSCR_J1)),"Ohne Darlehen entfällt die Kapitaldienstdeckung.",IF(DSCR_J1>=Ampel_DSCR_gruen,"Der Einnahmenüberschuss deckt die Rate an die Bank mit Reserve – Banken erwarten mindestens "&FIXED(Ampel_DSCR_gruen,2)&"×.",IF(DSCR_J1>=Ampel_DSCR_gelb,"Knapp: Banken erwarten meist mindestens "&FIXED(Ampel_DSCR_gruen,2)&"× – mehr Eigenkapital oder Sicherheiten einplanen.","Der Einnahmenüberschuss deckt nur "&FIXED(DSCR_J1*100,0)&" % der Rate. Banken erwarten mindestens "&FIXED(Ampel_DSCR_gruen,2)&"× – den Rest tragen Sie aus Ihrem Einkommen."))) -> Der Einnahmenüberschuss deckt nur 61 % der Rate. Banken erwarten mindestens 1.20× – den Rest tragen Sie aus Ihrem Einkommen.
C23: Hinweis Ein zweites Darlehen (z. B. KfW) erfassen Sie auf dem Blatt „Eingaben“. | F23: Darlehen II erfassen ›
H24: Zinsänderungsrisiko
C25: RESTSCHULD AM JAHRESENDE | F25: Jahre 1–35 · T€ · Jahresende | H25: ="Nach "&Zinsbindung_I&" Jahren stehen noch "&FIXED(Restschuld_ZB_I,0)&" € Restschuld. Jeder Prozentpunkt mehr Anschlusszins kostet "&FIXED(Restschuld_ZB_I*0.01,0)&" € pro Jahr ("&FIXED(Restschuld_ZB_I*0.01/12,0)&" € pro Monat). Angenommen sind "&FIXED(Anschlusszins_I*100,2)&" % ab Jahr "&(Zinsbindung_I+1)&". Sondertilgungen und eine höhere Anfangstilgung reduzieren dieses Risiko." -> Nach 10 Jahren stehen noch 191,071 € Restschuld. Jeder Prozentpunkt mehr Anschlusszins kostet 1,911 € pro Jahr (159 € pro Monat). Angenommen sind 4.50 % ab Jahr 11. Sondertilgungen und eine höhere Anfangstilgung reduzieren dieses Risiko.
H28: FINANZIERUNGSSTRUKTUR | I28: Anteile in %
C41: ‹ Zurück: Bewirtschaftung | E41: Übersicht: Leitfaden | H41: Weiter: Zwischenergebnis ›
C43: Keine Gewähr für die Richtigkeit der Angaben · ersetzt keine Rechts-, Steuer- oder Finanzberatung · Rechtsstand September 2026
C44: MM Holding GmbH · Kornhausgasse 4 · 88250 Weingarten · Amtsgericht Ulm HRB 750729

Sheet S08 Zwischenergebnis
C5: SCHRITT 08 / 12 · ZWISCHENERGEBNIS | I5: ‹ Leitfaden
C6: Zwischenergebnis | H6: =Obj_Name -> Beispiel: 3-Zimmer-Eigentumswohnung
C7: Cashflow vor Steuern: Miete abzüglich Bewirtschaftung, Zinsen und Tilgung. | H7: =Obj_Adresse&IFERROR(IF(Erstellt_fuer="",""," · Erstellt für "&Erstellt_fuer),"") -> Musterstraße 1, 88250 Weingarten · Erstellt für Max Mustermann
C10: Cashflow vor Steuern – Jahr 1 | H10: Cashflow vor Steuern | I10: =IF(CF_vSt_J1<0,"● kritisch"&" · "&IF(CF_vSt_J1<0,"−","")&FIXED(ABS(CF_vSt_J1/12),0)&" €",IF(ISNUMBER(CF_vSt_J1),"● erfüllt"&" · "&IF(CF_vSt_J1<0,"−","")&FIXED(ABS(CF_vSt_J1/12),0)&" €","")) -> ● kritisch · −453 €
C11: NETTOKALTMIETE IST / MONAT | E11: EINNAHMENÜBERSCHUSS (NOI) / MONAT | H11: =IF(CF_vSt_J1>=0,"Die Miete deckt Bewirtschaftung, Zinsen und Tilgung: Es bleiben "&FIXED(CF_vSt_J1/12,0)&" € pro Monat vor Steuern für Rücklagen oder Sondertilgungen.","Es fehlen "&FIXED(-CF_vSt_J1/12,0)&" € pro Monat, die aus anderen Einkünften zugeschossen werden. Ob sich das Objekt trotzdem lohnt, zeigen Steuereffekt (Schritte 9–10) und Wertentwicklung (Schritt 11).") -> Es fehlen 453 € pro Monat, die aus anderen Einkünften zugeschossen werden. Ob sich das Objekt trotzdem lohnt, zeigen Steuereffekt (Schritte 9–10) und Wertentwicklung (Schritt 11).
C12: =INDEX(Projektion!$D$15:$AQ$15,1)/12 -> 921.5 | E12: =INDEX(Projektion!$D$29:$AQ$29,1)/12 -> 714
C13: nach Mietausfall und Leerstand | E13: Miete abzüglich Bewirtschaftung
C14: RATE AN DIE BANK / MONAT | E14: CASHFLOW V. ST. / MONAT (JAHR 1) | H14: Kapitaldienstdeckung (DSCR) | I14: =IF(AND(ISNUMBER(DSCR_J1),DSCR_J1<Ampel_DSCR_gelb),"● kritisch"&" · "&FIXED(DSCR_J1,2)&"×",IF(AND(ISNUMBER(DSCR_J1),DSCR_J1<Ampel_DSCR_gruen),"● prüfen"&" · "&FIXED(DSCR_J1,2)&"×",IF(ISNUMBER(DSCR_J1),"● erfüllt"&" · "&FIXED(DSCR_J1,2)&"×",""))) -> ● kritisch · 0.61×
C15: =Kapitaldienst_Monat_J1 -> 1166.6667 | E15: =CF_vSt_J1/12 -> -452.66667 | H15: ="Banken erwarten meist eine Kapitaldienstdeckung von mindestens "&FIXED(Ampel_DSCR_gruen,2)&"× (Einnahmenüberschuss ÷ Rate). Darunter trägt der Investor einen Teil der Rate aus seinem Einkommen." -> Banken erwarten meist eine Kapitaldienstdeckung von mindestens 1.20× (Einnahmenüberschuss ÷ Rate). Darunter trägt der Investor einen Teil der Rate aus seinem Einkommen.
C16: Zinsen und Tilgung · Jahr 1 | E16: Ziel ≥ 0 € · nach Rate, vor Steuern | F16: =IF($E$15<0,"● kritisch",IF(ISNUMBER($E$15),"● erfüllt","")) -> ● kritisch
C17: HERLEITUNG PRO MONAT | D17: Jahr 1 | E17: EINNAHMEN VS. AUSGABEN | F17: € / Monat · vor Steuern | H17: STELLSCHRAUBEN | I17: Cashflow verbessern
C18: Nettokaltmiete Ist | D18: =INDEX(Projektion!$D$15:$AQ$15,1)/12 -> 921.5 | H18: Kaufpreis & Miete – Miete und Kaufpreis ›
C19: – Bewirtschaftung inkl. Rücklagen | D19: =INDEX(Projektion!$D$26:$AQ$26,1)/12 -> 207.5 | H19: Bewirtschaftung – nicht umlagefähige Kosten ›
C20: – Zinsen | D20: =INDEX(Projektion!$D$30:$AQ$30,1)/12 -> 750 | H20: Finanzierung – Eigenkapital, Zins und Tilgung ›
C21: – Tilgung | D21: =INDEX(Projektion!$D$31:$AQ$31,1)/12 -> 416.66667 | H21: Steuern – Rechtsform und Steuersatz ›
C22: = Cashflow vor Steuern / Monat | D22: =INDEX(Projektion!$D$33:$AQ$33,1)/12 -> -452.66667 | H22: Sensitivität – Break-even-Miete und Zinsänderung ›
C23: Kapitaldienstdeckung (DSCR) | D23: =DSCR_J1 -> 0.612 | H23: Cockpit – alle Kennzahlen im Detail ›
C26: ‹ Zurück: Finanzierung | E26: Übersicht: Leitfaden | H26: Weiter: Steuern ›
C28: Keine Gewähr für die Richtigkeit der Angaben · ersetzt keine Rechts-, Steuer- oder Finanzberatung · Rechtsstand September 2026
C29: MM Holding GmbH · Kornhausgasse 4 · 88250 Weingarten · Amtsgericht Ulm HRB 750729

Sheet S09 Steuern
C5: SCHRITT 09 / 12 · STEUERN | I5: ‹ Leitfaden
C6: Steuern | H6: =Obj_Name -> Beispiel: 3-Zimmer-Eigentumswohnung
C7: Rechtsform (Privat oder GmbH), Einkommen, Soli und Kirchensteuer – der angewendete Steuersatz. | H7: =Obj_Adresse&IFERROR(IF(Erstellt_fuer="",""," · Erstellt für "&Erstellt_fuer),"") -> Musterstraße 1, 88250 Weingarten · Erstellt für Max Mustermann
C10: Eingaben | H10: Ergebnis dieses Schritts | I10: Jahr 1
C11: POSITION | D11: EINGABE | E11: EINHEIT | F11: HINWEIS | H11: Grenzsteuersatz lt. Tarif 2026 | I11: =Grenzsteuersatz_Tarif -> 0.42
C12: Rechtsform | D12: =CHOOSE(Rechtsform_Idx,"Privatperson","vv-GmbH","GmbH / Holding") -> Privatperson | F12: Kauf als auf der Startseite ändern › | H12: Grenzbelastung inkl. Soli / KiSt | I12: =Steuersatz_Privat -> 0.462588
C13: Veranlagung | D13: Einzelveranlagung (Grundtarif) | F13: nur Privatperson | H13: Steuersatz GmbH Jahr 1 | I13: =Steuersatz_GmbH_J1 -> 0.15825
C14: Einkommen ohne dieses Objekt (zvE) | D14: 75000 | E14: pro Jahr | F14: nur Privatperson · Basis für den Grenzsteuersatz | H14: = Angewendeter Steuersatz Jahr 1 | I14: =Steuersatz_J1 -> 0.462588
C15: Grenzsteuersatz manuell | F15: nur Privat · optional, leer = nach Tarif 2026 | H15: Steuerliches Ergebnis Jahr 1 | I15: =Ergebnis_J1 -> -18397.357
C16: Solidaritätszuschlag | D16: Ja | F16: nur Privat · „Nein“ bei ESt unter der Freigrenze | H16: = Steuerwirkung Jahr 1 | I16: =INDEX(Steuern!$D$73:$AQ$73,1) -> -8510.3965
C17: Kirchensteuer | D17: 8 % (Baden-Württemberg, Bayern) | F17: nur Privat · Sonderausgabenabzug berücksichtigt
C18: Gewerbesteuer-Hebesatz | D18: 4 | F18: nur GmbH ohne erweiterte Kürzung · z. B. 400 % | H18: Besteuerung nach Rechtsform
H19: =IF(Rechtsform_Idx=1,"Privatperson: Das steuerliche Ergebnis (Miete abzüglich Werbungskosten, Zinsen und AfA) wird mit dem Grenzsteuersatz belastet – ein Verlust im Jahr 1 mindert die übrige Einkommensteuer (Erstattung). Nach zehn Jahren ist der Verkauf steuerfrei (§ 23 EStG).",IF(Rechtsform_Idx=2,"Vermögensverwaltende GmbH: Körperschaftsteuer 15 % (ab 2028 jährlich sinkend auf 10 % ab 2032) zuzüglich Soli; mit erweiterter Kürzung keine Gewerbesteuer auf Mieterträge. Verluste werden vorgetragen, der Verkauf ist immer steuerpflichtig. Ausschüttungen an Gesellschafter werden zusätzlich besteuert.","Gewerbliche GmbH: Körperschaftsteuer zuzüglich Soli und Gewerbesteuer ("&FIXED(GewSt_Satz*100,2)&" % bei Hebesatz "&FIXED(Hebesatz*100,0)&" %). Verluste werden vorgetragen; der Verkauf ist immer steuerpflichtig.")) -> Privatperson: Das steuerliche Ergebnis (Miete abzüglich Werbungskosten, Zinsen und AfA) wird mit dem Grenzsteuersatz belastet – ein Verlust im Jahr 1 mindert die übrige Einkommensteuer (Erstattung). Nach zehn Jahren ist der Verkauf steuerfrei (§ 23 EStG).
C20: STEUERLICHES ERGEBNIS UND STEUER | F20: Jahre 1–20 · T€ · Steuer: + Zahlung / − Erstattung
H23: STEUERWIRKUNG / MONAT (JAHR 1)
H24: =Steuer_J1/12 -> -709.19971
H25: =IF(Steuer_J1<0,"Erstattung","Zahlung")&" · Cash-Sicht wie Schritt 12" -> Erstattung · Cash-Sicht wie Schritt 12
H27: ALS NÄCHSTES | I27: Schritt 10 / 12
H28: Abschreibung · AfA-Methode, Sonder-AfA § 7b und erhöhte Absetzungen § 7h/7i – die steuerliche Hebelwirkung.
C31: ‹ Zurück: Zwischenergebnis | E31: Übersicht: Leitfaden | H31: Weiter: Abschreibung ›
C33: Keine Gewähr für die Richtigkeit der Angaben · ersetzt keine Rechts-, Steuer- oder Finanzberatung · Rechtsstand September 2026
C34: MM Holding GmbH · Kornhausgasse 4 · 88250 Weingarten · Amtsgericht Ulm HRB 750729

Sheet S10 Abschreibung
C5: SCHRITT 10 / 12 · ABSCHREIBUNG | I5: ‹ Leitfaden
C6: Abschreibung | H6: =Obj_Name -> Beispiel: 3-Zimmer-Eigentumswohnung
C7: AfA-Methode, Sonder-AfA § 7b und erhöhte Absetzungen § 7h/7i – die steuerliche Hebelwirkung. | H7: =Obj_Adresse&IFERROR(IF(Erstellt_fuer="",""," · Erstellt für "&Erstellt_fuer),"") -> Musterstraße 1, 88250 Weingarten · Erstellt für Max Mustermann
C10: Eingaben | H10: Ergebnis dieses Schritts | I10: Jahr 1
C11: POSITION | D11: EINGABE | E11: EINHEIT | F11: HINWEIS | H11: Angewendete AfA-Methode | I11: =IF(Methode_eff=5,"Degressiv 5 %",IF(Methode_eff=6,"Gutachten (RND)","Linear "&FIXED(CHOOSE(Methode_eff,AfA_Satz_auto,0.02,0.025,0.03)*100,1)&" %")) -> Linear 2.0 %
C12: AfA-Methode Gebäude | D12: Automatisch nach Baujahr (§ 7 Abs. 4 EStG) | F12: degressiv nur bei Baubeginn 10/2023 – 09/2029 | H12: Reguläre Gebäude-AfA | I12: =INDEX(Steuern!$D$49:$AQ$49,1) -> 4885.3569
C13: Restnutzungsdauer lt. Gutachten | D13: 0 | F13: nur Methode Gutachten · kürzere Restnutzungsdauer | H13: + Sonder-AfA § 7b | I13: =INDEX(Steuern!$D$50:$AQ$50,1) -> 0
C14: Degressiv: Wechsel zur linearen AfA | D14: Ja | F14: nur degressive AfA · Wechsel, sobald vorteilhaft | H14: + Erhöhte Absetzungen § 7h/7i | I14: =INDEX(Steuern!$D$54:$AQ$54,1) -> 0
C15: Sonder-AfA § 7b (Neubau) | D15: Nein | F15: 5 % p. a. für 4 Jahre · EH 40 + QNG, Baukostengrenze | H15: + AfA bewegliche Gegenstände | I15: =INDEX(Steuern!$D$55:$AQ$55,1) -> 800
C16: Erhöhte AfA § 7h / § 7i EStG | D16: Nein | F16: Sanierungsgebiet / Denkmal: 9 % (J. 1–8), 7 % (J. 9–12) | H16: = Abschreibungen gesamt Jahr 1 | I16: =INDEX(Steuern!$D$56:$AQ$56,1) -> 5685.3569
C17: Begünstigte Kosten § 7h / 7i | D17: 0 | F17: im Kaufpreis enthalten · lt. Bescheinigung | H17: Steuereffekt ggü. Standard-AfA (10 J.) | I17: =Steuereffekt_10J -> 0
C19: ABSCHREIBUNGEN NACH KOMPONENTEN | F19: Jahre 1–20 · T€ p. a. | H19: Wahl der Abschreibung
H20: =IF(AND(AfA_Idx=5,Methode_eff<>5),"Die degressive AfA ist für dieses Objekt nicht anwendbar (Fertigstellung vor 2023 oder Gewerbeeinheit) – es wird linear nach Baujahr abgeschrieben.",IF(AND(SonderAfA_7b="Ja",SonderAfA_aktiv=0),"Die Sonder-AfA § 7b greift nicht: Fertigstellung vor 2023, Gewerbeeinheit oder Anschaffungskosten über "&FIXED(Grenze_7b_Baukosten,0)&" €/m² (aktuell "&FIXED(Baukosten_qm,0)&" €/m²).",IF(SonderAfA_aktiv=1,"Sonder-AfA § 7b aktiv: 5 % p. a. auf "&FIXED(SonderAfA_BMG,0)&" € in den Jahren 1–4 zusätzlich zur regulären AfA; ab Jahr 5 Restwert-AfA. Voraussetzung: Effizienzhaus 40 mit QNG-Siegel.","Eine höhere AfA in den ersten Jahren ist ein Liquiditäts- und Zinsvorteil (Steuerstundung): Bei einem Verkauf innerhalb der Zehnjahresfrist (Privat) oder in der GmbH erhöht die kumulierte AfA den steuerpflichtigen Veräußerungsgewinn. Den vollständigen Variantenvergleich zeigt das Blatt „AfA-Vergleich“."))) -> Eine höhere AfA in den ersten Jahren ist ein Liquiditäts- und Zinsvorteil (Steuerstundung): Bei einem Verkauf innerhalb der Zehnjahresfrist (Privat) oder in der GmbH erhöht die kumulierte AfA den steuerpflichtigen Veräußerungsgewinn. Den vollständigen Variantenvergleich zeigt das Blatt „AfA-Vergleich“.
H22: ABSCHREIBUNGEN / MONAT (JAHR 1)
H23: =INDEX(Steuern!$D$56:$AQ$56,1)/12 -> 473.77974
H24: ="Jahr 1 gesamt: "&FIXED(INDEX(Steuern!$D$56:$AQ$56,1),0)&" € p. a." -> Jahr 1 gesamt: 5,685 € p. a.
H26: ALS NÄCHSTES | I26: Schritt 11 / 12
H27: Prognose & Exit · Miet-, Kosten- und Wertsteigerung, Haltedauer und Verkauf – inklusive 10-Jahres-Frist.
C30: ‹ Zurück: Steuern | E30: Übersicht: Leitfaden | H30: Weiter: Prognose & Exit ›
C32: Keine Gewähr für die Richtigkeit der Angaben · ersetzt keine Rechts-, Steuer- oder Finanzberatung · Rechtsstand September 2026
C33: MM Holding GmbH · Kornhausgasse 4 · 88250 Weingarten · Amtsgericht Ulm HRB 750729

Sheet S11 Prognose & Exit
C5: SCHRITT 11 / 12 · PROGNOSE & EXIT | I5: ‹ Leitfaden
C6: Prognose & Exit | H6: =Obj_Name -> Beispiel: 3-Zimmer-Eigentumswohnung
C7: Miet-, Kosten- und Wertsteigerung, Haltedauer und Verkauf – inklusive 10-Jahres-Frist. | H7: =Obj_Adresse&IFERROR(IF(Erstellt_fuer="",""," · Erstellt für "&Erstellt_fuer),"") -> Musterstraße 1, 88250 Weingarten · Erstellt für Max Mustermann
C10: Eingaben | H10: Ergebnis dieses Schritts | I10: Verkauf
C11: POSITION | D11: EINGABE | E11: EINHEIT | F11: HINWEIS | H11: Verkaufspreis bei Exit | I11: =Exit_VP -> 376667.81
C12: Mietsteigerung p. a. | D12: 0.02 | F12: Prognose · Mietpreisbremse und Kappungsgrenze | H12: Veräußerungsgewinn (steuerlich) | I12: =Exit_Gewinn -> 120534.24
C13: Kostensteigerung p. a. | D13: 0.02 | F13: Prognose | H13: Verkauf steuerpflichtig? | I13: =IF(Exit_steuerpflichtig=1,"Ja","Nein") -> Nein
C14: Wertsteigerung p. a. | D14: 0.02 | F14: Prognose; konservativ 0–2 % | H14: Steuer auf den Veräußerungsgewinn | I14: =Exit_Steuer -> 0
C15: Geplante Haltedauer | D15: 12 | F15: Privat: Verkauf nach über 10 Jahren steuerfrei | H15: = Nettoerlös nach Steuer und Ablösung | I15: =Exit_Netto -> 189109.9
C16: Verkaufskosten | D16: 0.02 | F16: vom Verkaufspreis · Makler, Notar, Löschung | H16: Gesamtertrag nach Steuern | I16: =Gesamtertrag -> 77296.866
C17: Verkaufspreis manuell | F17: optional · leer = Wertentwicklung lt. Prognose | H17: = IRR n. St. (Eigenkapitalrendite) | I17: =EK_IRR -> 0.053273956
C18: Verlustverrechnung | D18: Sofortige Verrechnung mit anderen Einkünften (Standard Privatperson) | F18: GmbH: immer Verlustvortrag (§ 10d EStG)
H19: Verkauf und Steuern
C20: IMMOBILIENWERT, RESTSCHULD UND NETTOVERMÖGEN | F20: Jahre 1–35 · T€ · Jahresende | H20: =IF(AND(Rechtsform_Idx=1,Haltedauer<=Frist_23),"Verkauf innerhalb der Zehnjahresfrist: Der Veräußerungsgewinn von "&FIXED(Exit_Gewinn,0)&" € ist steuerpflichtig (§ 23 EStG) – die bis dahin genutzte AfA wird über den Buchwert nachversteuert. Eine Haltedauer von mehr als zehn Jahren stellt den Gewinn steuerfrei.",IF(Rechtsform_Idx=1,"Verkauf nach mehr als zehn Jahren: Der Veräußerungsgewinn bleibt im Privatvermögen steuerfrei (§ 23 EStG). Prognosewerte für Miete, Kosten und Wert sind Annahmen – konservative Sätze schützen vor Fehlentscheidungen.","In der GmbH ist der Verkauf unabhängig von der Haltedauer steuerpflichtig; ein Verlustvortrag wird gegengerechnet. Ausschüttungen an die Gesellschafter lösen zusätzlich Abgeltungsteuer bzw. Teileinkünfteverfahren aus.")) -> Verkauf nach mehr als zehn Jahren: Der Veräußerungsgewinn bleibt im Privatvermögen steuerfrei (§ 23 EStG). Prognosewerte für Miete, Kosten und Wert sind Annahmen – konservative Sätze schützen vor Fehlentscheidungen.
H23: =UPPER("IRR n. St. ("&Haltedauer&" J.)") -> IRR N. ST. (12 J.)
H24: =EK_IRR -> 0.053273956
H25: ="Ziel ≥ "&FIXED(Ampel_IRR_gruen*100,1)&" %" -> Ziel ≥ 6.0 % | I25: =IF(AND(ISNUMBER($H$24),$H$24<Ampel_IRR_gelb),"● kritisch",IF(AND(ISNUMBER($H$24),$H$24<Ampel_IRR_gruen),"● prüfen",IF(ISNUMBER($H$24),"● erfüllt",""))) -> ● prüfen
H27: ALS NÄCHSTES | I27: Schritt 12 / 12
H28: Ergebnis · Cashflow nach Steuern, Eigenkapitalrendite, Vermögensaufbau und Zusatzrente nach Volltilgung.
C31: ‹ Zurück: Abschreibung | E31: Übersicht: Leitfaden | H31: Weiter: Ergebnis ›
C33: Keine Gewähr für die Richtigkeit der Angaben · ersetzt keine Rechts-, Steuer- oder Finanzberatung · Rechtsstand September 2026
C34: MM Holding GmbH · Kornhausgasse 4 · 88250 Weingarten · Amtsgericht Ulm HRB 750729

Sheet S12 Ergebnis
C5: SCHRITT 12 / 12 · ERGEBNIS | I5: ‹ Leitfaden
C6: Ergebnis | H6: =Obj_Name -> Beispiel: 3-Zimmer-Eigentumswohnung
C7: Cashflow nach Steuern, Eigenkapitalrendite, Vermögensaufbau und Zusatzrente nach Volltilgung. | H7: =Obj_Adresse&IFERROR(IF(Erstellt_fuer="",""," · Erstellt für "&Erstellt_fuer),"") -> Musterstraße 1, 88250 Weingarten · Erstellt für Max Mustermann
C10: Ergebnis der Kalkulation | H10: IRR n. St. (Eigenkapitalrendite) | I10: =IF(AND(ISNUMBER(EK_IRR),EK_IRR<Ampel_IRR_gelb),"● kritisch"&" · "&FIXED(EK_IRR*100,1)&" %",IF(AND(ISNUMBER(EK_IRR),EK_IRR<Ampel_IRR_gruen),"● prüfen"&" · "&FIXED(EK_IRR*100,1)&" %",IF(ISNUMBER(EK_IRR),"● erfüllt"&" · "&FIXED(EK_IRR*100,1)&" %",""))) -> ● prüfen · 5.3 %
C11: CASHFLOW N. ST. / MONAT (JAHR 1) | E11: STEUERWIRKUNG / MONAT (JAHR 1) | H11: =IFERROR(IF(EK_IRR>=Ampel_IRR_gruen,"Über "&Haltedauer&" Jahre verzinst sich das Eigenkapital mit "&FIXED(EK_IRR*100,1)&" % p. a. nach Steuern – das Ziel von "&FIXED(Ampel_IRR_gruen*100,1)&" % ist erreicht.",IF(EK_IRR>=Ampel_IRR_gelb,"Über "&Haltedauer&" Jahre verzinst sich das Eigenkapital mit "&FIXED(EK_IRR*100,1)&" % p. a. nach Steuern – solide, aber unter dem Ziel von "&FIXED(Ampel_IRR_gruen*100,1)&" %. Hebel: Kaufpreis, Miete, Finanzierung und Haltedauer.","Über "&Haltedauer&" Jahre verzinst sich das Eigenkapital nur mit "&FIXED(EK_IRR*100,1)&" % p. a. nach Steuern – unter der Mindestschwelle von "&FIXED(Ampel_IRR_gelb*100,1)&" %. Kaufpreis, Miete und Finanzierung prüfen.")),"Die Eigenkapitalrendite lässt sich mit diesen Annahmen nicht berechnen.") -> Über 12 Jahre verzinst sich das Eigenkapital mit 5.3 % p. a. nach Steuern – solide, aber unter dem Ziel von 6.0 %. Hebel: Kaufpreis, Miete, Finanzierung und Haltedauer.
C12: =CF_nSt_Monat_J1 -> 256.53305 | E12: =Steuer_J1/12 -> -709.19971
C13: ="ab Jahr 2: "&IF(INDEX(Projektion!$D$37:$AQ$37,2)<0,"−","")&FIXED(ABS(INDEX(Projektion!$D$37:$AQ$37,2)),0)&" €" -> ab Jahr 2: −274 € | D13: =IF($C$12<0,"● kritisch",IF(INDEX(Projektion!$D$37:$AQ$37,2)<0,"● prüfen",IF(ISNUMBER($C$12),"● erfüllt",""))) -> ● prüfen | E13: =IF(Steuer_J1<0,"Erstattung","Zahlung")&" · Cash-Sicht · Steuersatz "&FIXED(Steuersatz_J1*100,2)&" %" -> Erstattung · Cash-Sicht · Steuersatz 46.26 %
C14: EK-RENDITE JAHR 1 | E14: =UPPER("IRR n. St. ("&Haltedauer&" J.)") -> IRR N. ST. (12 J.) | H14: Cashflow nach Steuern
C15: =INDEX(Projektion!$D$45:$AQ$45,1) -> 0.17750535 | E15: =EK_IRR -> 0.053273956 | H15: =IF(CF_nSt_J1>=0,"Nach Steuern bleibt im ersten Jahr ein Überschuss von "&FIXED(CF_nSt_J1/12,0)&" € pro Monat.","Nach Steuern fehlen im ersten Jahr "&FIXED(-CF_nSt_J1/12,0)&" € pro Monat.")&" Der Wert ergibt sich aus der Miete ("&FIXED(INDEX(Projektion!$D$15:$AQ$15,1)/12,0)&" €) abzüglich Rate ("&FIXED(Kapitaldienst_Monat_J1,0)&" €) und Bewirtschaftung ("&FIXED(BWK_J1/12,0)&" €), "&IF(Steuer_J1<0,"zuzüglich Steuererstattung (","abzüglich Steuerzahlung (")&FIXED(ABS(Steuer_J1/12),0)&" €). Über die Tilgung wächst das Nettovermögen jedes Jahr – zusammen mit der Wertentwicklung ergibt sich die Eigenkapitalrendite."&CHAR(10)&CHAR(10)&"Ab "&IF(Darlehen_Summe>0,Volltilgung_Txt,"sofort")&" entfällt die Rate an die Bank – der Cashflow nach Steuern steigt dann auf rund "&FIXED(INDEX(Projektion!$D$37:$AQ$37,MIN(40,IFERROR(MATCH(0,Finanzierung!$D$38:$AQ$38,0),40)+1)),0)&" € pro Monat: die Zusatzrente aus dem Objekt (Prognosewerte)." -> Nach Steuern bleibt im ersten Jahr ein Überschuss von 257 € pro Monat. Der Wert ergibt sich aus der Miete (922 €) abzüglich Rate (1,167 €) und Bewirtschaftung (208 €), zuzüglich Steuererstattung (709 €). Über die Tilgung wächst das Nettovermögen jedes Jahr – zusammen mit der Wertentwicklung ergibt sich die Eigenkapitalrendite. Ab Jahr 32 (2057) entfällt die Rate an die Bank – der Cashflow nach Steuern steigt dann auf rund 805 € pro Monat: die Zusatzrente aus dem Objekt (Prognosewerte).
C16: ="Ziel ≥ "&FIXED(Ampel_EKR_gruen*100,1)&" %"&" · Vermögenszuwachs / Eigenkapital" -> Ziel ≥ 10.0 % · Vermögenszuwachs / Eigenkapital | D16: =IF(AND(ISNUMBER($C$15),$C$15<Ampel_EKR_gelb),"● kritisch",IF(AND(ISNUMBER($C$15),$C$15<Ampel_EKR_gruen),"● prüfen",IF(ISNUMBER($C$15),"● erfüllt",""))) -> ● erfüllt | E16: ="Ziel ≥ "&FIXED(Ampel_IRR_gruen*100,1)&" %"&" · Multiple "&FIXED(EK_Multiple,2)&"×" -> Ziel ≥ 6.0 % · Multiple 1.98× | F16: =IF(AND(ISNUMBER($E$15),$E$15<Ampel_IRR_gelb),"● kritisch",IF(AND(ISNUMBER($E$15),$E$15<Ampel_IRR_gruen),"● prüfen",IF(ISNUMBER($E$15),"● erfüllt",""))) -> ● prüfen
C17: ="NETTOVERMÖGEN NACH "&Haltedauer&" JAHREN" -> NETTOVERMÖGEN NACH 12 JAHREN | E17: ="ZUSATZRENTE / MONAT AB "&IF(Darlehen_Summe>0,UPPER(Volltilgung_Txt),"SOFORT") -> ZUSATZRENTE / MONAT AB JAHR 32 (2057)
C18: =INDEX(Projektion!$D$43:$AQ$43,Haltedauer) -> 196643.25 | E18: =INDEX(Projektion!$D$37:$AQ$37,MIN(40,IFERROR(MATCH(0,Finanzierung!$D$38:$AQ$38,0),40)+1)) -> 804.65546
C19: Immobilienwert abzüglich Restschuld | E19: Cashflow nach Steuern nach Volltilgung (Prognose)
C20: HERLEITUNG PRO MONAT | D20: Jahr 1 | E20: CASHFLOW NACH STEUERN | F20: Jahre 1–30 · T€ p. a. | H20: WEITER ZUR AUSWERTUNG
C21: Cashflow vor Steuern / Monat | D21: =CF_vSt_J1/12 -> -452.66667 | H21: Dashboard – Gesamtbewertung, Ampel, Zeitverlauf ›
C22: ± Steuerwirkung / Monat (+ Erstattung) | D22: =Steuer_J1/12 -> -709.19971 | H22: Cockpit – alle Kennzahlen im Detail ›
C23: = Cashflow nach Steuern / Monat | D23: =CF_nSt_J1/12 -> 256.53305 | H23: Diagramme – Investition, Cashflow, Vermögen ›
C24: Eigenkapitalbedarf inkl. Reserve | D24: =EK_Bedarf_gesamt -> 83974.5 | H24: AfA-Vergleich – Abschreibungsvarianten ›
C25: Gesamtertrag n. St. bis Verkauf | D25: =Gesamtertrag -> 77296.866 | H25: Sensitivität – Break-even und Was-wäre-wenn ›
C26: Eigenkapital-Multiple | D26: =EK_Multiple -> 1.9787573 | H26: Bankgespräch – druckfertige Übersicht ›
C29: ‹ Zurück: Prognose & Exit | E29: Übersicht: Leitfaden | H29: Weiter: Dashboard ›
C31: Keine Gewähr für die Richtigkeit der Angaben · ersetzt keine Rechts-, Steuer- oder Finanzberatung · Rechtsstand September 2026
C32: MM Holding GmbH · Kornhausgasse 4 · 88250 Weingarten · Amtsgericht Ulm HRB 750729

Sheet Dashboard
B5: AUSWERTUNG · GESAMTBEWERTUNG AUF EINER SEITE
B6: Dashboard | K6: =Obj_Name -> Beispiel: 3-Zimmer-Eigentumswohnung
B7: ="Kaufpreis "&FIXED(Kaufpreis,0)&" € · Kauf am "&IFERROR(TEXT(DAY(Kaufdatum),"00")&"."&TEXT(MONTH(Kaufdatum),"00")&"."&YEAR(Kaufdatum),"–")&" · Haltedauer "&Haltedauer&" Jahre · "&Bundesland -> Kaufpreis 285,000 € · Kauf am 01.12.2026 · Haltedauer 12 Jahre · Baden-Württemberg | K7: =Obj_Adresse&IFERROR(IF(Erstellt_fuer="",""," · Erstellt für "&Erstellt_fuer),"") -> Musterstraße 1, 88250 Weingarten · Erstellt für Max Mustermann
B9: ‹ Schritt 12: Ergebnis | E9: Cockpit › | H9: Diagramme › | K9: Sensitivität › | N9: Bankgespräch › | Q9: ="KAUF ALS · "&CHOOSE(Rechtsform_Idx,"Privat","vv-GmbH","GmbH")&" ▾" -> KAUF ALS · Privat ▾
B11: GESAMTBEWERTUNG | E11: =IF(ISNUMBER(SEARCH("kritisch",$B$12)),"● kritisch"&" · "&COUNTIF($H$20:$H$25,"erfüllt")&" von 6 Kennzahlen erfüllt",IF(ISNUMBER(SEARCH("Prüfpunkten",$B$12)),"● prüfen"&" · "&COUNTIF($H$20:$H$25,"erfüllt")&" von 6 Kennzahlen erfüllt",IF($B$12="Solide","● erfüllt"&" · "&COUNTIF($H$20:$H$25,"erfüllt")&" von 6 Kennzahlen erfüllt",""))) -> ● kritisch · 1 von 6 Kennzahlen erfüllt | K11: ="– DSCR (Jahr 1) "&FIXED(DSCR_J1,2)&"×"&IF(DSCR_J1<Ampel_DSCR_gruen," statt mindestens "," bei Ziel ")&FIXED(Ampel_DSCR_gruen,2)&"×"&CHAR(10)&"– IRR n. St. "&FIXED(EK_IRR*100,1)&" % über "&Haltedauer&" Jahre (Ziel "&FIXED(Ampel_IRR_gruen*100,1)&" %)"&CHAR(10)&"– Cashflow n. St. "&FIXED(CF_nSt_Monat_J1,0)&" € / Monat im Jahr 1, ab Jahr 2 "&FIXED(INDEX(Projektion!$D$37:$AQ$37,2),0)&" € / Monat" -> – DSCR (Jahr 1) 0.61× statt mindestens 1.20× – IRR n. St. 5.3 % über 12 Jahre (Ziel 6.0 %) – Cashflow n. St. 257 € / Monat im Jahr 1, ab Jahr 2 -274 € / Monat
B12: =IF(OR($H$23="kritisch",$H$20="kritisch"),"Liquidität kritisch",IF(COUNTIF($H$20:$H$25,"kritisch")>0,"Rendite kritisch",IF(COUNTIF($H$20:$H$25,"prüfen")>0,"Solide mit Prüfpunkten","Solide"))) -> Liquidität kritisch
B14: GESAMTINVESTITION | E14: EIGENKAPITALBEDARF INKL. RESERVE | H14: CASHFLOW N. ST. / MONAT (JAHR 1) | K14: BRUTTOMIETRENDITE | N14: DSCR | Q14: =UPPER("IRR n. St. ("&Haltedauer&" J.)") -> IRR N. ST. (12 J.)
B15: =Gesamtinvestition -> 328974.5 | E15: =EK_Bedarf_gesamt -> 83974.5 | H15: =CF_nSt_Monat_J1 -> 256.53305 | K15: =Bruttomietrendite -> 0.04 | N15: =DSCR_J1 -> 0.612 | Q15: =EK_IRR -> 0.053273956
B16: ="Kaufpreis "&FIXED(Kaufpreis,0)&" € · NK "&FIXED(NK_Quote*100,1)&" %" -> Kaufpreis 285,000 € · NK 10.6 % | E16: ="Quote "&FIXED(EK_Quote*100,1)&" % · Beleihung "&FIXED(Beleihung*100,1)&" %" -> Quote 24.0 % · Beleihung 87.7 % | H16: ="Jahr 2: "&FIXED(INDEX(Projektion!$D$37:$AQ$37,2),0)&" €" -> Jahr 2: -274 € | I16: =IF(CF_nSt_Monat_J1<0,"● kritisch",IF(INDEX(Projektion!$D$37:$AQ$37,2)<0,"● prüfen",IF(ISNUMBER(CF_nSt_Monat_J1),"● erfüllt",""))) -> ● prüfen | K16: ="Faktor "&FIXED(Kaufpreisfaktor,1)&"×" -> Faktor 25.0× | L16: =IF(AND(ISNUMBER(Bruttomietrendite),Bruttomietrendite<Ampel_BMR_gelb),"● kritisch",IF(AND(ISNUMBER(Bruttomietrendite),Bruttomietrendite<Ampel_BMR_gruen),"● prüfen",IF(ISNUMBER(Bruttomietrendite),"● erfüllt",""))) -> ● prüfen | N16: ="Rate "&FIXED(Kapitaldienst_J1/12,0)&" €" -> Rate 1,167 € | O16: =IF(AND(ISNUMBER(DSCR_J1),DSCR_J1<Ampel_DSCR_gelb),"● kritisch",IF(AND(ISNUMBER(DSCR_J1),DSCR_J1<Ampel_DSCR_gruen),"● prüfen",IF(ISNUMBER(DSCR_J1),"● erfüllt",""))) -> ● kritisch | Q16: ="Multiple "&FIXED(EK_Multiple,2)&"×" -> Multiple 1.98× | R16: =IF(AND(ISNUMBER(EK_IRR),EK_IRR<Ampel_IRR_gelb),"● kritisch",IF(AND(ISNUMBER(EK_IRR),EK_IRR<Ampel_IRR_gruen),"● prüfen",IF(ISNUMBER(EK_IRR),"● erfüllt",""))) -> ● prüfen
B18: Kennzahlen-Check | I18: Ist gegen Zielwert | K18: Cashflow Jahr 1 | R18: ■ Zufluss ■ Abfluss ■ Summe · € je Monat
B19: KENNZAHL | E19: IST | F19: ZIEL | H19: STATUS | I19: ERREICHUNG | AK19: Verkaufsmarke (Diagramm Vermögensentwicklung) | AL19: Punkt Nettovermögen im Verkaufsjahr
B20: Cashflow n. St. / Monat | E20: =CF_nSt_Monat_J1 -> 256.53305 | F20: ="≥ 0 €" -> ≥ 0 € | H20: =IF(E20<0,"kritisch",IF(INDEX(Projektion!$D$37:$AQ$37,2)<0,"prüfen","erfüllt")) -> prüfen | I20: =IF(E20>=0,1,0) -> 1 | T20: Miete | U20: =Miete_Ist_J1/12 -> 921.5 | V20: 0 | W20: =V20+U20 -> 921.5 | X20: =IF(MAX(V20,W20)>=0,MAX(MIN(V20,W20),0),0) -> 0 | Y20: =IF(MAX(V20,W20)>=0,0,IF(MAX(V20,W20)+$U$29>=0,MAX(V20,W20),MAX(V20,W20)+$U$29)) -> 0 | Z20: =IF(MAX(V20,W20)>=0,MAX(V20,W20)-MAX(MIN(V20,W20),0),0) -> 921.5 | AA20: =IF(MAX(V20,W20)+$U$29>=0,$U$29,-$U$29) -> 219.86667 | AB20: 0 | AC20: 0 | AD20: 0 | AE20: 0 | AF20: 0 | AG20: 0 | AH20: =IF(MAX(V20,W20)>=0,MIN(MIN(V20,W20),0),MIN(V20,W20)-MAX(V20,W20)) -> 0 | AI20: =IF(U20>=0.5,"+",IF(U20<=-0.5,"−",""))&FIXED(ABS(U20),0) -> +922 | AJ20: =IF(Cockpit!$AB$50="","",IF(LEFT(Cockpit!$AB$50,1)="⚠",0,100)+1) | AK20: =IF(1=Haltedauer,MAX(INDEX(Projektion!$D$41:$AQ$41,1),INDEX(Projektion!$D$43:$AQ$43,1))*1.12,NA()) -> #N/A | AL20: =IF(1=Haltedauer,INDEX(Projektion!$D$43:$AQ$43,1),NA()) -> #N/A
B21: Bruttomietrendite | E21: =Bruttomietrendite -> 0.04 | F21: ="≥ "&FIXED(Ampel_BMR_gruen*100,1)&" %" -> ≥ 5.0 % | H21: =IF(E21>=Ampel_BMR_gruen,"erfüllt",IF(E21>=Ampel_BMR_gelb,"prüfen","kritisch")) -> prüfen | I21: =IF(Ampel_BMR_gruen>0,MIN(MAX(0,E21/Ampel_BMR_gruen),1),IF(E21>=Ampel_BMR_gruen,1,0)) -> 0.8 | T21: Bewirt- schaftung | U21: =-BWK_J1/12 -> -207.5 | V21: =W20 -> 921.5 | W21: =V21+U21 -> 714 | X21: =IF(MAX(V21,W21)>=0,MAX(MIN(V21,W21),0),0) -> 714 | Y21: =IF(MAX(V21,W21)>=0,0,IF(MAX(V21,W21)+$U$29>=0,MAX(V21,W21),MAX(V21,W21)+$U$29)) -> 0 | Z21: =IF(MAX(V21,W21)>=0,MAX(V21,W21)-MAX(MIN(V21,W21),0),0) -> 207.5 | AA21: 0 | AB21: =IF(MAX(V21,W21)+$U$29>=0,$U$29,-$U$29) -> 219.86667 | AC21: 0 | AD21: 0 | AE21: 0 | AF21: 0 | AG21: 0 | AH21: =IF(MAX(V21,W21)>=0,MIN(MIN(V21,W21),0),MIN(V21,W21)-MAX(V21,W21)) -> 0 | AI21: =IF(U21>=0.5,"+",IF(U21<=-0.5,"−",""))&FIXED(ABS(U21),0) -> −208 | AJ21: =IF(Cockpit!$AB$51="","",IF(LEFT(Cockpit!$AB$51,1)="⚠",0,100)+2) | AK21: =IF(2=Haltedauer,MAX(INDEX(Projektion!$D$41:$AQ$41,2),INDEX(Projektion!$D$43:$AQ$43,2))*1.12,NA()) -> #N/A | AL21: =IF(2=Haltedauer,INDEX(Projektion!$D$43:$AQ$43,2),NA()) -> #N/A
B22: Nettomietrendite | E22: =Nettomietrendite -> 0.026044572 | F22: ="≥ "&FIXED(Ampel_NMR_gruen*100,1)&" %" -> ≥ 3.5 % | H22: =IF(E22>=Ampel_NMR_gruen,"erfüllt",IF(E22>=Ampel_NMR_gelb,"prüfen","kritisch")) -> prüfen | I22: =IF(Ampel_NMR_gruen>0,MIN(MAX(0,E22/Ampel_NMR_gruen),1),IF(E22>=Ampel_NMR_gruen,1,0)) -> 0.74413062 | T22: Zinsen | U22: =-Zins_J1/12 -> -750 | V22: =W21 -> 714 | W22: =V22+U22 -> -36 | X22: =IF(MAX(V22,W22)>=0,MAX(MIN(V22,W22),0),0) -> 0 | Y22: =IF(MAX(V22,W22)>=0,0,IF(MAX(V22,W22)+$U$29>=0,MAX(V22,W22),MAX(V22,W22)+$U$29)) -> 0 | Z22: =IF(MAX(V22,W22)>=0,MAX(V22,W22)-MAX(MIN(V22,W22),0),0) -> 714 | AA22: 0 | AB22: 0 | AC22: =IF(MAX(V22,W22)+$U$29>=0,$U$29,-$U$29) -> 219.86667 | AD22: 0 | AE22: 0 | AF22: 0 | AG22: 0 | AH22: =IF(MAX(V22,W22)>=0,MIN(MIN(V22,W22),0),MIN(V22,W22)-MAX(V22,W22)) -> -36 | AI22: =IF(U22>=0.5,"+",IF(U22<=-0.5,"−",""))&FIXED(ABS(U22),0) -> −750 | AJ22: =IF(Cockpit!$AB$52="","",IF(LEFT(Cockpit!$AB$52,1)="⚠",0,100)+3) | AK22: =IF(3=Haltedauer,MAX(INDEX(Projektion!$D$41:$AQ$41,3),INDEX(Projektion!$D$43:$AQ$43,3))*1.12,NA()) -> #N/A | AL22: =IF(3=Haltedauer,INDEX(Projektion!$D$43:$AQ$43,3),NA()) -> #N/A
B23: DSCR | E23: =DSCR_J1 -> 0.612 | F23: ="≥ "&FIXED(Ampel_DSCR_gruen,2)&"×" -> ≥ 1.20× | H23: =IF(E23>=Ampel_DSCR_gruen,"erfüllt",IF(E23>=Ampel_DSCR_gelb,"prüfen","kritisch")) -> kritisch | I23: =IF(Ampel_DSCR_gruen>0,MIN(MAX(0,E23/Ampel_DSCR_gruen),1),IF(E23>=Ampel_DSCR_gruen,1,0)) -> 0.51 | T23: Tilgung | U23: =-Tilgung_J1/12 -> -416.66667 | V23: =W22 -> -36 | W23: =V23+U23 -> -452.66667 | X23: =IF(MAX(V23,W23)>=0,MAX(MIN(V23,W23),0),0) -> 0 | Y23: =IF(MAX(V23,W23)>=0,0,IF(MAX(V23,W23)+$U$29>=0,MAX(V23,W23),MAX(V23,W23)+$U$29)) -> -36 | Z23: =IF(MAX(V23,W23)>=0,MAX(V23,W23)-MAX(MIN(V23,W23),0),0) -> 0 | AA23: 0 | AB23: 0 | AC23: 0 | AD23: =IF(MAX(V23,W23)+$U$29>=0,$U$29,-$U$29) -> 219.86667 | AE23: 0 | AF23: 0 | AG23: 0 | AH23: =IF(MAX(V23,W23)>=0,MIN(MIN(V23,W23),0),MIN(V23,W23)-MAX(V23,W23)) -> -416.66667 | AI23: =IF(U23>=0.5,"+",IF(U23<=-0.5,"−",""))&FIXED(ABS(U23),0) -> −417 | AJ23: =IF(Cockpit!$AB$53="","",IF(LEFT(Cockpit!$AB$53,1)="⚠",0,100)+4) | AK23: =IF(4=Haltedauer,MAX(INDEX(Projektion!$D$41:$AQ$41,4),INDEX(Projektion!$D$43:$AQ$43,4))*1.12,NA()) -> #N/A | AL23: =IF(4=Haltedauer,INDEX(Projektion!$D$43:$AQ$43,4),NA()) -> #N/A
B24: EK-Rendite Jahr 1 | E24: =EKR_Tile -> 0.17750535 | F24: ="≥ "&FIXED(Ampel_EKR_gruen*100,1)&" %" -> ≥ 10.0 % | H24: =IF(E24>=Ampel_EKR_gruen,"erfüllt",IF(E24>=Ampel_EKR_gelb,"prüfen","kritisch")) -> erfüllt | I24: =IF(Ampel_EKR_gruen>0,MIN(MAX(0,E24/Ampel_EKR_gruen),1),IF(E24>=Ampel_EKR_gruen,1,0)) -> 1 | T24: = vor Steuern | U24: =CF_vSt_J1/12 -> -452.66667 | V24: 0 | W24: =V24+U24 -> -452.66667 | X24: =IF(MAX(V24,W24)>=0,MAX(MIN(V24,W24),0),0) -> 0 | Y24: =IF(MAX(V24,W24)>=0,0,IF(MAX(V24,W24)+$U$29>=0,MAX(V24,W24),MAX(V24,W24)+$U$29)) -> 0 | Z24: =IF(MAX(V24,W24)>=0,MAX(V24,W24)-MAX(MIN(V24,W24),0),0) -> 0 | AA24: 0 | AB24: 0 | AC24: 0 | AD24: 0 | AE24: =IF(MAX(V24,W24)+$U$29>=0,$U$29,-$U$29) -> 219.86667 | AF24: 0 | AG24: 0 | AH24: =IF(MAX(V24,W24)>=0,MIN(MIN(V24,W24),0),MIN(V24,W24)-MAX(V24,W24)) -> -452.66667 | AI24: =IF(U24>=0.5,"+",IF(U24<=-0.5,"−",""))&FIXED(ABS(U24),0) -> −453 | AJ24: =IF(Cockpit!$AB$54="","",IF(LEFT(Cockpit!$AB$54,1)="⚠",0,100)+5) | AK24: =IF(5=Haltedauer,MAX(INDEX(Projektion!$D$41:$AQ$41,5),INDEX(Projektion!$D$43:$AQ$43,5))*1.12,NA()) -> #N/A | AL24: =IF(5=Haltedauer,INDEX(Projektion!$D$43:$AQ$43,5),NA()) -> #N/A
B25: ="IRR n. St. ("&Haltedauer&" J.)" -> IRR n. St. (12 J.) | E25: =EK_IRR -> 0.053273956 | F25: ="≥ "&FIXED(Ampel_IRR_gruen*100,1)&" %" -> ≥ 6.0 % | H25: =IF(E25>=Ampel_IRR_gruen,"erfüllt",IF(E25>=Ampel_IRR_gelb,"prüfen","kritisch")) -> prüfen | I25: =IF(Ampel_IRR_gruen>0,MIN(MAX(0,E25/Ampel_IRR_gruen),1),IF(E25>=Ampel_IRR_gruen,1,0)) -> 0.88789927 | T25: Steuer | U25: =-Steuer_J1/12 -> 709.19971 | V25: =W24 -> -452.66667 | W25: =V25+U25 -> 256.53305 | X25: =IF(MAX(V25,W25)>=0,MAX(MIN(V25,W25),0),0) -> 0 | Y25: =IF(MAX(V25,W25)>=0,0,IF(MAX(V25,W25)+$U$29>=0,MAX(V25,W25),MAX(V25,W25)+$U$29)) -> 0 | Z25: =IF(U25<0,0,IF(MAX(V25,W25)>=0,MAX(V25,W25)-MAX(MIN(V25,W25),0),0)) -> 256.53305 | AA25: 0 | AB25: 0 | AC25: 0 | AD25: 0 | AE25: 0 | AF25: =IF(MAX(V25,W25)+$U$29>=0,$U$29,-$U$29) -> 219.86667 | AG25: 0 | AH25: =IF(U25<0,0,IF(MAX(V25,W25)>=0,MIN(MIN(V25,W25),0),MIN(V25,W25)-MAX(V25,W25))) -> -452.66667 | AI25: =IF(U25>=0.5,"+",IF(U25<=-0.5,"−",""))&FIXED(ABS(U25),0) -> +709 | AJ25: =IF(Cockpit!$AB$55="","",IF(LEFT(Cockpit!$AB$55,1)="⚠",0,100)+6) | AK25: =IF(6=Haltedauer,MAX(INDEX(Projektion!$D$41:$AQ$41,6),INDEX(Projektion!$D$43:$AQ$43,6))*1.12,NA()) -> #N/A | AL25: =IF(6=Haltedauer,INDEX(Projektion!$D$43:$AQ$43,6),NA()) -> #N/A
B26: ● erfüllt · ● prüfen · ● kritisch · Balken voll = Ziel erreicht | H26: Schwellen › | T26: = nach Steuern | U26: =CF_nSt_J1/12 -> 256.53305 | V26: 0 | W26: =V26+U26 -> 256.53305 | X26: =IF(MAX(V26,W26)>=0,MAX(MIN(V26,W26),0),0) -> 0 | Y26: =IF(MAX(V26,W26)>=0,0,IF(MAX(V26,W26)+$U$29>=0,MAX(V26,W26),MAX(V26,W26)+$U$29)) -> 0 | Z26: =IF(MAX(V26,W26)>=0,MAX(V26,W26)-MAX(MIN(V26,W26),0),0) -> 256.53305 | AA26: 0 | AB26: 0 | AC26: 0 | AD26: 0 | AE26: 0 | AF26: 0 | AG26: =IF(MAX(V26,W26)+$U$29>=0,$U$29,-$U$29) -> 219.86667 | AH26: =IF(MAX(V26,W26)>=0,MIN(MIN(V26,W26),0),MIN(V26,W26)-MAX(V26,W26)) -> 0 | AI26: =IF(U26>=0.5,"+",IF(U26<=-0.5,"−",""))&FIXED(ABS(U26),0) -> +257 | AJ26: =IF(Cockpit!$AB$56="","",IF(LEFT(Cockpit!$AB$56,1)="⚠",0,100)+7) | AK26: =IF(7=Haltedauer,MAX(INDEX(Projektion!$D$41:$AQ$41,7),INDEX(Projektion!$D$43:$AQ$43,7))*1.12,NA()) -> #N/A | AL26: =IF(7=Haltedauer,INDEX(Projektion!$D$43:$AQ$43,7),NA()) -> #N/A
AJ27: =IF(Cockpit!$AB$57="","",IF(LEFT(Cockpit!$AB$57,1)="⚠",0,100)+8) | AK27: =IF(8=Haltedauer,MAX(INDEX(Projektion!$D$41:$AQ$41,8),INDEX(Projektion!$D$43:$AQ$43,8))*1.12,NA()) -> #N/A | AL27: =IF(8=Haltedauer,INDEX(Projektion!$D$43:$AQ$43,8),NA()) -> #N/A
B28: Vermögensentwicklung | R28: ="Verkauf nach "&Haltedauer&" J. ("&INDEX(Projektion!$D$10:$AQ$10,Haltedauer)&") · T€ · jeweils Jahresende · 40 Jahre" -> Verkauf nach 12 J. (2037) · T€ · jeweils Jahresende · 40 Jahre | AJ28: =IF(Cockpit!$AB$58="","",IF(LEFT(Cockpit!$AB$58,1)="⚠",0,100)+9) | AK28: =IF(9=Haltedauer,MAX(INDEX(Projektion!$D$41:$AQ$41,9),INDEX(Projektion!$D$43:$AQ$43,9))*1.12,NA()) -> #N/A | AL28: =IF(9=Haltedauer,INDEX(Projektion!$D$43:$AQ$43,9),NA()) -> #N/A
U29: =MAX(1,0.16*(MAX($V$20:$W$26,0)-MIN($V$20:$W$26,0))) -> 219.86667 | AJ29: =IF(Cockpit!$AB$59="","",IF(LEFT(Cockpit!$AB$59,1)="⚠",0,100)+10) | AK29: =IF(10=Haltedauer,MAX(INDEX(Projektion!$D$41:$AQ$41,10),INDEX(Projektion!$D$43:$AQ$43,10))*1.12,NA()) -> #N/A | AL29: =IF(10=Haltedauer,INDEX(Projektion!$D$43:$AQ$43,10),NA()) -> #N/A
AJ30: =IF(Cockpit!$AB$60="","",IF(LEFT(Cockpit!$AB$60,1)="⚠",0,100)+11) -> 11 | AK30: =IF(11=Haltedauer,MAX(INDEX(Projektion!$D$41:$AQ$41,11),INDEX(Projektion!$D$43:$AQ$43,11))*1.12,NA()) -> #N/A | AL30: =IF(11=Haltedauer,INDEX(Projektion!$D$43:$AQ$43,11),NA()) -> #N/A
U31: Steuer als Abfluss + | V31: 0 | W31: 0 | X31: 0 | Y31: 0 | Z31: 0 | AA31: =IF(U25<0,IF(MAX(V25,W25)>=0,MAX(V25,W25)-MAX(MIN(V25,W25),0),0),0) -> 0 | AB31: 0 | AJ31: =IF(Cockpit!$AB$61="","",IF(LEFT(Cockpit!$AB$61,1)="⚠",0,100)+12) -> 112 | AK31: =IF(12=Haltedauer,MAX(INDEX(Projektion!$D$41:$AQ$41,12),INDEX(Projektion!$D$43:$AQ$43,12))*1.12,NA()) -> 421867.95 | AL31: =IF(12=Haltedauer,INDEX(Projektion!$D$43:$AQ$43,12),NA()) -> 196643.25
U32: Steuer als Abfluss − | V32: 0 | W32: 0 | X32: 0 | Y32: 0 | Z32: 0 | AA32: =IF(U25<0,IF(MAX(V25,W25)>=0,MIN(MIN(V25,W25),0),MIN(V25,W25)-MAX(V25,W25)),0) -> 0 | AB32: 0 | AJ32: =IF(Cockpit!$AB$62="","",IF(LEFT(Cockpit!$AB$62,1)="⚠",0,100)+13) | AK32: =IF(13=Haltedauer,MAX(INDEX(Projektion!$D$41:$AQ$41,13),INDEX(Projektion!$D$43:$AQ$43,13))*1.12,NA()) -> #N/A | AL32: =IF(13=Haltedauer,INDEX(Projektion!$D$43:$AQ$43,13),NA()) -> #N/A
AJ33: =IF(Cockpit!$AB$63="","",IF(LEFT(Cockpit!$AB$63,1)="⚠",0,100)+14) -> 114 | AK33: =IF(14=Haltedauer,MAX(INDEX(Projektion!$D$41:$AQ$41,14),INDEX(Projektion!$D$43:$AQ$43,14))*1.12,NA()) -> #N/A | AL33: =IF(14=Haltedauer,INDEX(Projektion!$D$43:$AQ$43,14),NA()) -> #N/A
AJ34: =IF(Cockpit!$AB$64="","",IF(LEFT(Cockpit!$AB$64,1)="⚠",0,100)+15) | AK34: =IF(15=Haltedauer,MAX(INDEX(Projektion!$D$41:$AQ$41,15),INDEX(Projektion!$D$43:$AQ$43,15))*1.12,NA()) -> #N/A | AL34: =IF(15=Haltedauer,INDEX(Projektion!$D$43:$AQ$43,15),NA()) -> #N/A
AJ35: =IF(Cockpit!$AB$65="","",IF(LEFT(Cockpit!$AB$65,1)="⚠",0,100)+16) | AK35: =IF(16=Haltedauer,MAX(INDEX(Projektion!$D$41:$AQ$41,16),INDEX(Projektion!$D$43:$AQ$43,16))*1.12,NA()) -> #N/A | AL35: =IF(16=Haltedauer,INDEX(Projektion!$D$43:$AQ$43,16),NA()) -> #N/A
AJ36: =IF(Cockpit!$AB$66="","",IF(LEFT(Cockpit!$AB$66,1)="⚠",0,100)+17) -> 117 | AK36: =IF(17=Haltedauer,MAX(INDEX(Projektion!$D$41:$AQ$41,17),INDEX(Projektion!$D$43:$AQ$43,17))*1.12,NA()) -> #N/A | AL36: =IF(17=Haltedauer,INDEX(Projektion!$D$43:$AQ$43,17),NA()) -> #N/A
AJ37: =IF(Cockpit!$AB$67="","",IF(LEFT(Cockpit!$AB$67,1)="⚠",0,100)+18) | AK37: =IF(18=Haltedauer,MAX(INDEX(Projektion!$D$41:$AQ$41,18),INDEX(Projektion!$D$43:$AQ$43,18))*1.12,NA()) -> #N/A | AL37: =IF(18=Haltedauer,INDEX(Projektion!$D$43:$AQ$43,18),NA()) -> #N/A
AJ38: =IF(Cockpit!$AB$68="","",IF(LEFT(Cockpit!$AB$68,1)="⚠",0,100)+19) | AK38: =IF(19=Haltedauer,MAX(INDEX(Projektion!$D$41:$AQ$41,19),INDEX(Projektion!$D$43:$AQ$43,19))*1.12,NA()) -> #N/A | AL38: =IF(19=Haltedauer,INDEX(Projektion!$D$43:$AQ$43,19),NA()) -> #N/A
AJ39: =IF(Cockpit!$AB$69="","",IF(LEFT(Cockpit!$AB$69,1)="⚠",0,100)+20) | AK39: =IF(20=Haltedauer,MAX(INDEX(Projektion!$D$41:$AQ$41,20),INDEX(Projektion!$D$43:$AQ$43,20))*1.12,NA()) -> #N/A | AL39: =IF(20=Haltedauer,INDEX(Projektion!$D$43:$AQ$43,20),NA()) -> #N/A
AJ40: =IF(Cockpit!$AB$70="","",IF(LEFT(Cockpit!$AB$70,1)="⚠",0,100)+21) | AK40: =IF(21=Haltedauer,MAX(INDEX(Projektion!$D$41:$AQ$41,21),INDEX(Projektion!$D$43:$AQ$43,21))*1.12,NA()) -> #N/A | AL40: =IF(21=Haltedauer,INDEX(Projektion!$D$43:$AQ$43,21),NA()) -> #N/A
AJ41: =IF(Cockpit!$AB$71="","",IF(LEFT(Cockpit!$AB$71,1)="⚠",0,100)+22) | AK41: =IF(22=Haltedauer,MAX(INDEX(Projektion!$D$41:$AQ$41,22),INDEX(Projektion!$D$43:$AQ$43,22))*1.12,NA()) -> #N/A | AL41: =IF(22=Haltedauer,INDEX(Projektion!$D$43:$AQ$43,22),NA()) -> #N/A
B42: Kennzahlen im Zeitverlauf | R42: € p. a. · Jahr 1 = 12 Monate ab Kaufdatum | AJ42: =IF(Cockpit!$AB$72="","",IF(LEFT(Cockpit!$AB$72,1)="⚠",0,100)+23) | AK42: =IF(23=Haltedauer,MAX(INDEX(Projektion!$D$41:$AQ$41,23),INDEX(Projektion!$D$43:$AQ$43,23))*1.12,NA()) -> #N/A | AL42: =IF(23=Haltedauer,INDEX(Projektion!$D$43:$AQ$43,23),NA()) -> #N/A
B43: PROJEKTJAHR | E43: 1 | F43: 2 | H43: 3 | I43: 5 | K43: 10 | L43: 15 | N43: 20 | O43: 25 | Q43: 30 | R43: 40 | AJ43: =IF(Cockpit!$AB$73="","",IF(LEFT(Cockpit!$AB$73,1)="⚠",0,100)+24) | AK43: =IF(24=Haltedauer,MAX(INDEX(Projektion!$D$41:$AQ$41,24),INDEX(Projektion!$D$43:$AQ$43,24))*1.12,NA()) -> #N/A | AL43: =IF(24=Haltedauer,INDEX(Projektion!$D$43:$AQ$43,24),NA()) -> #N/A
B44: Kalenderjahr | E44: =INDEX(Projektion!$D$10:$AQ$10,E$43) -> 2026 | F44: =INDEX(Projektion!$D$10:$AQ$10,F$43) -> 2027 | H44: =INDEX(Projektion!$D$10:$AQ$10,H$43) -> 2028 | I44: =INDEX(Projektion!$D$10:$AQ$10,I$43) -> 2030 | K44: =INDEX(Projektion!$D$10:$AQ$10,K$43) -> 2035 | L44: =INDEX(Projektion!$D$10:$AQ$10,L$43) -> 2040 | N44: =INDEX(Projektion!$D$10:$AQ$10,N$43) -> 2045 | O44: =INDEX(Projektion!$D$10:$AQ$10,O$43) -> 2050 | Q44: =INDEX(Projektion!$D$10:$AQ$10,Q$43) -> 2055 | R44: =INDEX(Projektion!$D$10:$AQ$10,R$43) -> 2065 | AJ44: =IF(Cockpit!$AB$74="","",IF(LEFT(Cockpit!$AB$74,1)="⚠",0,100)+25) | AK44: =IF(25=Haltedauer,MAX(INDEX(Projektion!$D$41:$AQ$41,25),INDEX(Projektion!$D$43:$AQ$43,25))*1.12,NA()) -> #N/A | AL44: =IF(25=Haltedauer,INDEX(Projektion!$D$43:$AQ$43,25),NA()) -> #N/A
B45: CASHFLOW | AK45: =IF(26=Haltedauer,MAX(INDEX(Projektion!$D$41:$AQ$41,26),INDEX(Projektion!$D$43:$AQ$43,26))*1.12,NA()) -> #N/A | AL45: =IF(26=Haltedauer,INDEX(Projektion!$D$43:$AQ$43,26),NA()) -> #N/A
B46: Nettokaltmiete Ist | E46: =INDEX(Projektion!$D$15:$AQ$15,E$43) -> 11058 | F46: =INDEX(Projektion!$D$15:$AQ$15,F$43) -> 11279.16 | H46: =INDEX(Projektion!$D$15:$AQ$15,H$43) -> 11504.743 | I46: =INDEX(Projektion!$D$15:$AQ$15,I$43) -> 11969.535 | K46: =INDEX(Projektion!$D$15:$AQ$15,K$43) -> 13215.334 | L46: =INDEX(Projektion!$D$15:$AQ$15,L$43) -> 14590.796 | N46: =INDEX(Projektion!$D$15:$AQ$15,N$43) -> 16109.418 | O46: =INDEX(Projektion!$D$15:$AQ$15,O$43) -> 17786.099 | Q46: =INDEX(Projektion!$D$15:$AQ$15,Q$43) -> 19637.291 | R46: =INDEX(Projektion!$D$15:$AQ$15,R$43) -> 23937.748 | AK46: =IF(27=Haltedauer,MAX(INDEX(Projektion!$D$41:$AQ$41,27),INDEX(Projektion!$D$43:$AQ$43,27))*1.12,NA()) -> #N/A | AL46: =IF(27=Haltedauer,INDEX(Projektion!$D$43:$AQ$43,27),NA()) -> #N/A
B47: Bewirtschaftungskosten | E47: =-INDEX(Projektion!$D$26:$AQ$26,E$43) -> -2490 | F47: =-INDEX(Projektion!$D$26:$AQ$26,F$43) -> -2539.8 | H47: =-INDEX(Projektion!$D$26:$AQ$26,H$43) -> -2590.596 | I47: =-INDEX(Projektion!$D$26:$AQ$26,I$43) -> -2695.2561 | K47: =-INDEX(Projektion!$D$26:$AQ$26,K$43) -> -2975.7805 | L47: =-INDEX(Projektion!$D$26:$AQ$26,L$43) -> -3285.5021 | N47: =-INDEX(Projektion!$D$26:$AQ$26,N$43) -> -3627.4598 | O47: =-INDEX(Projektion!$D$26:$AQ$26,O$43) -> -4005.0088 | Q47: =-INDEX(Projektion!$D$26:$AQ$26,Q$43) -> -4421.8533 | R47: =-INDEX(Projektion!$D$26:$AQ$26,R$43) -> -5390.2145 | AK47: =IF(28=Haltedauer,MAX(INDEX(Projektion!$D$41:$AQ$41,28),INDEX(Projektion!$D$43:$AQ$43,28))*1.12,NA()) -> #N/A | AL47: =IF(28=Haltedauer,INDEX(Projektion!$D$43:$AQ$43,28),NA()) -> #N/A
B48: Kapitaldienst | E48: =-INDEX(Projektion!$D$32:$AQ$32,E$43) -> -14000 | F48: =-INDEX(Projektion!$D$32:$AQ$32,F$43) -> -14000 | H48: =-INDEX(Projektion!$D$32:$AQ$32,H$43) -> -14000 | I48: =-INDEX(Projektion!$D$32:$AQ$32,I$43) -> -14000 | K48: =-INDEX(Projektion!$D$32:$AQ$32,K$43) -> -14000 | L48: =-INDEX(Projektion!$D$32:$AQ$32,L$43) -> -14000 | N48: =-INDEX(Projektion!$D$32:$AQ$32,N$43) -> -14000 | O48: =-INDEX(Projektion!$D$32:$AQ$32,O$43) -> -14000 | Q48: =-INDEX(Projektion!$D$32:$AQ$32,Q$43) -> -14000 | R48: =-INDEX(Projektion!$D$32:$AQ$32,R$43) -> 0 | AK48: =IF(29=Haltedauer,MAX(INDEX(Projektion!$D$41:$AQ$41,29),INDEX(Projektion!$D$43:$AQ$43,29))*1.12,NA()) -> #N/A | AL48: =IF(29=Haltedauer,INDEX(Projektion!$D$43:$AQ$43,29),NA()) -> #N/A
B49: davon Zinsen | E49: =-INDEX(Projektion!$D$30:$AQ$30,E$43) -> -9000 | F49: =-INDEX(Projektion!$D$30:$AQ$30,F$43) -> -8820 | H49: =-INDEX(Projektion!$D$30:$AQ$30,H$43) -> -8633.52 | I49: =-INDEX(Projektion!$D$30:$AQ$30,I$43) -> -8240.1785 | K49: =-INDEX(Projektion!$D$30:$AQ$30,K$43) -> -7126.0273 | L49: =-INDEX(Projektion!$D$30:$AQ$30,L$43) -> -7558.2594 | N49: =-INDEX(Projektion!$D$30:$AQ$30,N$43) -> -5972.4192 | O49: =-INDEX(Projektion!$D$30:$AQ$30,O$43) -> -3996.1738 | Q49: =-INDEX(Projektion!$D$30:$AQ$30,Q$43) -> -1533.4125 | R49: =-INDEX(Projektion!$D$30:$AQ$30,R$43) -> 0 | AK49: =IF(30=Haltedauer,MAX(INDEX(Projektion!$D$41:$AQ$41,30),INDEX(Projektion!$D$43:$AQ$43,30))*1.12,NA()) -> #N/A | AL49: =IF(30=Haltedauer,INDEX(Projektion!$D$43:$AQ$43,30),NA()) -> #N/A
B50: davon Tilgung | E50: =-INDEX(Projektion!$D$31:$AQ$31,E$43) -> -5000 | F50: =-INDEX(Projektion!$D$31:$AQ$31,F$43) -> -5180 | H50: =-INDEX(Projektion!$D$31:$AQ$31,H$43) -> -5366.48 | I50: =-INDEX(Projektion!$D$31:$AQ$31,I$43) -> -5759.8215 | K50: =-INDEX(Projektion!$D$31:$AQ$31,K$43) -> -6873.9727 | L50: =-INDEX(Projektion!$D$31:$AQ$31,L$43) -> -6441.7406 | N50: =-INDEX(Projektion!$D$31:$AQ$31,N$43) -> -8027.5808 | O50: =-INDEX(Projektion!$D$31:$AQ$31,O$43) -> -10003.826 | Q50: =-INDEX(Projektion!$D$31:$AQ$31,Q$43) -> -12466.587 | R50: =-INDEX(Projektion!$D$31:$AQ$31,R$43) -> 0 | AK50: =IF(31=Haltedauer,MAX(INDEX(Projektion!$D$41:$AQ$41,31),INDEX(Projektion!$D$43:$AQ$43,31))*1.12,NA()) -> #N/A | AL50: =IF(31=Haltedauer,INDEX(Projektion!$D$43:$AQ$43,31),NA()) -> #N/A
B51: = Cashflow vor Steuern | E51: =INDEX(Projektion!$D$33:$AQ$33,E$43) -> -5432 | F51: =INDEX(Projektion!$D$33:$AQ$33,F$43) -> -5260.64 | H51: =INDEX(Projektion!$D$33:$AQ$33,H$43) -> -5085.8528 | I51: =INDEX(Projektion!$D$33:$AQ$33,I$43) -> -4725.7213 | K51: =INDEX(Projektion!$D$33:$AQ$33,K$43) -> -3760.4469 | L51: =INDEX(Projektion!$D$33:$AQ$33,L$43) -> -2694.706 | N51: =INDEX(Projektion!$D$33:$AQ$33,N$43) -> -1518.0419 | O51: =INDEX(Projektion!$D$33:$AQ$33,O$43) -> -218.90965 | Q51: =INDEX(Projektion!$D$33:$AQ$33,Q$43) -> 1215.4373 | R51: =INDEX(Projektion!$D$33:$AQ$33,R$43) -> 18547.533 | AK51: =IF(32=Haltedauer,MAX(INDEX(Projektion!$D$41:$AQ$41,32),INDEX(Projektion!$D$43:$AQ$43,32))*1.12,NA()) -> #N/A | AL51: =IF(32=Haltedauer,INDEX(Projektion!$D$43:$AQ$43,32),NA()) -> #N/A
B52: ± Steuerwirkung (Cash-Sicht) | E52: =-INDEX(Projektion!$D$35:$AQ$35,E$43) -> 8510.3965 | F52: =-INDEX(Projektion!$D$35:$AQ$35,F$43) -> 1973.6765 | H52: =-INDEX(Projektion!$D$35:$AQ$35,H$43) -> 1792.6866 | I52: =-INDEX(Projektion!$D$35:$AQ$35,I$43) -> 1415.5569 | K52: =-INDEX(Projektion!$D$35:$AQ$35,K$43) -> 377.03005 | L52: =-INDEX(Projektion!$D$35:$AQ$35,L$43) -> -370.67708 | N52: =-INDEX(Projektion!$D$35:$AQ$35,N$43) -> -1741.965 | O52: =-INDEX(Projektion!$D$35:$AQ$35,O$43) -> -3360.2218 | Q52: =-INDEX(Projektion!$D$35:$AQ$35,Q$43) -> -5276.8151 | R52: =-INDEX(Projektion!$D$35:$AQ$35,R$43) -> -7791.9947 | AK52: =IF(33=Haltedauer,MAX(INDEX(Projektion!$D$41:$AQ$41,33),INDEX(Projektion!$D$43:$AQ$43,33))*1.12,NA()) -> #N/A | AL52: =IF(33=Haltedauer,INDEX(Projektion!$D$43:$AQ$43,33),NA()) -> #N/A
B53: = Cashflow nach Steuern | E53: =INDEX(Projektion!$D$36:$AQ$36,E$43) -> 3078.3965 | F53: =INDEX(Projektion!$D$36:$AQ$36,F$43) -> -3286.9635 | H53: =INDEX(Projektion!$D$36:$AQ$36,H$43) -> -3293.1662 | I53: =INDEX(Projektion!$D$36:$AQ$36,I$43) -> -3310.1643 | K53: =INDEX(Projektion!$D$36:$AQ$36,K$43) -> -3383.4168 | L53: =INDEX(Projektion!$D$36:$AQ$36,L$43) -> -3065.383 | N53: =INDEX(Projektion!$D$36:$AQ$36,N$43) -> -3260.0069 | O53: =INDEX(Projektion!$D$36:$AQ$36,O$43) -> -3579.1315 | Q53: =INDEX(Projektion!$D$36:$AQ$36,Q$43) -> -4061.3778 | R53: =INDEX(Projektion!$D$36:$AQ$36,R$43) -> 10755.539 | AK53: =IF(34=Haltedauer,MAX(INDEX(Projektion!$D$41:$AQ$41,34),INDEX(Projektion!$D$43:$AQ$43,34))*1.12,NA()) -> #N/A | AL53: =IF(34=Haltedauer,INDEX(Projektion!$D$43:$AQ$43,34),NA()) -> #N/A
B54: Kumulierter Cashflow n. St. | E54: =INDEX(Projektion!$D$38:$AQ$38,E$43) -> 3078.3965 | F54: =INDEX(Projektion!$D$38:$AQ$38,F$43) -> -208.56691 | H54: =INDEX(Projektion!$D$38:$AQ$38,H$43) -> -3501.7331 | I54: =INDEX(Projektion!$D$38:$AQ$38,I$43) -> -10112.771 | K54: =INDEX(Projektion!$D$38:$AQ$38,K$43) -> -26864.422 | L54: =INDEX(Projektion!$D$38:$AQ$38,L$43) -> -41957.864 | N54: =INDEX(Projektion!$D$38:$AQ$38,N$43) -> -57825.467 | O54: =INDEX(Projektion!$D$38:$AQ$38,O$43) -> -75026.027 | Q54: =INDEX(Projektion!$D$38:$AQ$38,Q$43) -> -94294.231 | R54: =INDEX(Projektion!$D$38:$AQ$38,R$43) -> -16195.544 | AK54: =IF(35=Haltedauer,MAX(INDEX(Projektion!$D$41:$AQ$41,35),INDEX(Projektion!$D$43:$AQ$43,35))*1.12,NA()) -> #N/A | AL54: =IF(35=Haltedauer,INDEX(Projektion!$D$43:$AQ$43,35),NA()) -> #N/A
B55: STEUER | AK55: =IF(36=Haltedauer,MAX(INDEX(Projektion!$D$41:$AQ$41,36),INDEX(Projektion!$D$43:$AQ$43,36))*1.12,NA()) -> #N/A | AL55: =IF(36=Haltedauer,INDEX(Projektion!$D$43:$AQ$43,36),NA()) -> #N/A
B56: Abschreibungen (AfA) | E56: =INDEX(Steuern!$D$56:$AQ$56,E$43) -> 5685.3569 | F56: =INDEX(Steuern!$D$56:$AQ$56,F$43) -> 5685.3569 | H56: =INDEX(Steuern!$D$56:$AQ$56,H$43) -> 5685.3569 | I56: =INDEX(Steuern!$D$56:$AQ$56,I$43) -> 5685.3569 | K56: =INDEX(Steuern!$D$56:$AQ$56,K$43) -> 5685.3569 | L56: =INDEX(Steuern!$D$56:$AQ$56,L$43) -> 4885.3569 | N56: =INDEX(Steuern!$D$56:$AQ$56,N$43) -> 4885.3569 | O56: =INDEX(Steuern!$D$56:$AQ$56,O$43) -> 4885.3569 | Q56: =INDEX(Steuern!$D$56:$AQ$56,Q$43) -> 4885.3569 | R56: =INDEX(Steuern!$D$56:$AQ$56,R$43) -> 4885.3569 | AK56: =IF(37=Haltedauer,MAX(INDEX(Projektion!$D$41:$AQ$41,37),INDEX(Projektion!$D$43:$AQ$43,37))*1.12,NA()) -> #N/A | AL56: =IF(37=Haltedauer,INDEX(Projektion!$D$43:$AQ$43,37),NA()) -> #N/A
B57: Steuerliches Ergebnis | E57: =INDEX(Steuern!$D$67:$AQ$67,E$43) -> -18397.357 | F57: =INDEX(Steuern!$D$67:$AQ$67,F$43) -> -4266.5969 | H57: =INDEX(Steuern!$D$67:$AQ$67,H$43) -> -3875.3417 | I57: =INDEX(Steuern!$D$67:$AQ$67,I$43) -> -3060.0814 | K57: =INDEX(Steuern!$D$67:$AQ$67,K$43) -> -815.04503 | L57: =INDEX(Steuern!$D$67:$AQ$67,L$43) -> 801.31148 | N57: =INDEX(Steuern!$D$67:$AQ$67,N$43) -> 3765.6944 | O57: =INDEX(Steuern!$D$67:$AQ$67,O$43) -> 7263.9623 | Q57: =INDEX(Steuern!$D$67:$AQ$67,Q$43) -> 11407.16 | R57: =INDEX(Steuern!$D$67:$AQ$67,R$43) -> 16844.351 | AK57: =IF(38=Haltedauer,MAX(INDEX(Projektion!$D$41:$AQ$41,38),INDEX(Projektion!$D$43:$AQ$43,38))*1.12,NA()) -> #N/A | AL57: =IF(38=Haltedauer,INDEX(Projektion!$D$43:$AQ$43,38),NA()) -> #N/A
B58: VERMÖGEN | AK58: =IF(39=Haltedauer,MAX(INDEX(Projektion!$D$41:$AQ$41,39),INDEX(Projektion!$D$43:$AQ$43,39))*1.12,NA()) -> #N/A | AL58: =IF(39=Haltedauer,INDEX(Projektion!$D$43:$AQ$43,39),NA()) -> #N/A
B59: Immobilienwert (Jahresende) | E59: =INDEX(Projektion!$D$41:$AQ$41,E$43) -> 302940 | F59: =INDEX(Projektion!$D$41:$AQ$41,F$43) -> 308998.8 | H59: =INDEX(Projektion!$D$41:$AQ$41,H$43) -> 315178.78 | I59: =INDEX(Projektion!$D$41:$AQ$41,I$43) -> 327912 | K59: =INDEX(Projektion!$D$41:$AQ$41,K$43) -> 362041.34 | L59: =INDEX(Projektion!$D$41:$AQ$41,L$43) -> 399722.9 | N59: =INDEX(Projektion!$D$41:$AQ$41,N$43) -> 441326.38 | O59: =INDEX(Projektion!$D$41:$AQ$41,O$43) -> 487259.98 | Q59: =INDEX(Projektion!$D$41:$AQ$41,Q$43) -> 537974.39 | R59: =INDEX(Projektion!$D$41:$AQ$41,R$43) -> 655787.78 | AK59: =IF(40=Haltedauer,MAX(INDEX(Projektion!$D$41:$AQ$41,40),INDEX(Projektion!$D$43:$AQ$43,40))*1.12,NA()) -> #N/A | AL59: =IF(40=Haltedauer,INDEX(Projektion!$D$43:$AQ$43,40),NA()) -> #N/A
B60: Restschuld | E60: =-INDEX(Projektion!$D$42:$AQ$42,E$43) -> -245000 | F60: =-INDEX(Projektion!$D$42:$AQ$42,F$43) -> -239820 | H60: =-INDEX(Projektion!$D$42:$AQ$42,H$43) -> -234453.52 | I60: =-INDEX(Projektion!$D$42:$AQ$42,I$43) -> -223134.03 | K60: =-INDEX(Projektion!$D$42:$AQ$42,K$43) -> -191071.23 | L60: =-INDEX(Projektion!$D$42:$AQ$42,L$43) -> -161519.58 | N60: =-INDEX(Projektion!$D$42:$AQ$42,N$43) -> -124692.85 | O60: =-INDEX(Projektion!$D$42:$AQ$42,O$43) -> -78800.037 | Q60: =-INDEX(Projektion!$D$42:$AQ$42,Q$43) -> -21609.246 | R60: =-INDEX(Projektion!$D$42:$AQ$42,R$43) -> 0
B61: = Nettovermögen | E61: =INDEX(Projektion!$D$43:$AQ$43,E$43) -> 57940 | F61: =INDEX(Projektion!$D$43:$AQ$43,F$43) -> 69178.8 | H61: =INDEX(Projektion!$D$43:$AQ$43,H$43) -> 80725.256 | I61: =INDEX(Projektion!$D$43:$AQ$43,I$43) -> 104777.97 | K61: =INDEX(Projektion!$D$43:$AQ$43,K$43) -> 170970.11 | L61: =INDEX(Projektion!$D$43:$AQ$43,L$43) -> 238203.32 | N61: =INDEX(Projektion!$D$43:$AQ$43,N$43) -> 316633.53 | O61: =INDEX(Projektion!$D$43:$AQ$43,O$43) -> 408459.94 | Q61: =INDEX(Projektion!$D$43:$AQ$43,Q$43) -> 516365.14 | R61: =INDEX(Projektion!$D$43:$AQ$43,R$43) -> 655787.78
B62: EK-Rendite | E62: =INDEX(Projektion!$D$45:$AQ$45,E$43) -> 0.17750535 | F62: =INDEX(Projektion!$D$45:$AQ$45,F$43) -> 0.10068866 | H62: =INDEX(Projektion!$D$45:$AQ$45,H$43) -> 0.10450576 | I62: =INDEX(Projektion!$D$45:$AQ$45,I$43) -> 0.11243255 | K62: =INDEX(Projektion!$D$45:$AQ$45,K$43) -> 0.13408639 | L62: =INDEX(Projektion!$D$45:$AQ$45,L$43) -> 0.14199598 | N62: =INDEX(Projektion!$D$45:$AQ$45,N$43) -> 0.16994134 | O62: =INDEX(Projektion!$D$45:$AQ$45,O$43) -> 0.20232875 | Q62: =INDEX(Projektion!$D$45:$AQ$45,Q$43) -> 0.23999806 | R62: =INDEX(Projektion!$D$45:$AQ$45,R$43) -> 0.29900946 | AK62: ="Verkauf "&INDEX(Projektion!$D$10:$AQ$10,Haltedauer)&CHAR(10)&"Nettovermögen"&CHAR(10)&FIXED(INDEX(Projektion!$D$43:$AQ$43,Haltedauer)/1000,0)&" T€" -> Verkauf 2037 Nettovermögen 197 T€
B63: Cash-Sicht: + fließt zu, − fließt ab (Steuerwirkung: + Erstattung, − Zahlung) · Rot – negative Ergebnis- und Kumulwerte | N63: Alle 40 Jahre: Projektion ›
B65: Prüfhinweise & steuerliche Einordnung | R65: =IF(COUNTIF(Cockpit!$AB$50:$AB$74,"⚠*")=0,"Keine Warnungen",IF(COUNTIF(Cockpit!$AB$50:$AB$74,"⚠*")=1,"1 Warnung",COUNTIF(Cockpit!$AB$50:$AB$74,"⚠*")&" Warnungen"))&" · "&IF(COUNT($AJ$20:$AJ$44)-COUNTIF(Cockpit!$AB$50:$AB$74,"⚠*")=0,"keine Hinweise",IF(COUNT($AJ$20:$AJ$44)-COUNTIF(Cockpit!$AB$50:$AB$74,"⚠*")=1,"1 Hinweis",(COUNT($AJ$20:$AJ$44)-COUNTIF(Cockpit!$AB$50:$AB$74,"⚠*"))&" Hinweise")) -> 1 Warnung · 3 Hinweise
B67: =IF(COUNT($AJ$20:$AJ$44)=0,"Keine Prüfhinweise – alle Plausibilitätsprüfungen ohne Befund.",IF(LEFT(IFERROR(INDEX(Cockpit!$AB$50:$AB$74,MATCH(SMALL($AJ$20:$AJ$44,1),$AJ$20:$AJ$44,0)),""),1)="⚠","▲ "&TRIM(MID(IFERROR(INDEX(Cockpit!$AB$50:$AB$74,MATCH(SMALL($AJ$20:$AJ$44,1),$AJ$20:$AJ$44,0)),""),2,999)),IF(LEFT(IFERROR(INDEX(Cockpit!$AB$50:$AB$74,MATCH(SMALL($AJ$20:$AJ$44,1),$AJ$20:$AJ$44,0)),""),1)="ℹ","• "&TRIM(MID(IFERROR(INDEX(Cockpit!$AB$50:$AB$74,MATCH(SMALL($AJ$20:$AJ$44,1),$AJ$20:$AJ$44,0)),""),2,999)),IFERROR(INDEX(Cockpit!$AB$50:$AB$74,MATCH(SMALL($AJ$20:$AJ$44,1),$AJ$20:$AJ$44,0)),"")))) -> ▲ Kapitaldienstdeckung (DSCR) im Jahr 1 nur 0.61 – Banken erwarten meist ≥ 1,1 bis 1,2 (NOI / Kapitaldienst).
B68: =IF(LEFT(IFERROR(INDEX(Cockpit!$AB$50:$AB$74,MATCH(SMALL($AJ$20:$AJ$44,2),$AJ$20:$AJ$44,0)),""),1)="⚠","▲ "&TRIM(MID(IFERROR(INDEX(Cockpit!$AB$50:$AB$74,MATCH(SMALL($AJ$20:$AJ$44,2),$AJ$20:$AJ$44,0)),""),2,999)),IF(LEFT(IFERROR(INDEX(Cockpit!$AB$50:$AB$74,MATCH(SMALL($AJ$20:$AJ$44,2),$AJ$20:$AJ$44,0)),""),1)="ℹ","• "&TRIM(MID(IFERROR(INDEX(Cockpit!$AB$50:$AB$74,MATCH(SMALL($AJ$20:$AJ$44,2),$AJ$20:$AJ$44,0)),""),2,999)),IFERROR(INDEX(Cockpit!$AB$50:$AB$74,MATCH(SMALL($AJ$20:$AJ$44,2),$AJ$20:$AJ$44,0)),""))) -> • Zinsbindung Darlehen I endet nach 10 Jahren bei einer Restschuld von 191,071 € – Anschlusszins 4.50 % angenommen; jeder Prozentpunkt mehr kostet 1,911 € p. a.
B69: =IF(LEFT(IFERROR(INDEX(Cockpit!$AB$50:$AB$74,MATCH(SMALL($AJ$20:$AJ$44,3),$AJ$20:$AJ$44,0)),""),1)="⚠","▲ "&TRIM(MID(IFERROR(INDEX(Cockpit!$AB$50:$AB$74,MATCH(SMALL($AJ$20:$AJ$44,3),$AJ$20:$AJ$44,0)),""),2,999)),IF(LEFT(IFERROR(INDEX(Cockpit!$AB$50:$AB$74,MATCH(SMALL($AJ$20:$AJ$44,3),$AJ$20:$AJ$44,0)),""),1)="ℹ","• "&TRIM(MID(IFERROR(INDEX(Cockpit!$AB$50:$AB$74,MATCH(SMALL($AJ$20:$AJ$44,3),$AJ$20:$AJ$44,0)),""),2,999)),IFERROR(INDEX(Cockpit!$AB$50:$AB$74,MATCH(SMALL($AJ$20:$AJ$44,3),$AJ$20:$AJ$44,0)),""))) -> • Steuerliches Ergebnis Jahr 1 negativ (-18,397 €) – Verlust wird mit anderen Einkünften verrechnet (Erstattung 8,510 €). Einkünfteerzielungsabsicht / Totalüberschussprognose beachten.
B70: =IF(LEFT(IFERROR(INDEX(Cockpit!$AB$50:$AB$74,MATCH(SMALL($AJ$20:$AJ$44,4),$AJ$20:$AJ$44,0)),""),1)="⚠","▲ "&TRIM(MID(IFERROR(INDEX(Cockpit!$AB$50:$AB$74,MATCH(SMALL($AJ$20:$AJ$44,4),$AJ$20:$AJ$44,0)),""),2,999)),IF(LEFT(IFERROR(INDEX(Cockpit!$AB$50:$AB$74,MATCH(SMALL($AJ$20:$AJ$44,4),$AJ$20:$AJ$44,0)),""),1)="ℹ","• "&TRIM(MID(IFERROR(INDEX(Cockpit!$AB$50:$AB$74,MATCH(SMALL($AJ$20:$AJ$44,4),$AJ$20:$AJ$44,0)),""),2,999)),IFERROR(INDEX(Cockpit!$AB$50:$AB$74,MATCH(SMALL($AJ$20:$AJ$44,4),$AJ$20:$AJ$44,0)),""))) -> • Bewegliche Gegenstände (8,000 €) sind grunderwerbsteuerfrei und werden über 10 Jahre gesondert abgeschrieben – im Kaufvertrag gesondert und angemessen ausweisen.
B71: =IF(LEFT(IFERROR(INDEX(Cockpit!$AB$50:$AB$74,MATCH(SMALL($AJ$20:$AJ$44,5),$AJ$20:$AJ$44,0)),""),1)="⚠","▲ "&TRIM(MID(IFERROR(INDEX(Cockpit!$AB$50:$AB$74,MATCH(SMALL($AJ$20:$AJ$44,5),$AJ$20:$AJ$44,0)),""),2,999)),IF(LEFT(IFERROR(INDEX(Cockpit!$AB$50:$AB$74,MATCH(SMALL($AJ$20:$AJ$44,5),$AJ$20:$AJ$44,0)),""),1)="ℹ","• "&TRIM(MID(IFERROR(INDEX(Cockpit!$AB$50:$AB$74,MATCH(SMALL($AJ$20:$AJ$44,5),$AJ$20:$AJ$44,0)),""),2,999)),IFERROR(INDEX(Cockpit!$AB$50:$AB$74,MATCH(SMALL($AJ$20:$AJ$44,5),$AJ$20:$AJ$44,0)),"")))
B72: =IF(COUNT($AJ$20:$AJ$44)>6,"› "&(COUNT($AJ$20:$AJ$44)-5)&" weitere Hinweise im Cockpit",IF(LEFT(IFERROR(INDEX(Cockpit!$AB$50:$AB$74,MATCH(SMALL($AJ$20:$AJ$44,6),$AJ$20:$AJ$44,0)),""),1)="⚠","▲ "&TRIM(MID(IFERROR(INDEX(Cockpit!$AB$50:$AB$74,MATCH(SMALL($AJ$20:$AJ$44,6),$AJ$20:$AJ$44,0)),""),2,999)),IF(LEFT(IFERROR(INDEX(Cockpit!$AB$50:$AB$74,MATCH(SMALL($AJ$20:$AJ$44,6),$AJ$20:$AJ$44,0)),""),1)="ℹ","• "&TRIM(MID(IFERROR(INDEX(Cockpit!$AB$50:$AB$74,MATCH(SMALL($AJ$20:$AJ$44,6),$AJ$20:$AJ$44,0)),""),2,999)),IFERROR(INDEX(Cockpit!$AB$50:$AB$74,MATCH(SMALL($AJ$20:$AJ$44,6),$AJ$20:$AJ$44,0)),""))))
B74: Keine Gewähr für die Richtigkeit der Angaben · ersetzt keine Rechts-, Steuer- oder Finanzberatung · Rechtsstand September 2026 | R74: =TODAY() -> 46289
B75: MM Holding GmbH · Kornhausgasse 4 · 88250 Weingarten · Amtsgericht Ulm HRB 750729

Sheet Cockpit
B5: ERGEBNIS · ÜBERSICHT AUF EINER SEITE | K5: GESAMTBEWERTUNG
B6: Cockpit | K6: =Dashboard!$B$12 -> Liquidität kritisch
B7: =Obj_Name&" · "&Obj_Adresse&" · Kauf am "&TEXT(DAY(Kaufdatum),"00")&"."&TEXT(MONTH(Kaufdatum),"00")&"."&YEAR(Kaufdatum)&" · Haltedauer "&Haltedauer&" Jahre · "&CHOOSE(Rechtsform_Idx,"Privat","vv-GmbH","GmbH") -> Beispiel: 3-Zimmer-Eigentumswohnung · Musterstraße 1, 88250 Weingarten · Kauf am 01.12.2026 · Haltedauer 12 Jahre · Privat | K7: =IFERROR(IF(Erstellt_fuer="","","Erstellt für "&Erstellt_fuer),"") -> Erstellt für Max Mustermann
B8: GESAMTINVESTITION | C8: BRUTTOMIETRENDITE | F8: EIGENKAPITALBEDARF INKL. RESERVE | G8: DSCR | J8: CASHFLOW N. ST. / MONAT (JAHR 1) | K8: =UPPER("IRR n. St. ("&Haltedauer&" J.)") -> IRR N. ST. (12 J.) | N8: Bruttomietrendite | Kaufpreisfaktor | R8: Eigenkapitalrendite Jahr 1 (Vermögenszuwachs / EK) | V8: ="IRR nach Steuern – Verkauf nach "&Haltedauer&" J." -> IRR nach Steuern – Verkauf nach 12 J.
B9: =Gesamtinvestition -> 328974.5 | C9: =Bruttomietrendite -> 0.04 | F9: =EK_Bedarf_gesamt -> 83974.5 | G9: =DSCR_J1 -> 0.612 | J9: =INDEX(Projektion!$D$37:$AQ$37,1) -> 256.53305 | K9: =IRR_Tile -> 0.053273956 | N9: =FIXED(Bruttomietrendite*100,2)&" % | "&FIXED(Kaufpreisfaktor,1)&"-fach" -> 4.00 % | 25.0-fach | R9: =INDEX(Projektion!$D$45:$AQ$45,1) -> 0.17750535 | V9: =EK_IRR -> 0.053273956
B10: ="Kaufpreis "&FIXED(Kaufpreis,0)&" € · Nebenkosten "&FIXED(NK_Quote*100,1)&" %" -> Kaufpreis 285,000 € · Nebenkosten 10.6 % | C10: ="Ziel ≥ "&FIXED(Ampel_BMR_gruen*100,1)&" %" -> Ziel ≥ 5.0 % | D10: =IF(AND(ISNUMBER($C$9),$C$9<Ampel_BMR_gelb),"● kritisch",IF(AND(ISNUMBER($C$9),$C$9<Ampel_BMR_gruen),"● prüfen",IF(ISNUMBER($C$9),"● erfüllt",""))) -> ● prüfen | F10: =IF(Reserve_Einmalig=0,"ohne Liquiditätsreserve","davon Liquiditätsreserve "&FIXED(Reserve_Einmalig,0)&" €") -> davon Liquiditätsreserve 5,000 € | G10: ="Ziel ≥ "&FIXED(Ampel_DSCR_gruen,2)&"×" -> Ziel ≥ 1.20× | H10: =IF(AND(ISNUMBER($G$9),$G$9<Ampel_DSCR_gelb),"● kritisch",IF(AND(ISNUMBER($G$9),$G$9<Ampel_DSCR_gruen),"● prüfen",IF(ISNUMBER($G$9),"● erfüllt",""))) -> ● kritisch | J10: ="ab Jahr 2: "&SUBSTITUTE(FIXED(INDEX(Projektion!$D$37:$AQ$37,2),0),"-","−")&" € / Monat" -> ab Jahr 2: −274 € / Monat | K10: ="Ziel ≥ "&FIXED(Ampel_IRR_gruen*100,1)&" %" -> Ziel ≥ 6.0 % | L10: =IF(AND(ISNUMBER($K$9),$K$9<Ampel_IRR_gelb),"● kritisch",IF(AND(ISNUMBER($K$9),$K$9<Ampel_IRR_gruen),"● prüfen",IF(ISNUMBER($K$9),"● erfüllt",""))) -> ● prüfen
N11: Kennzahlen im Zeitverlauf
B13: Objekt & Investition | D13: Eingaben › | F13: Miete, Bewirtschaftung & Rendite | H13: Projektion › | J13: Finanzierung | L13: Finanzierung › | N13: JAHR DER KALKULATION | O13: 1 | P13: 2 | Q13: 3 | R13: 5 | S13: 10 | T13: 15 | U13: 20 | V13: 25 | W13: 30 | X13: 40
B14: Objektart | C14: =Objektart -> Eigentumswohnung | F14: Nettokaltmiete pro Monat (Soll) | G14: =Miete_Monat -> 950 | J14: Darlehen gesamt | K14: =Darlehen_Summe -> 250000 | N14: Kalenderjahr | O14: =YEAR(Kaufdatum)+1-1 -> 2026 | P14: =YEAR(Kaufdatum)+2-1 -> 2027 | Q14: =YEAR(Kaufdatum)+3-1 -> 2028 | R14: =YEAR(Kaufdatum)+5-1 -> 2030 | S14: =YEAR(Kaufdatum)+10-1 -> 2035 | T14: =YEAR(Kaufdatum)+15-1 -> 2040 | U14: =YEAR(Kaufdatum)+20-1 -> 2045 | V14: =YEAR(Kaufdatum)+25-1 -> 2050 | W14: =YEAR(Kaufdatum)+30-1 -> 2055 | X14: =YEAR(Kaufdatum)+40-1 -> 2065
B15: Wohn-/Nutzfläche | C15: =Wohnflaeche -> 75 | F15: Miete je m² und Monat | G15: =Miete_qm -> 12.666667 | J15: Darlehen I · Darlehen II | K15: =FIXED(Darlehen_I,0)&" € · "&IF(Darlehen_II=0,"kein Darlehen II",FIXED(Darlehen_II,0)&" €") -> 250,000 € · kein Darlehen II | N15: Nettokaltmiete Ist | O15: =INDEX(Projektion!$D$15:$AQ$15,1) -> 11058 | P15: =INDEX(Projektion!$D$15:$AQ$15,2) -> 11279.16 | Q15: =INDEX(Projektion!$D$15:$AQ$15,3) -> 11504.743 | R15: =INDEX(Projektion!$D$15:$AQ$15,5) -> 11969.535 | S15: =INDEX(Projektion!$D$15:$AQ$15,10) -> 13215.334 | T15: =INDEX(Projektion!$D$15:$AQ$15,15) -> 14590.796 | U15: =INDEX(Projektion!$D$15:$AQ$15,20) -> 16109.418 | V15: =INDEX(Projektion!$D$15:$AQ$15,25) -> 17786.099 | W15: =INDEX(Projektion!$D$15:$AQ$15,30) -> 19637.291 | X15: =INDEX(Projektion!$D$15:$AQ$15,40) -> 23937.748
B16: Baujahr | C16: =Baujahr -> 1996 | F16: Jahresnettokaltmiete (Soll) | G16: =Jahresmiete -> 11400 | J16: Eigenkapital (ohne Reserve) | K16: =Eigenkapital -> 78974.5 | N16: Bewirtschaftungskosten | O16: =INDEX(Projektion!$D$26:$AQ$26,1) -> 2490 | P16: =INDEX(Projektion!$D$26:$AQ$26,2) -> 2539.8 | Q16: =INDEX(Projektion!$D$26:$AQ$26,3) -> 2590.596 | R16: =INDEX(Projektion!$D$26:$AQ$26,5) -> 2695.2561 | S16: =INDEX(Projektion!$D$26:$AQ$26,10) -> 2975.7805 | T16: =INDEX(Projektion!$D$26:$AQ$26,15) -> 3285.5021 | U16: =INDEX(Projektion!$D$26:$AQ$26,20) -> 3627.4598 | V16: =INDEX(Projektion!$D$26:$AQ$26,25) -> 4005.0088 | W16: =INDEX(Projektion!$D$26:$AQ$26,30) -> 4421.8533 | X16: =INDEX(Projektion!$D$26:$AQ$26,40) -> 5390.2145
B17: Kaufpreis | C17: =Kaufpreis -> 285000 | F17: Nettokaltmiete Ist Jahr 1 (nach Ausfall) | G17: =INDEX(Projektion!$D$15:$AQ$15,1) -> 11058 | J17: Eigenkapitalquote | K17: =EK_Quote -> 0.24006268 | N17: Zinsen | O17: =INDEX(Projektion!$D$30:$AQ$30,1) -> 9000 | P17: =INDEX(Projektion!$D$30:$AQ$30,2) -> 8820 | Q17: =INDEX(Projektion!$D$30:$AQ$30,3) -> 8633.52 | R17: =INDEX(Projektion!$D$30:$AQ$30,5) -> 8240.1785 | S17: =INDEX(Projektion!$D$30:$AQ$30,10) -> 7126.0273 | T17: =INDEX(Projektion!$D$30:$AQ$30,15) -> 7558.2594 | U17: =INDEX(Projektion!$D$30:$AQ$30,20) -> 5972.4192 | V17: =INDEX(Projektion!$D$30:$AQ$30,25) -> 3996.1738 | W17: =INDEX(Projektion!$D$30:$AQ$30,30) -> 1533.4125 | X17: =INDEX(Projektion!$D$30:$AQ$30,40) -> 0
B18: Kaufpreis je m² (Immobilie) | C18: =IF(Wohnflaeche>0,KP_Immobilie/Wohnflaeche,0) -> 3653.3333 | F18: – Bewirtschaftung Jahr 1 (inkl. Rücklagen) | G18: =INDEX(Projektion!$D$26:$AQ$26,1) -> 2490 | J18: Beleihungsauslauf (Darlehen / Kaufpreis) | K18: =Beleihung -> 0.87719298 | N18: Tilgung | O18: =INDEX(Projektion!$D$31:$AQ$31,1) -> 5000 | P18: =INDEX(Projektion!$D$31:$AQ$31,2) -> 5180 | Q18: =INDEX(Projektion!$D$31:$AQ$31,3) -> 5366.48 | R18: =INDEX(Projektion!$D$31:$AQ$31,5) -> 5759.8215 | S18: =INDEX(Projektion!$D$31:$AQ$31,10) -> 6873.9727 | T18: =INDEX(Projektion!$D$31:$AQ$31,15) -> 6441.7406 | U18: =INDEX(Projektion!$D$31:$AQ$31,20) -> 8027.5808 | V18: =INDEX(Projektion!$D$31:$AQ$31,25) -> 10003.826 | W18: =INDEX(Projektion!$D$31:$AQ$31,30) -> 12466.587 | X18: =INDEX(Projektion!$D$31:$AQ$31,40) -> 0
B19: + Kaufnebenkosten | C19: =NK_Summe -> 30224.5 | F19: in % der Nettokaltmiete | G19: =IF(INDEX(Projektion!$D$15:$AQ$15,1)>0,BWK_J1/INDEX(Projektion!$D$15:$AQ$15,1),0) -> 0.22517634 | J19: Gewichteter Sollzins Jahr 1 | K19: =INDEX(Finanzierung!$D$39:$AQ$39,1) -> 0.036 | N19: Cashflow vor Steuern | O19: =INDEX(Projektion!$D$33:$AQ$33,1) -> -5432 | P19: =INDEX(Projektion!$D$33:$AQ$33,2) -> -5260.64 | Q19: =INDEX(Projektion!$D$33:$AQ$33,3) -> -5085.8528 | R19: =INDEX(Projektion!$D$33:$AQ$33,5) -> -4725.7213 | S19: =INDEX(Projektion!$D$33:$AQ$33,10) -> -3760.4469 | T19: =INDEX(Projektion!$D$33:$AQ$33,15) -> -2694.706 | U19: =INDEX(Projektion!$D$33:$AQ$33,20) -> -1518.0419 | V19: =INDEX(Projektion!$D$33:$AQ$33,25) -> -218.90965 | W19: =INDEX(Projektion!$D$33:$AQ$33,30) -> 1215.4373 | X19: =INDEX(Projektion!$D$33:$AQ$33,40) -> 18547.533
B20: Kaufnebenkostenquote | C20: =NK_Quote -> 0.10605088 | F20: = Einnahmenüberschuss (NOI) Jahr 1 | G20: =INDEX(Projektion!$D$29:$AQ$29,1) -> 8568 | N20: Abschreibungen gesamt | O20: =INDEX(Steuern!$D$56:$AQ$56,1) -> 5685.3569 | P20: =INDEX(Steuern!$D$56:$AQ$56,2) -> 5685.3569 | Q20: =INDEX(Steuern!$D$56:$AQ$56,3) -> 5685.3569 | R20: =INDEX(Steuern!$D$56:$AQ$56,5) -> 5685.3569 | S20: =INDEX(Steuern!$D$56:$AQ$56,10) -> 5685.3569 | T20: =INDEX(Steuern!$D$56:$AQ$56,15) -> 4885.3569 | U20: =INDEX(Steuern!$D$56:$AQ$56,20) -> 4885.3569 | V20: =INDEX(Steuern!$D$56:$AQ$56,25) -> 4885.3569 | W20: =INDEX(Steuern!$D$56:$AQ$56,30) -> 4885.3569 | X20: =INDEX(Steuern!$D$56:$AQ$56,40) -> 4885.3569
B21: + Finanzierungsnebenkosten | C21: =FinNK_Summe -> 1750 | J21: KAPITALDIENST UND ZINSRISIKO | N21: Steuerliches Ergebnis | O21: =INDEX(Steuern!$D$67:$AQ$67,1) -> -18397.357 | P21: =INDEX(Steuern!$D$67:$AQ$67,2) -> -4266.5969 | Q21: =INDEX(Steuern!$D$67:$AQ$67,3) -> -3875.3417 | R21: =INDEX(Steuern!$D$67:$AQ$67,5) -> -3060.0814 | S21: =INDEX(Steuern!$D$67:$AQ$67,10) -> -815.04503 | T21: =INDEX(Steuern!$D$67:$AQ$67,15) -> 801.31148 | U21: =INDEX(Steuern!$D$67:$AQ$67,20) -> 3765.6944 | V21: =INDEX(Steuern!$D$67:$AQ$67,25) -> 7263.9623 | W21: =INDEX(Steuern!$D$67:$AQ$67,30) -> 11407.16 | X21: =INDEX(Steuern!$D$67:$AQ$67,40) -> 16844.351
B22: + Maßnahmen Jahr 1 | C22: =Investition_J1 -> 12000 | F22: RENDITE, ANNAHMEN UND BREAK-EVEN | J22: Kapitaldienst pro Monat (Jahr 1) | K22: =INDEX(Finanzierung!$D$40:$AQ$40,1) -> 1166.6667 | N22: Steuer (+ Zahlung / – Erstattung) | O22: =INDEX(Projektion!$D$35:$AQ$35,1) -> -8510.3965 | P22: =INDEX(Projektion!$D$35:$AQ$35,2) -> -1973.6765 | Q22: =INDEX(Projektion!$D$35:$AQ$35,3) -> -1792.6866 | R22: =INDEX(Projektion!$D$35:$AQ$35,5) -> -1415.5569 | S22: =INDEX(Projektion!$D$35:$AQ$35,10) -> -377.03005 | T22: =INDEX(Projektion!$D$35:$AQ$35,15) -> 370.67708 | U22: =INDEX(Projektion!$D$35:$AQ$35,20) -> 1741.965 | V22: =INDEX(Projektion!$D$35:$AQ$35,25) -> 3360.2218 | W22: =INDEX(Projektion!$D$35:$AQ$35,30) -> 5276.8151 | X22: =INDEX(Projektion!$D$35:$AQ$35,40) -> 7791.9947
B23: = Gesamtinvestition | C23: =Gesamtinvestition -> 328974.5 | F23: Bruttomietrendite (Jahresmiete / Kaufpreis) | G23: =Bruttomietrendite -> 0.04 | J23: Kapitaldienst pro Jahr (Jahr 1) | K23: =INDEX(Finanzierung!$D$37:$AQ$37,1) -> 14000 | N23: Cashflow nach Steuern | O23: =INDEX(Projektion!$D$36:$AQ$36,1) -> 3078.3965 | P23: =INDEX(Projektion!$D$36:$AQ$36,2) -> -3286.9635 | Q23: =INDEX(Projektion!$D$36:$AQ$36,3) -> -3293.1662 | R23: =INDEX(Projektion!$D$36:$AQ$36,5) -> -3310.1643 | S23: =INDEX(Projektion!$D$36:$AQ$36,10) -> -3383.4168 | T23: =INDEX(Projektion!$D$36:$AQ$36,15) -> -3065.383 | U23: =INDEX(Projektion!$D$36:$AQ$36,20) -> -3260.0069 | V23: =INDEX(Projektion!$D$36:$AQ$36,25) -> -3579.1315 | W23: =INDEX(Projektion!$D$36:$AQ$36,30) -> -4061.3778 | X23: =INDEX(Projektion!$D$36:$AQ$36,40) -> 10755.539
F24: Nettomietrendite (NOI / Gesamtinvestition) | G24: =IF(Gesamtinvestition>0,NOI_J1/Gesamtinvestition,0) -> 0.026044572 | J24: Kapitaldienstdeckung (DSCR) | K24: =IF(Kapitaldienst_J1>0,NOI_J1/Kapitaldienst_J1,0) -> 0.612 | N24: Cashflow nach Steuern pro Monat | O24: =INDEX(Projektion!$D$37:$AQ$37,1) -> 256.53305 | P24: =INDEX(Projektion!$D$37:$AQ$37,2) -> -273.91362 | Q24: =INDEX(Projektion!$D$37:$AQ$37,3) -> -274.43052 | R24: =INDEX(Projektion!$D$37:$AQ$37,5) -> -275.84703 | S24: =INDEX(Projektion!$D$37:$AQ$37,10) -> -281.9514 | T24: =INDEX(Projektion!$D$37:$AQ$37,15) -> -255.44859 | U24: =INDEX(Projektion!$D$37:$AQ$37,20) -> -271.66724 | V24: =INDEX(Projektion!$D$37:$AQ$37,25) -> -298.26095 | W24: =INDEX(Projektion!$D$37:$AQ$37,30) -> -338.44815 | X24: =INDEX(Projektion!$D$37:$AQ$37,40) -> 896.29488
B25: KAUFPREISAUFTEILUNG (AfA-BEMESSUNGSGRUNDLAGE) | F25: Kaufpreisfaktor (Kaufpreis / Jahresmiete) | G25: =Kaufpreisfaktor -> 25 | J25: Restschuld nach Zinsbindung (Darlehen I) | K25: =IFERROR(INDEX(Finanzierung!$D$19:$AQ$19,MIN(Zinsbindung_I,40)),0) -> 191071.23 | N25: Kumulierter Cashflow nach Steuern | O25: =INDEX(Projektion!$D$38:$AQ$38,1) -> 3078.3965 | P25: =INDEX(Projektion!$D$38:$AQ$38,2) -> -208.56691 | Q25: =INDEX(Projektion!$D$38:$AQ$38,3) -> -3501.7331 | R25: =INDEX(Projektion!$D$38:$AQ$38,5) -> -10112.771 | S25: =INDEX(Projektion!$D$38:$AQ$38,10) -> -26864.422 | T25: =INDEX(Projektion!$D$38:$AQ$38,15) -> -41957.864 | U25: =INDEX(Projektion!$D$38:$AQ$38,20) -> -57825.467 | V25: =INDEX(Projektion!$D$38:$AQ$38,25) -> -75026.027 | W25: =INDEX(Projektion!$D$38:$AQ$38,30) -> -94294.231 | X25: =INDEX(Projektion!$D$38:$AQ$38,40) -> -16195.544
B26: Bodenanteil am Kaufpreis | C26: =1-Gebaeudeanteil_Pct -> 0.19708029 | F26: Mietsteigerung · Kosten · Wert p. a. | G26: =FIXED(Mietsteigerung*100,1)&" % · "&FIXED(Kostensteigerung*100,1)&" % · "&FIXED(Wertsteigerung*100,1)&" %" -> 2.0 % · 2.0 % · 2.0 % | J26: Volltilgung (Restschuld = 0) | K26: =IF(Darlehen_Summe<=0,"kein Darlehen",IFERROR("Jahr "&MATCH(0,Finanzierung!$D$38:$AQ$38,0)&" ("&(YEAR(Kaufdatum)+MATCH(0,Finanzierung!$D$38:$AQ$38,0)-1)&")","nach > 40 Jahren")) -> Jahr 32 (2057) | N26: Restschuld Jahresende | O26: =INDEX(Projektion!$D$42:$AQ$42,1) -> 245000 | P26: =INDEX(Projektion!$D$42:$AQ$42,2) -> 239820 | Q26: =INDEX(Projektion!$D$42:$AQ$42,3) -> 234453.52 | R26: =INDEX(Projektion!$D$42:$AQ$42,5) -> 223134.03 | S26: =INDEX(Projektion!$D$42:$AQ$42,10) -> 191071.23 | T26: =INDEX(Projektion!$D$42:$AQ$42,15) -> 161519.58 | U26: =INDEX(Projektion!$D$42:$AQ$42,20) -> 124692.85 | V26: =INDEX(Projektion!$D$42:$AQ$42,25) -> 78800.037 | W26: =INDEX(Projektion!$D$42:$AQ$42,30) -> 21609.246 | X26: =INDEX(Projektion!$D$42:$AQ$42,40) -> 0
B27: AK Grund und Boden (inkl. Nebenkosten) | C27: =AK_Boden -> 59956.653 | F27: Mietausfallwagnis · Leerstand Jahr 1 | G27: =FIXED(Mietausfall_Pct*100,1)&" % · "&Leerstand_Monate&" Monate" -> 3.0 % · 0 Monate | J27: Anschlusszins +1 %-Pkt. kostet p. a. | K27: =Restschuld_ZB_I*0.01 -> 1910.7123 | N27: Immobilienwert Jahresende | O27: =INDEX(Projektion!$D$41:$AQ$41,1) -> 302940 | P27: =INDEX(Projektion!$D$41:$AQ$41,2) -> 308998.8 | Q27: =INDEX(Projektion!$D$41:$AQ$41,3) -> 315178.78 | R27: =INDEX(Projektion!$D$41:$AQ$41,5) -> 327912 | S27: =INDEX(Projektion!$D$41:$AQ$41,10) -> 362041.34 | T27: =INDEX(Projektion!$D$41:$AQ$41,15) -> 399722.9 | U27: =INDEX(Projektion!$D$41:$AQ$41,20) -> 441326.38 | V27: =INDEX(Projektion!$D$41:$AQ$41,25) -> 487259.98 | W27: =INDEX(Projektion!$D$41:$AQ$41,30) -> 537974.39 | X27: =INDEX(Projektion!$D$41:$AQ$41,40) -> 655787.78
B28: = AfA-Basis Gebäude (inkl. Nebenkosten) | C28: =AK_Gebaeude -> 244267.85 | F28: Eigenkapitalrendite Jahr 1 | G28: =EKR_Tile -> 0.17750535 | J28: Zinsbindung Darlehen I | K28: =Zinsbindung_I -> 10 | N28: Nettovermögen (Wert – Restschuld) | O28: =INDEX(Projektion!$D$43:$AQ$43,1) -> 57940 | P28: =INDEX(Projektion!$D$43:$AQ$43,2) -> 69178.8 | Q28: =INDEX(Projektion!$D$43:$AQ$43,3) -> 80725.256 | R28: =INDEX(Projektion!$D$43:$AQ$43,5) -> 104777.97 | S28: =INDEX(Projektion!$D$43:$AQ$43,10) -> 170970.11 | T28: =INDEX(Projektion!$D$43:$AQ$43,15) -> 238203.32 | U28: =INDEX(Projektion!$D$43:$AQ$43,20) -> 316633.53 | V28: =INDEX(Projektion!$D$43:$AQ$43,25) -> 408459.94 | W28: =INDEX(Projektion!$D$43:$AQ$43,30) -> 516365.14 | X28: =INDEX(Projektion!$D$43:$AQ$43,40) -> 655787.78
B29: Bewegliche Gegenstände (eigene AfA) | C29: =KP_bewegl -> 8000 | F29: Break-even-Miete v. St. / Monat | G29: =BE_Miete_vSt -> 1416.6667 | J29: Anschlusszins nach Zinsbindung (Annahme) | K29: =Anschlusszins_I -> 0.045 | N29: Eigenkapitalrendite im Jahr | O29: =INDEX(Projektion!$D$45:$AQ$45,1) -> 0.17750535 | P29: =INDEX(Projektion!$D$45:$AQ$45,2) -> 0.10068866 | Q29: =INDEX(Projektion!$D$45:$AQ$45,3) -> 0.10450576 | R29: =INDEX(Projektion!$D$45:$AQ$45,5) -> 0.11243255 | S29: =INDEX(Projektion!$D$45:$AQ$45,10) -> 0.13408639 | T29: =INDEX(Projektion!$D$45:$AQ$45,15) -> 0.14199598 | U29: =INDEX(Projektion!$D$45:$AQ$45,20) -> 0.16994134 | V29: =INDEX(Projektion!$D$45:$AQ$45,25) -> 0.20232875 | W29: =INDEX(Projektion!$D$45:$AQ$45,30) -> 0.23999806 | X29: =INDEX(Projektion!$D$45:$AQ$45,40) -> 0.29900946
B30: Erhaltungsrücklage (nicht abschreibbar) | C30: =Ruecklage_mitverkauft -> 3000 | F30: Break-even-Miete n. St. / Monat | G30: =BE_Miete_nSt -> 457.8877 | J30: Anfängliche Tilgung Darlehen I | K30: =Tilgung_I -> 0.02 | N30: Alle Werte in € p. a.; Jahr 1 = 12 Monate ab Kaufdatum. Vollständige Reihen: Blätter Projektion / Steuern.
B32: Cashflow Jahr 1 | D32: Projektion › | F32: Steuern & AfA Jahr 1 | H32: Steuern › | J32: Exit-Szenario nach Haltedauer | L32: Sensitivität ›
C35: PRO MONAT | D35: PRO JAHR | F35: Rechtsform | G35: =CHOOSE(Rechtsform_Idx,"Privat","vv-GmbH","GmbH") -> Privat | J35: Verkauf nach | K35: =Haltedauer -> 12
B36: Nettokaltmiete Ist | C36: =INDEX(Projektion!$D$15:$AQ$15,1)/12 -> 921.5 | D36: =INDEX(Projektion!$D$15:$AQ$15,1) -> 11058 | F36: Steuersatz angewendet (Jahr 1) | G36: =INDEX(Steuern!$D$72:$AQ$72,1) -> 0.462588 | J36: Verkaufspreis (Prognose bzw. Eingabe) | K36: =Exit_VP -> 376667.81
B37: – Bewirtschaftungskosten (inkl. Rücklagen) | C37: =INDEX(Projektion!$D$26:$AQ$26,1)/12 -> 207.5 | D37: =INDEX(Projektion!$D$26:$AQ$26,1) -> 2490 | F37: AfA-Methode angewendet | G37: =CHOOSE(Methode_eff,"Automatisch nach Baujahr","Linear 2,0 %","Linear 2,5 %","Linear 3,0 %","Degressiv 5 %","Gutachten (RND)") -> Automatisch nach Baujahr | J37: – Verkaufskosten | K37: =Exit_VK -> 7533.3563
B38: = Einnahmenüberschuss (NOI) | C38: =INDEX(Projektion!$D$29:$AQ$29,1)/12 -> 714 | D38: =INDEX(Projektion!$D$29:$AQ$29,1) -> 8568 | F38: Reguläre Gebäude-AfA Jahr 1 | G38: =INDEX(Steuern!$D$49:$AQ$49,1) -> 4885.3569 | J38: – Restschuld (Ablösung) | K38: =Exit_Restschuld -> 180024.56
B39: – Zinsen | C39: =INDEX(Projektion!$D$30:$AQ$30,1)/12 -> 750 | D39: =INDEX(Projektion!$D$30:$AQ$30,1) -> 9000 | F39: + Sonder-AfA § 7b Jahr 1 | G39: =INDEX(Steuern!$D$50:$AQ$50,1) -> 0 | J39: Veräußerungsgewinn (steuerlich) | K39: =Exit_Gewinn -> 120534.24
B40: – Tilgung | C40: =INDEX(Projektion!$D$31:$AQ$31,1)/12 -> 416.66667 | D40: =INDEX(Projektion!$D$31:$AQ$31,1) -> 5000 | F40: + Erhöhte Absetzungen § 7h/7i Jahr 1 | G40: =INDEX(Steuern!$D$54:$AQ$54,1) -> 0 | J40: Steuerpflichtig? | K40: =IF(Exit_steuerpflichtig=1,IF(Rechtsform_Idx=1,"Ja (§ 23 EStG)","Ja (GmbH)"),"Nein (steuerfrei)") -> Nein (steuerfrei)
B41: = Cashflow vor Steuern | C41: =INDEX(Projektion!$D$33:$AQ$33,1)/12 -> -452.66667 | D41: =INDEX(Projektion!$D$33:$AQ$33,1) -> -5432 | F41: + AfA bewegliche Gegenstände | G41: =INDEX(Steuern!$D$55:$AQ$55,1) -> 800 | J41: – Steuer auf Veräußerungsgewinn | K41: =Exit_Steuer -> 0
B42: ± Steuerwirkung (Cash-Sicht) | C42: =INDEX(Projektion!$D$35:$AQ$35,1)/12 -> -709.19971 | D42: =INDEX(Projektion!$D$35:$AQ$35,1) -> -8510.3965 | F42: = Abschreibungen gesamt Jahr 1 | G42: =INDEX(Steuern!$D$56:$AQ$56,1) -> 5685.3569 | J42: = Nettoerlös nach Steuern und Ablösung | K42: =Exit_Netto -> 189109.9
B43: = Cashflow nach Steuern | C43: =INDEX(Projektion!$D$36:$AQ$36,1)/12 -> 256.53305 | D43: =INDEX(Projektion!$D$36:$AQ$36,1) -> 3078.3965 | F43: Erhaltungsaufwand sofort abziehbar Jahr 1 | G43: =INDEX(Steuern!$D$64:$AQ$64,1) -> 12000 | J43: + Kumulierter Cashflow n. St. bis Verkauf | K43: =Exit_CF_kum -> -32838.531
B44: nachrichtlich: Warmmiete | C44: =INDEX(Projektion!$D$17:$AQ$17,1)/12 -> 1141.5 | D44: =INDEX(Projektion!$D$17:$AQ$17,1) -> 13698 | F44: Aktivierte Herstellungskosten Jahr 1 | G44: =INDEX(Steuern!$D$45:$AQ$45,1) -> 0 | J44: – Eingesetztes Eigenkapital | K44: =Eigenkapital -> 78974.5
B45: AUSBLICK FOLGEJAHR (JAHR 2) | F45: = Steuerliches Ergebnis Jahr 1 | G45: =INDEX(Steuern!$D$67:$AQ$67,1) -> -18397.357 | J45: = Gesamtertrag nach Steuern | K45: =Gesamtertrag -> 77296.866
B46: Cashflow vor Steuern Jahr 2 | C46: =INDEX(Projektion!$D$33:$AQ$33,2)/12 -> -438.38667 | D46: =INDEX(Projektion!$D$33:$AQ$33,2) -> -5260.64 | F46: = Steuerwirkung Jahr 1 | G46: =INDEX(Steuern!$D$73:$AQ$73,1) -> -8510.3965 | J46: Eigenkapital-Multiple | K46: =EK_Multiple -> 1.9787573
B47: Cashflow nach Steuern Jahr 2 | C47: =INDEX(Projektion!$D$36:$AQ$36,2)/12 -> -273.91362 | D47: =INDEX(Projektion!$D$36:$AQ$36,2) -> -3286.9635 | F47: Steuereffekt gewählte AfA vs. Standard (10 J.) | G47: =Steuereffekt_10J -> 0 | J47: = Eigenkapitalrendite p. a. (IRR n. St.) | K47: =EK_IRR -> 0.053273956
B49: Prüfhinweise & steuerliche Einordnung | J49: =IF(COUNTIF($AB$50:$AB$74,"⚠*")=0,"",COUNTIF($AB$50:$AB$74,"⚠*")&IF(COUNTIF($AB$50:$AB$74,"⚠*")=1," Warnung"," Warnungen")) -> 1 Warnung | K49: =IF(COUNT($AC$50:$AC$74)=0,"keine Hinweise",IF(COUNTIF($AB$50:$AB$74,"ℹ*")=0,"",IF(COUNTIF($AB$50:$AB$74,"⚠*")>0," · ","")&COUNTIF($AB$50:$AB$74,"ℹ*")&IF(COUNTIF($AB$50:$AB$74,"ℹ*")=1," Hinweis"," Hinweise"))) -> · 3 Hinweise | L49: ↑ Übersicht
B50: =IFERROR(SUBSTITUTE(SUBSTITUTE(SUBSTITUTE(SUBSTITUTE(INDEX($AB$50:$AB$74,SMALL($AC$50:$AC$74,1)),"(-","(−"),"⚠","▲",1),"ℹ","ⓘ",1)," – Banken erwarten meist ≥ 1,1 bis 1,2","× – "&"Ziel ≥ "&FIXED(Ampel_DSCR_gruen,2)&"×"),"") -> ▲ Kapitaldienstdeckung (DSCR) im Jahr 1 nur 0.61× – Ziel ≥ 1.20× (NOI / Kapitaldienst). | AB50: =IF(AND(AfA_Idx=5,Methode_eff<>5),"⚠ Degressive AfA gewählt, aber nicht anwendbar (Fertigstellung vor 2023 oder Gewerbeeinheit) – es wird linear nach Baujahr abgeschrieben.","") | AC50: =IF(AB50<>"",1,"")
B51: =IFERROR(SUBSTITUTE(SUBSTITUTE(SUBSTITUTE(SUBSTITUTE(INDEX($AB$50:$AB$74,SMALL($AC$50:$AC$74,2)),"(-","(−"),"⚠","▲",1),"ℹ","ⓘ",1)," – Banken erwarten meist ≥ 1,1 bis 1,2","× – "&"Ziel ≥ "&FIXED(Ampel_DSCR_gruen,2)&"×"),"") -> ⓘ Zinsbindung Darlehen I endet nach 10 Jahren bei einer Restschuld von 191,071 € – Anschlusszins 4.50 % angenommen; jeder Prozentpunkt mehr kostet 1,911 € p. a. | AB51: =IF(AND(AfA_Idx=6,N(RND_Gutachten)<=0),"⚠ AfA nach Gutachten gewählt, aber keine Restnutzungsdauer eingegeben – Fallback auf lineare AfA nach Baujahr.","") | AC51: =IF(AB51<>"",2,"")
B52: =IFERROR(SUBSTITUTE(SUBSTITUTE(SUBSTITUTE(SUBSTITUTE(INDEX($AB$50:$AB$74,SMALL($AC$50:$AC$74,3)),"(-","(−"),"⚠","▲",1),"ℹ","ⓘ",1)," – Banken erwarten meist ≥ 1,1 bis 1,2","× – "&"Ziel ≥ "&FIXED(Ampel_DSCR_gruen,2)&"×"),"") -> ⓘ Steuerliches Ergebnis Jahr 1 negativ (−18,397 €) – Verlust wird mit anderen Einkünften verrechnet (Erstattung 8,510 €). Einkünfteerzielungsabsicht / Totalüberschussprognose beachten. | AB52: =IF(AND(SonderAfA_7b="Ja",SonderAfA_aktiv=0),"⚠ Sonder-AfA § 7b nicht anwendbar: Fertigstellung vor 2023, Gewerbeeinheit oder Anschaffungskosten über "&FIXED(Grenze_7b_Baukosten,0)&" €/m² (aktuell "&FIXED(Baukosten_qm,0)&" €/m²).","") | AC52: =IF(AB52<>"",3,"")
B53: =IFERROR(SUBSTITUTE(SUBSTITUTE(SUBSTITUTE(SUBSTITUTE(INDEX($AB$50:$AB$74,SMALL($AC$50:$AC$74,4)),"(-","(−"),"⚠","▲",1),"ℹ","ⓘ",1)," – Banken erwarten meist ≥ 1,1 bis 1,2","× – "&"Ziel ≥ "&FIXED(Ampel_DSCR_gruen,2)&"×"),"") -> ⓘ Bewegliche Gegenstände (8,000 €) sind grunderwerbsteuerfrei und werden über 10 Jahre gesondert abgeschrieben – im Kaufvertrag gesondert und angemessen ausweisen. | AB53: =IF(AND(SonderAfA_aktiv=1,Baukosten_qm>Grenze_7b_BMG),"ℹ § 7b: Bemessungsgrundlage auf "&FIXED(Grenze_7b_BMG,0)&" €/m² Wohnfläche gedeckelt ("&FIXED(SonderAfA_BMG,0)&" €). EH 40 / QNG-Nachweis erforderlich.","") | AC53: =IF(AB53<>"",4,"")
B54: =IFERROR(SUBSTITUTE(SUBSTITUTE(SUBSTITUTE(SUBSTITUTE(INDEX($AB$50:$AB$74,SMALL($AC$50:$AC$74,5)),"(-","(−"),"⚠","▲",1),"ℹ","ⓘ",1)," – Banken erwarten meist ≥ 1,1 bis 1,2","× – "&"Ziel ≥ "&FIXED(Ampel_DSCR_gruen,2)&"×"),"") | AB54: =IF(AND(SonderAfA_aktiv=1,Baukosten_qm<=Grenze_7b_BMG),"ℹ § 7b aktiv: 5 % p. a. auf "&FIXED(SonderAfA_BMG,0)&" € in den Jahren 1–4; danach Restwert-AfA (§ 7a Abs. 9 EStG). EH 40 / QNG-Nachweis erforderlich.","") | AC54: =IF(AB54<>"",5,"")
B55: =IF(COUNT($AC$50:$AC$74)>6,"+ "&(COUNT($AC$50:$AC$74)-5)&" weitere Hinweise – Eingaben im Leitfaden (S01–S12) prüfen",IFERROR(SUBSTITUTE(SUBSTITUTE(SUBSTITUTE(SUBSTITUTE(INDEX($AB$50:$AB$74,SMALL($AC$50:$AC$74,6)),"(-","(−"),"⚠","▲",1),"ℹ","ⓘ",1)," – Banken erwarten meist ≥ 1,1 bis 1,2","× – "&"Ziel ≥ "&FIXED(Ampel_DSCR_gruen,2)&"×"),"")) | AB55: =IF(AND(Reno_Idx=1,Reno_Netto>Grenze_15),"⚠ Anschaffungsnahe Herstellungskosten (§ 6 Abs. 1 Nr. 1a EStG): Maßnahmen netto "&FIXED(Reno_Netto,0)&" € übersteigen 15 % der Gebäude-AK ("&FIXED(Grenze_15,0)&" €) – kein Sofortabzug, Aktivierung und AfA.",IF(AND(Reno_Idx=1,Reno_Netto>0.8*Grenze_15),"ℹ Maßnahmen ("&FIXED(Reno_Netto,0)&" € netto) liegen nahe der 15 %-Grenze ("&FIXED(Grenze_15,0)&" €) – weitere Instandsetzungen in den ersten 3 Jahren können die Aktivierung auslösen.","")) | AC55: =IF(AB55<>"",6,"")
AB56: =IF(AND(Reno_Idx=2,Reno_Netto>Grenze_15),"⚠ Sofortabzug manuell gewählt, obwohl die 15 %-Grenze überschritten ist ("&FIXED(Reno_Netto,0)&" € > "&FIXED(Grenze_15,0)&" €) – steuerlich riskant, Finanzamt wird aktivieren.","") | AC56: =IF(AB56<>"",7,"")
B57: Diagramme | K57: Alle Diagramme › | L57: ↑ Übersicht | AB57: =IF(AND(Denkmal="Ja",N(Sanierungskosten_7i)<=0),"⚠ Erhöhte Absetzungen § 7h/7i gewählt, aber keine bescheinigten Sanierungskosten eingegeben.","") | AC57: =IF(AB57<>"",8,"")
AB58: =IF(AND(Rechtsform_Idx=1,Haltedauer<=Frist_23),"⚠ Verkauf innerhalb der 10-Jahres-Frist (§ 23 EStG): Veräußerungsgewinn "&FIXED(Exit_Gewinn,0)&" € steuerpflichtig, Steuer ca. "&FIXED(Exit_Steuer,0)&" €. Haltedauer > 10 Jahre prüfen.","") | AC58: =IF(AB58<>"",9,"")
AB59: =IF(INDEX(Projektion!$D$36:$AQ$36,1)<0,"⚠ Negativer Cashflow nach Steuern im Jahr 1: "&FIXED(INDEX(Projektion!$D$37:$AQ$37,1),0)&" € pro Monat – laufende Liquidität aus anderen Einkünften sicherstellen.","") | AC59: =IF(AB59<>"",10,"")
AB60: =IF(AND(Kapitaldienst_J1>0,DSCR_J1<1.1),"⚠ Kapitaldienstdeckung (DSCR) im Jahr 1 nur "&FIXED(DSCR_J1,2)&" – Banken erwarten meist ≥ 1,1 bis 1,2 (NOI / Kapitaldienst).","") -> ⚠ Kapitaldienstdeckung (DSCR) im Jahr 1 nur 0.61 – Banken erwarten meist ≥ 1,1 bis 1,2 (NOI / Kapitaldienst). | AC60: =IF(AB60<>"",11,"") -> 11
AB61: =IF(AND(Darlehen_I>0,Zinsbindung_I<Haltedauer),"ℹ Zinsbindung Darlehen I endet nach "&Zinsbindung_I&" Jahren bei einer Restschuld von "&FIXED(Restschuld_ZB_I,0)&" € – Anschlusszins "&FIXED(Anschlusszins_I*100,2)&" % angenommen; jeder Prozentpunkt mehr kostet "&FIXED(Restschuld_ZB_I*0.01,0)&" € p. a.","") -> ℹ Zinsbindung Darlehen I endet nach 10 Jahren bei einer Restschuld von 191,071 € – Anschlusszins 4.50 % angenommen; jeder Prozentpunkt mehr kostet 1,911 € p. a. | AC61: =IF(AB61<>"",12,"") -> 12
AB62: =IF(Beleihung>1,"ℹ Beleihungsauslauf über 100 % (Kaufnebenkosten mitfinanziert) – Bank verlangt i. d. R. Zusatzsicherheiten oder Zinsaufschlag.","") | AC62: =IF(AB62<>"",13,"")
AB63: =IF(AND(Rechtsform_Idx=1,Verlust_Idx=1,INDEX(Steuern!$D$67:$AQ$67,1)<0),"ℹ Steuerliches Ergebnis Jahr 1 negativ ("&FIXED(INDEX(Steuern!$D$67:$AQ$67,1),0)&" €) – Verlust wird mit anderen Einkünften verrechnet (Erstattung "&FIXED(-INDEX(Steuern!$D$73:$AQ$73,1),0)&" €). Einkünfteerzielungsabsicht / Totalüberschussprognose beachten.","") -> ℹ Steuerliches Ergebnis Jahr 1 negativ (-18,397 €) – Verlust wird mit anderen Einkünften verrechnet (Erstattung 8,510 €). Einkünfteerzielungsabsicht / Totalüberschussprognose beachten. | AC63: =IF(AB63<>"",14,"") -> 14
AB64: =IF(Rechtsform_Idx=3,"ℹ Gewerbliche GmbH: Gewerbesteuer "&FIXED(GewSt_Satz*100,2)&" % zusätzlich zur KSt eingerechnet. Erweiterte Kürzung (§ 9 Nr. 1 S. 2 GewStG) nur bei ausschließlicher Verwaltung eigenen Grundbesitzes.","") | AC64: =IF(AB64<>"",15,"")
AB65: =IF(Rechtsform_Idx>1,"ℹ GmbH: Ausschüttungen an Gesellschafter werden zusätzlich mit Abgeltungsteuer (26,375 %) bzw. im Teileinkünfteverfahren belastet – nicht im Cashflow enthalten. Verkauf ist unabhängig von der Haltedauer steuerpflichtig.","") | AC65: =IF(AB65<>"",16,"")
AB66: =IF(KP_bewegl>0,"ℹ Bewegliche Gegenstände ("&FIXED(KP_bewegl,0)&" €) sind grunderwerbsteuerfrei und werden über "&ND_bewegl&" Jahre gesondert abgeschrieben – im Kaufvertrag gesondert und angemessen ausweisen.","") -> ℹ Bewegliche Gegenstände (8,000 €) sind grunderwerbsteuerfrei und werden über 10 Jahre gesondert abgeschrieben – im Kaufvertrag gesondert und angemessen ausweisen. | AC66: =IF(AB66<>"",17,"") -> 17
AB67: =IF(AND(Rechtsform_Idx=1,Verteilung_eff>1,HK_Flag=0),"ℹ Größerer Erhaltungsaufwand wird gleichmäßig auf "&Verteilung_eff&" Jahre verteilt (§ 82b EStDV) – sinnvoll bei schwankender Progression.","") | AC67: =IF(AB67<>"",18,"")
AB68: =IF(AND(Disagio_Pct>0,Disagio_sofort=0),"ℹ Disagio ("&FIXED(Disagio_Betrag,0)&" €) übersteigt 5 % oder Zinsbindung < 5 Jahre – Verteilung über die Zinsbindung statt Sofortabzug.","") | AC68: =IF(AB68<>"",19,"")
AB69: =IF(AND(Objektart_Idx=4,Rechtsform_Idx=1),"ℹ Gewerbeeinheit im Privatvermögen: AfA linear nach Baujahr (2 % / 2,5 % / 3 %); Option zur Umsatzsteuer (§ 9 UStG) bei gewerblichen Mietern prüfen – nicht modelliert.","") | AC69: =IF(AB69<>"",20,"")
AB70: =IF(Hausgeld_nicht_umlagefaehig>Hausgeld,"⚠ Eingabeprüfung: Der nicht umlagefähige Anteil übersteigt das gesamte Hausgeld – bitte Schritt 06 prüfen.","") | AC70: =IF(AB70<>"",21,"")
AB71: =IF(Hausgeld_Ruecklage>Hausgeld_nicht_umlagefaehig,"⚠ Eingabeprüfung: Die Rücklagenzuführung übersteigt den nicht umlagefähigen Hausgeldanteil – bitte Schritt 06 prüfen.","") | AC71: =IF(AB71<>"",22,"")
AB72: =IF(KP_bewegl+Ruecklage_mitverkauft>=Kaufpreis*0.5,"⚠ Eingabeprüfung: Bewegliche Gegenstände und Rücklagenanteil sind unplausibel hoch im Verhältnis zum Kaufpreis – bitte Schritt 02 prüfen.","") | AC72: =IF(AB72<>"",23,"")
AB73: =IF(Darlehen_Summe>Gesamtinvestition,"⚠ Eingabeprüfung: Die Darlehenssumme übersteigt die Gesamtinvestition (negatives Eigenkapital) – bitte Schritt 07 bzw. Blatt Eingaben prüfen.","") | AC73: =IF(AB73<>"",24,"")
AB74: =IF(AND(Rechtsform_Idx=1,Grenzsteuersatz_Tarif=0,NOT(ISNUMBER(Grenzsteuersatz_Override))),"ℹ Grenzsteuersatz 0 %: Das zu versteuernde Einkommen liegt unter dem Grundfreibetrag – Steuereffekte des Objekts werden nicht wirksam. Ggf. Grenzsteuersatz manuell setzen (Schritt 09).","") | AC74: =IF(AB74<>"",25,"")
B75: Keine Gewähr für die Richtigkeit der Angaben · ersetzt keine Rechts-, Steuer- oder Finanzberatung · Rechtsstand September 2026
B76: MM Holding GmbH · Kornhausgasse 4 · 88250 Weingarten · Amtsgericht Ulm HRB 750729

Sheet Diagramme
B5: DIAGRAMME | P5: ‹ Start
B6: Diagramme | P6: =Obj_Name -> Beispiel: 3-Zimmer-Eigentumswohnung
B7: Alle Auswertungen als Grafik – aktualisieren sich automatisch aus den Eingaben (Datenbasis: Projektion, Finanzierung, Steuern). | P7: =IF(Erstellt_fuer="","","Erstellt für "&Erstellt_fuer) -> Erstellt für Max Mustermann
B9: Investition, Finanzierung und Kaufpreisaufteilung · Zeitpunkt Kauf · Anteile | P9: ↑ Übersicht
B30: Einnahmen, Ausgaben und Cashflow · Jahr 1 · Jahre 1–30 | P30: ↑ Übersicht
B51: Entwicklung von Vermögen, Darlehen und Cashflow · Jahre 1–35 · Jahresende | P51: ↑ Übersicht
I69: =IF(MAX(D181:AL181)>0,"","Kein zweites Darlehen – dargestellt ist Darlehen I") -> Kein zweites Darlehen – dargestellt ist Darlehen I
B92: Steuern und Abschreibung · Jahre 1–20 · T€ p. a. | P92: ↑ Übersicht
B110: =IF(SUM(D203:W203)>0,"","Keine Sonder-AfA (§ 7b, § 7h/7i) im Modell") -> Keine Sonder-AfA (§ 7b, § 7h/7i) im Modell
B113: Exit – Verkauf nach der geplanten Haltedauer · Verkaufsjahr aus Schritt 11 | P113: ↑ Übersicht
B138: Diagrammdaten · Anhang eingeklappt – über [+] am linken Rand öffnen · bitte nicht ändern | P138: ↑ Übersicht
B140: Gesamtinvestition | C140: Betrag (€) | F140: Haushalt (Diagramm) | G140: Wert | H140: Sortier | I140: Objekt | J140: Rang | K140: Position | L140: Label | M140: Bestand | N140: Objekt neu | P140: Vermögen (Diagramm) | Q140: Wert | R140: Sortier | S140: Rang | T140: Position | U140: Label | V140: Wert sortiert | AI140: Kreise: Legende
B141: Kaufpreis | C141: =Kaufpreis -> 285000 | F141: Wohnen | G141: =N(Haushaltsrechnung!$C$31) -> 1100 | H141: =IF(G141>0,G141+(13-1)/1000,0) -> 1100.012 | I141: =IF(ISNUMBER(SEARCH("kalkulierten",Haushaltsrechnung!$B$31)),1,0) -> 0 | J141: 1 | K141: =IF(J141<=COUNTIF($G$141:$G$152,">0"),MATCH(LARGE($H$141:$H$152,J141),$H$141:$H$152,0),"") -> 11 | L141: =IF(K141="","",INDEX($F$141:$F$152,K141)) -> Kapitaldienst neu | M141: =IF(K141="",0,IF(INDEX($I$141:$I$152,K141)=1,0,INDEX($G$141:$G$152,K141))) -> 0 | N141: =IF(K141="",0,IF(INDEX($I$141:$I$152,K141)=1,INDEX($G$141:$G$152,K141),0)) -> 1166.6667 | P141: Girokonten | Q141: =N(Vermögensaufstellung!$C$10) -> 8000 | R141: =IF(Q141>0,Q141+(10-1)/1000,0) -> 8000.009 | S141: 1 | T141: =IF(S141<=COUNTIF($Q$141:$Q$149,">0"),MATCH(LARGE($R$141:$R$149,S141),$R$141:$R$149,0),"") -> 3 | U141: =IF(T141="","",INDEX($P$141:$P$149,T141)) -> Wertpapierdepot | V141: =IF(T141="",0,INDEX($Q$141:$Q$149,T141)) -> 30000 | AI141: ="Grunderwerbsteuer · "&TEXT(IFERROR(MAX(0,'S03 Kaufnebenkosten'!$D$61)/SUM('S03 Kaufnebenkosten'!$D$61:$D$65),0),"0 %") -> Grunderwerbsteuer · 46 %
B142: Kaufnebenkosten | C142: =NK_Summe -> 30224.5 | F142: Lebenshaltung | G142: =N(Haushaltsrechnung!$C$32) -> 600 | H142: =IF(G142>0,G142+(13-2)/1000,0) -> 600.011 | I142: =IF(ISNUMBER(SEARCH("kalkulierten",Haushaltsrechnung!$B$32)),1,0) -> 0 | J142: 2 | K142: =IF(J142<=COUNTIF($G$141:$G$152,">0"),MATCH(LARGE($H$141:$H$152,J142),$H$141:$H$152,0),"") -> 1 | L142: =IF(K142="","",INDEX($F$141:$F$152,K142)) -> Wohnen | M142: =IF(K142="",0,IF(INDEX($I$141:$I$152,K142)=1,0,INDEX($G$141:$G$152,K142))) -> 1100 | N142: =IF(K142="",0,IF(INDEX($I$141:$I$152,K142)=1,INDEX($G$141:$G$152,K142),0)) -> 0 | P142: Tagesgeld / Festgeld | Q142: =N(Vermögensaufstellung!$C$11) -> 25000 | R142: =IF(Q142>0,Q142+(10-2)/1000,0) -> 25000.008 | S142: 2 | T142: =IF(S142<=COUNTIF($Q$141:$Q$149,">0"),MATCH(LARGE($R$141:$R$149,S142),$R$141:$R$149,0),"") -> 2 | U142: =IF(T142="","",INDEX($P$141:$P$149,T142)) -> Tagesgeld / Festgeld | V142: =IF(T142="",0,INDEX($Q$141:$Q$149,T142)) -> 25000 | AI142: ="Notar · "&TEXT(IFERROR(MAX(0,'S03 Kaufnebenkosten'!$D$62)/SUM('S03 Kaufnebenkosten'!$D$61:$D$65),0),"0 %") -> Notar · 14 %
B143: Finanzierungsnebenkosten | C143: =FinNK_Summe -> 1750 | F143: Mobilität | G143: =N(Haushaltsrechnung!$C$33) -> 300 | H143: =IF(G143>0,G143+(13-3)/1000,0) -> 300.01 | I143: =IF(ISNUMBER(SEARCH("kalkulierten",Haushaltsrechnung!$B$33)),1,0) -> 0 | J143: 3 | K143: =IF(J143<=COUNTIF($G$141:$G$152,">0"),MATCH(LARGE($H$141:$H$152,J143),$H$141:$H$152,0),"") -> 2 | L143: =IF(K143="","",INDEX($F$141:$F$152,K143)) -> Lebenshaltung | M143: =IF(K143="",0,IF(INDEX($I$141:$I$152,K143)=1,0,INDEX($G$141:$G$152,K143))) -> 600 | N143: =IF(K143="",0,IF(INDEX($I$141:$I$152,K143)=1,INDEX($G$141:$G$152,K143),0)) -> 0 | P143: Wertpapierdepot | Q143: =N(Vermögensaufstellung!$C$12) -> 30000 | R143: =IF(Q143>0,Q143+(10-3)/1000,0) -> 30000.007 | S143: 3 | T143: =IF(S143<=COUNTIF($Q$141:$Q$149,">0"),MATCH(LARGE($R$141:$R$149,S143),$R$141:$R$149,0),"") -> 8 | U143: =IF(T143="","",INDEX($P$141:$P$149,T143)) -> Fahrzeuge | V143: =IF(T143="",0,INDEX($Q$141:$Q$149,T143)) -> 15000 | AI143: ="Grundbuch · "&TEXT(IFERROR(MAX(0,'S03 Kaufnebenkosten'!$D$63)/SUM('S03 Kaufnebenkosten'!$D$61:$D$65),0),"0 %") -> Grundbuch · 5 %
B144: Maßnahmen Jahr 1 | C144: =Investition_J1 -> 12000 | F144: Versicherungen | G144: =N(Haushaltsrechnung!$C$34) -> 150 | H144: =IF(G144>0,G144+(13-4)/1000,0) -> 150.009 | I144: =IF(ISNUMBER(SEARCH("kalkulierten",Haushaltsrechnung!$B$34)),1,0) -> 0 | J144: 4 | K144: =IF(J144<=COUNTIF($G$141:$G$152,">0"),MATCH(LARGE($H$141:$H$152,J144),$H$141:$H$152,0),"") -> 3 | L144: =IF(K144="","",INDEX($F$141:$F$152,K144)) -> Mobilität | M144: =IF(K144="",0,IF(INDEX($I$141:$I$152,K144)=1,0,INDEX($G$141:$G$152,K144))) -> 300 | N144: =IF(K144="",0,IF(INDEX($I$141:$I$152,K144)=1,INDEX($G$141:$G$152,K144),0)) -> 0 | P144: Lebens-/Rentenversicherungen | Q144: =N(Vermögensaufstellung!$C$13) -> 0 | R144: =IF(Q144>0,Q144+(10-4)/1000,0) -> 0 | S144: 4 | T144: =IF(S144<=COUNTIF($Q$141:$Q$149,">0"),MATCH(LARGE($R$141:$R$149,S144),$R$141:$R$149,0),"") -> 1 | U144: =IF(T144="","",INDEX($P$141:$P$149,T144)) -> Girokonten | V144: =IF(T144="",0,INDEX($Q$141:$Q$149,T144)) -> 8000 | AI144: ="Makler · "&TEXT(IFERROR(MAX(0,'S03 Kaufnebenkosten'!$D$64)/SUM('S03 Kaufnebenkosten'!$D$61:$D$65),0),"0 %") -> Makler · 34 %
F145: Altersvorsorge | G145: =N(Haushaltsrechnung!$C$35) -> 250 | H145: =IF(G145>0,G145+(13-5)/1000,0) -> 250.008 | I145: =IF(ISNUMBER(SEARCH("kalkulierten",Haushaltsrechnung!$B$35)),1,0) -> 0 | J145: 5 | K145: =IF(J145<=COUNTIF($G$141:$G$152,">0"),MATCH(LARGE($H$141:$H$152,J145),$H$141:$H$152,0),"") -> 6 | L145: =IF(K145="","",INDEX($F$141:$F$152,K145)) -> Freizeit | M145: =IF(K145="",0,IF(INDEX($I$141:$I$152,K145)=1,0,INDEX($G$141:$G$152,K145))) -> 300 | N145: =IF(K145="",0,IF(INDEX($I$141:$I$152,K145)=1,INDEX($G$141:$G$152,K145),0)) -> 0 | P145: Bausparverträge | Q145: =N(Vermögensaufstellung!$C$14) -> 0 | R145: =IF(Q145>0,Q145+(10-5)/1000,0) -> 0 | S145: 5 | T145: =IF(S145<=COUNTIF($Q$141:$Q$149,">0"),MATCH(LARGE($R$141:$R$149,S145),$R$141:$R$149,0),"") | U145: =IF(T145="","",INDEX($P$141:$P$149,T145)) | V145: =IF(T145="",0,INDEX($Q$141:$Q$149,T145)) -> 0 | AI145: ="Sonstige · "&TEXT(IFERROR(MAX(0,'S03 Kaufnebenkosten'!$D$65)/SUM('S03 Kaufnebenkosten'!$D$61:$D$65),0),"0 %") -> Sonstige · 2 %
B146: Finanzierungsstruktur | C146: Betrag (€) | F146: Freizeit | G146: =N(Haushaltsrechnung!$C$36) -> 300 | H146: =IF(G146>0,G146+(13-6)/1000,0) -> 300.007 | I146: =IF(ISNUMBER(SEARCH("kalkulierten",Haushaltsrechnung!$B$36)),1,0) -> 0 | J146: 6 | K146: =IF(J146<=COUNTIF($G$141:$G$152,">0"),MATCH(LARGE($H$141:$H$152,J146),$H$141:$H$152,0),"") -> 5 | L146: =IF(K146="","",INDEX($F$141:$F$152,K146)) -> Altersvorsorge | M146: =IF(K146="",0,IF(INDEX($I$141:$I$152,K146)=1,0,INDEX($G$141:$G$152,K146))) -> 250 | N146: =IF(K146="",0,IF(INDEX($I$141:$I$152,K146)=1,INDEX($G$141:$G$152,K146),0)) -> 0 | P146: Immobilien | Q146: =N(Vermögensaufstellung!$C$15) -> 0 | R146: =IF(Q146>0,Q146+(10-6)/1000,0) -> 0 | S146: 6 | T146: =IF(S146<=COUNTIF($Q$141:$Q$149,">0"),MATCH(LARGE($R$141:$R$149,S146),$R$141:$R$149,0),"") | U146: =IF(T146="","",INDEX($P$141:$P$149,T146)) | V146: =IF(T146="",0,INDEX($Q$141:$Q$149,T146)) -> 0
B147: Darlehen I | C147: =Darlehen_I -> 250000 | F147: Unterhalt | G147: =N(Haushaltsrechnung!$C$37) -> 0 | H147: =IF(G147>0,G147+(13-7)/1000,0) -> 0 | I147: =IF(ISNUMBER(SEARCH("kalkulierten",Haushaltsrechnung!$B$37)),1,0) -> 0 | J147: 7 | K147: =IF(J147<=COUNTIF($G$141:$G$152,">0"),MATCH(LARGE($H$141:$H$152,J147),$H$141:$H$152,0),"") -> 12 | L147: =IF(K147="","",INDEX($F$141:$F$152,K147)) -> Bewirtschaftung neu | M147: =IF(K147="",0,IF(INDEX($I$141:$I$152,K147)=1,0,INDEX($G$141:$G$152,K147))) -> 0 | N147: =IF(K147="",0,IF(INDEX($I$141:$I$152,K147)=1,INDEX($G$141:$G$152,K147),0)) -> 207.5 | P147: Unternehmensbeteiligungen | Q147: =N(Vermögensaufstellung!$C$16) -> 0 | R147: =IF(Q147>0,Q147+(10-7)/1000,0) -> 0 | S147: 7 | T147: =IF(S147<=COUNTIF($Q$141:$Q$149,">0"),MATCH(LARGE($R$141:$R$149,S147),$R$141:$R$149,0),"") | U147: =IF(T147="","",INDEX($P$141:$P$149,T147)) | V147: =IF(T147="",0,INDEX($Q$141:$Q$149,T147)) -> 0 | AI147: ="Boden · "&TEXT(IFERROR(MAX(0,Diagramme!$C$152)/SUM(Diagramme!$C$152:$C$155),0),"0 %") -> Boden · 19 %
B148: Darlehen II | C148: =Darlehen_II -> 0 | F148: Kredite | G148: =N(Haushaltsrechnung!$C$38) -> 0 | H148: =IF(G148>0,G148+(13-8)/1000,0) -> 0 | I148: =IF(ISNUMBER(SEARCH("kalkulierten",Haushaltsrechnung!$B$38)),1,0) -> 0 | J148: 8 | K148: =IF(J148<=COUNTIF($G$141:$G$152,">0"),MATCH(LARGE($H$141:$H$152,J148),$H$141:$H$152,0),"") -> 4 | L148: =IF(K148="","",INDEX($F$141:$F$152,K148)) -> Versicherungen | M148: =IF(K148="",0,IF(INDEX($I$141:$I$152,K148)=1,0,INDEX($G$141:$G$152,K148))) -> 150 | N148: =IF(K148="",0,IF(INDEX($I$141:$I$152,K148)=1,INDEX($G$141:$G$152,K148),0)) -> 0 | P148: Fahrzeuge | Q148: =N(Vermögensaufstellung!$C$17) -> 15000 | R148: =IF(Q148>0,Q148+(10-8)/1000,0) -> 15000.002 | S148: 8 | T148: =IF(S148<=COUNTIF($Q$141:$Q$149,">0"),MATCH(LARGE($R$141:$R$149,S148),$R$141:$R$149,0),"") | U148: =IF(T148="","",INDEX($P$141:$P$149,T148)) | V148: =IF(T148="",0,INDEX($Q$141:$Q$149,T148)) -> 0 | AI148: ="Gebäude · "&TEXT(IFERROR(MAX(0,Diagramme!$C$153)/SUM(Diagramme!$C$152:$C$155),0),"0 %") -> Gebäude · 77 %
B149: Eigenkapital | C149: =Eigenkapital -> 78974.5 | F149: Bestandsobjekte | G149: =N(Haushaltsrechnung!$C$39) -> 0 | H149: =IF(G149>0,G149+(13-9)/1000,0) -> 0 | I149: =IF(ISNUMBER(SEARCH("kalkulierten",Haushaltsrechnung!$B$39)),1,0) -> 0 | J149: 9 | K149: =IF(J149<=COUNTIF($G$141:$G$152,">0"),MATCH(LARGE($H$141:$H$152,J149),$H$141:$H$152,0),"") | L149: =IF(K149="","",INDEX($F$141:$F$152,K149)) | M149: =IF(K149="",0,IF(INDEX($I$141:$I$152,K149)=1,0,INDEX($G$141:$G$152,K149))) -> 0 | N149: =IF(K149="",0,IF(INDEX($I$141:$I$152,K149)=1,INDEX($G$141:$G$152,K149),0)) -> 0 | P149: Sonstige Vermögenswerte | Q149: =N(Vermögensaufstellung!$C$18) -> 0 | R149: =IF(Q149>0,Q149+(10-9)/1000,0) -> 0 | S149: 9 | T149: =IF(S149<=COUNTIF($Q$141:$Q$149,">0"),MATCH(LARGE($R$141:$R$149,S149),$R$141:$R$149,0),"") | U149: =IF(T149="","",INDEX($P$141:$P$149,T149)) | V149: =IF(T149="",0,INDEX($Q$141:$Q$149,T149)) -> 0 | AI149: ="Inventar · "&TEXT(IFERROR(MAX(0,Diagramme!$C$154)/SUM(Diagramme!$C$152:$C$155),0),"0 %") -> Inventar · 3 %
F150: Bestandsdarlehen | G150: =N(Haushaltsrechnung!$C$40) -> 0 | H150: =IF(G150>0,G150+(13-10)/1000,0) -> 0 | I150: =IF(ISNUMBER(SEARCH("kalkulierten",Haushaltsrechnung!$B$40)),1,0) -> 0 | J150: 10 | K150: =IF(J150<=COUNTIF($G$141:$G$152,">0"),MATCH(LARGE($H$141:$H$152,J150),$H$141:$H$152,0),"") | L150: =IF(K150="","",INDEX($F$141:$F$152,K150)) | M150: =IF(K150="",0,IF(INDEX($I$141:$I$152,K150)=1,0,INDEX($G$141:$G$152,K150))) -> 0 | N150: =IF(K150="",0,IF(INDEX($I$141:$I$152,K150)=1,INDEX($G$141:$G$152,K150),0)) -> 0 | AI150: ="Rücklage · "&TEXT(IFERROR(MAX(0,Diagramme!$C$155)/SUM(Diagramme!$C$152:$C$155),0),"0 %") -> Rücklage · 1 %
B151: Kaufpreisaufteilung | C151: Betrag (€) | F151: Kapitaldienst neu | G151: =N(Haushaltsrechnung!$C$41) -> 1166.6667 | H151: =IF(G151>0,G151+(13-11)/1000,0) -> 1166.6687 | I151: =IF(ISNUMBER(SEARCH("kalkulierten",Haushaltsrechnung!$B$41)),1,0) -> 1 | J151: 11 | K151: =IF(J151<=COUNTIF($G$141:$G$152,">0"),MATCH(LARGE($H$141:$H$152,J151),$H$141:$H$152,0),"") | L151: =IF(K151="","",INDEX($F$141:$F$152,K151)) | M151: =IF(K151="",0,IF(INDEX($I$141:$I$152,K151)=1,0,INDEX($G$141:$G$152,K151))) -> 0 | N151: =IF(K151="",0,IF(INDEX($I$141:$I$152,K151)=1,INDEX($G$141:$G$152,K151),0)) -> 0
B152: Grund und Boden | C152: =Bodenwert -> 54000 | F152: Bewirtschaftung neu | G152: =N(Haushaltsrechnung!$C$42) -> 207.5 | H152: =IF(G152>0,G152+(13-12)/1000,0) -> 207.501 | I152: =IF(ISNUMBER(SEARCH("kalkulierten",Haushaltsrechnung!$B$42)),1,0) -> 1 | J152: 12 | K152: =IF(J152<=COUNTIF($G$141:$G$152,">0"),MATCH(LARGE($H$141:$H$152,J152),$H$141:$H$152,0),"") | L152: =IF(K152="","",INDEX($F$141:$F$152,K152)) | M152: =IF(K152="",0,IF(INDEX($I$141:$I$152,K152)=1,0,INDEX($G$141:$G$152,K152))) -> 0 | N152: =IF(K152="",0,IF(INDEX($I$141:$I$152,K152)=1,INDEX($G$141:$G$152,K152),0)) -> 0 | AI152: ="Kaufpreis · "&TEXT(IFERROR(MAX(0,Diagramme!$C$141)/SUM(Diagramme!$C$141:$C$144),0),"0 %") -> Kaufpreis · 87 %
B153: Gebäude (AfA-fähig) | C153: =KP_Immobilie-Bodenwert -> 220000 | AI153: ="Nebenkosten · "&TEXT(IFERROR(MAX(0,Diagramme!$C$142)/SUM(Diagramme!$C$141:$C$144),0),"0 %") -> Nebenkosten · 9 %
B154: Bewegliche Gegenstände | C154: =KP_bewegl -> 8000 | F154: AfA je Variante (Diagramm) | G154: Modell | H154: Anwendbar | I154: Nicht anw. | AI154: ="Finanzierungskosten · "&TEXT(IFERROR(MAX(0,Diagramme!$C$143)/SUM(Diagramme!$C$141:$C$144),0),"0 %") -> Finanzierungskosten · 1 %
B155: Anteil Erhaltungsrücklage | C155: =Ruecklage_mitverkauft -> 3000 | F155: =IF('AfA-Vergleich'!$S$19="Im Modell angewendet","Im Modell",'AfA-Vergleich'!$S$19&IF(N('AfA-Vergleich'!$O$19)=0," – n. v.","")) -> Linear 2,0 % | G155: =IF('AfA-Vergleich'!$S$19="Im Modell angewendet",'AfA-Vergleich'!$O$19,0) -> 0 | H155: =IF(AND(NOT('AfA-Vergleich'!$S$19="Im Modell angewendet"),LEFT('AfA-Vergleich'!$C$19,2)="Ja"),'AfA-Vergleich'!$O$19,0) -> 48853.569 | I155: =IF(AND(NOT('AfA-Vergleich'!$S$19="Im Modell angewendet"),LEFT('AfA-Vergleich'!$C$19,2)<>"Ja"),'AfA-Vergleich'!$O$19,0) -> 0 | AI155: ="Maßnahmen · "&TEXT(IFERROR(MAX(0,Diagramme!$C$144)/SUM(Diagramme!$C$141:$C$144),0),"0 %") -> Maßnahmen · 4 %
F156: =IF('AfA-Vergleich'!$S$20="Im Modell angewendet","Im Modell",'AfA-Vergleich'!$S$20&IF(N('AfA-Vergleich'!$O$20)=0," – n. v.","")) -> Linear 2,5 % | G156: =IF('AfA-Vergleich'!$S$20="Im Modell angewendet",'AfA-Vergleich'!$O$20,0) -> 0 | H156: =IF(AND(NOT('AfA-Vergleich'!$S$20="Im Modell angewendet"),LEFT('AfA-Vergleich'!$C$20,2)="Ja"),'AfA-Vergleich'!$O$20,0) -> 0 | I156: =IF(AND(NOT('AfA-Vergleich'!$S$20="Im Modell angewendet"),LEFT('AfA-Vergleich'!$C$20,2)<>"Ja"),'AfA-Vergleich'!$O$20,0) -> 61066.962
B157: Verwendung des Verkaufserlöses | C157: Betrag (€) | F157: =IF('AfA-Vergleich'!$S$21="Im Modell angewendet","Im Modell",'AfA-Vergleich'!$S$21&IF(N('AfA-Vergleich'!$O$21)=0," – n. v.","")) -> Linear 3,0 % | G157: =IF('AfA-Vergleich'!$S$21="Im Modell angewendet",'AfA-Vergleich'!$O$21,0) -> 0 | H157: =IF(AND(NOT('AfA-Vergleich'!$S$21="Im Modell angewendet"),LEFT('AfA-Vergleich'!$C$21,2)="Ja"),'AfA-Vergleich'!$O$21,0) -> 0 | I157: =IF(AND(NOT('AfA-Vergleich'!$S$21="Im Modell angewendet"),LEFT('AfA-Vergleich'!$C$21,2)<>"Ja"),'AfA-Vergleich'!$O$21,0) -> 73280.354 | AI157: ="Hausgeld · "&TEXT(IFERROR(MAX(0,'S06 Bewirtschaftung'!$D$61)/SUM('S06 Bewirtschaftung'!$D$61:$D$66),0),"0 %") -> Hausgeld · 15 %
B158: Verkaufskosten | C158: =Exit_VK -> 7533.3563 | F158: =IF('AfA-Vergleich'!$S$22="Im Modell angewendet","Im Modell",'AfA-Vergleich'!$S$22&IF(N('AfA-Vergleich'!$O$22)=0," – n. v.","")) -> Gutachten (RND) – n. v. | G158: =IF('AfA-Vergleich'!$S$22="Im Modell angewendet",'AfA-Vergleich'!$O$22,0) -> 0 | H158: =IF(AND(NOT('AfA-Vergleich'!$S$22="Im Modell angewendet"),LEFT('AfA-Vergleich'!$C$22,2)="Ja"),'AfA-Vergleich'!$O$22,0) -> 0 | I158: =IF(AND(NOT('AfA-Vergleich'!$S$22="Im Modell angewendet"),LEFT('AfA-Vergleich'!$C$22,2)<>"Ja"),'AfA-Vergleich'!$O$22,0) -> 0 | AI158: ="Erhaltungsrücklage · "&TEXT(IFERROR(MAX(0,'S06 Bewirtschaftung'!$D$62)/SUM('S06 Bewirtschaftung'!$D$61:$D$66),0),"0 %") -> Erhaltungsrücklage · 25 %
B159: Steuer auf Veräußerungsgewinn | C159: =Exit_Steuer -> 0 | F159: =IF('AfA-Vergleich'!$S$23="Im Modell angewendet","Im Modell",'AfA-Vergleich'!$S$23&IF(N('AfA-Vergleich'!$O$23)=0," – n. v.","")) -> Degressiv 5 % | G159: =IF('AfA-Vergleich'!$S$23="Im Modell angewendet",'AfA-Vergleich'!$O$23,0) -> 0 | H159: =IF(AND(NOT('AfA-Vergleich'!$S$23="Im Modell angewendet"),LEFT('AfA-Vergleich'!$C$23,2)="Ja"),'AfA-Vergleich'!$O$23,0) -> 0 | I159: =IF(AND(NOT('AfA-Vergleich'!$S$23="Im Modell angewendet"),LEFT('AfA-Vergleich'!$C$23,2)<>"Ja"),'AfA-Vergleich'!$O$23,0) -> 98015.664 | AI159: ="Verwaltung · "&TEXT(IFERROR(MAX(0,'S06 Bewirtschaftung'!$D$63)/SUM('S06 Bewirtschaftung'!$D$61:$D$66),0),"0 %") -> Verwaltung · 11 %
B160: Ablösung Restschuld | C160: =Exit_Restschuld -> 180024.56 | F160: =IF('AfA-Vergleich'!$S$24="Im Modell angewendet","Im Modell",'AfA-Vergleich'!$S$24&IF(N('AfA-Vergleich'!$O$24)=0," – n. v.","")) -> Linear 3 % + § 7b | G160: =IF('AfA-Vergleich'!$S$24="Im Modell angewendet",'AfA-Vergleich'!$O$24,0) -> 0 | H160: =IF(AND(NOT('AfA-Vergleich'!$S$24="Im Modell angewendet"),LEFT('AfA-Vergleich'!$C$24,2)="Ja"),'AfA-Vergleich'!$O$24,0) -> 0 | I160: =IF(AND(NOT('AfA-Vergleich'!$S$24="Im Modell angewendet"),LEFT('AfA-Vergleich'!$C$24,2)<>"Ja"),'AfA-Vergleich'!$O$24,0) -> 112141.15 | AI160: ="Instandhaltung · "&TEXT(IFERROR(MAX(0,'S06 Bewirtschaftung'!$D$64)/SUM('S06 Bewirtschaftung'!$D$61:$D$66),0),"0 %") -> Instandhaltung · 26 %
B161: Nettoerlös (an Investor) | C161: =MAX(0,Exit_Netto) -> 189109.9 | F161: =IF('AfA-Vergleich'!$S$25="Im Modell angewendet","Im Modell",'AfA-Vergleich'!$S$25&IF(N('AfA-Vergleich'!$O$25)=0," – n. v.","")) -> Degressiv + § 7b | G161: =IF('AfA-Vergleich'!$S$25="Im Modell angewendet",'AfA-Vergleich'!$O$25,0) -> 0 | H161: =IF(AND(NOT('AfA-Vergleich'!$S$25="Im Modell angewendet"),LEFT('AfA-Vergleich'!$C$25,2)="Ja"),'AfA-Vergleich'!$O$25,0) -> 0 | I161: =IF(AND(NOT('AfA-Vergleich'!$S$25="Im Modell angewendet"),LEFT('AfA-Vergleich'!$C$25,2)<>"Ja"),'AfA-Vergleich'!$O$25,0) -> 131322.79 | AI161: ="Mietausfall · "&TEXT(IFERROR(MAX(0,'S06 Bewirtschaftung'!$D$65)/SUM('S06 Bewirtschaftung'!$D$61:$D$66),0),"0 %") -> Mietausfall · 12 %
F162: =IF('AfA-Vergleich'!$S$26="Im Modell angewendet","Im Modell",'AfA-Vergleich'!$S$26&IF(N('AfA-Vergleich'!$O$26)=0," – n. v.","")) -> Im Modell | G162: =IF('AfA-Vergleich'!$S$26="Im Modell angewendet",'AfA-Vergleich'!$O$26,0) -> 48853.569 | H162: =IF(AND(NOT('AfA-Vergleich'!$S$26="Im Modell angewendet"),LEFT('AfA-Vergleich'!$C$26,2)="Ja"),'AfA-Vergleich'!$O$26,0) -> 0 | I162: =IF(AND(NOT('AfA-Vergleich'!$S$26="Im Modell angewendet"),LEFT('AfA-Vergleich'!$C$26,2)<>"Ja"),'AfA-Vergleich'!$O$26,0) -> 0 | AI162: ="Werbungskosten · "&TEXT(IFERROR(MAX(0,'S06 Bewirtschaftung'!$D$66)/SUM('S06 Bewirtschaftung'!$D$61:$D$66),0),"0 %") -> Werbungskosten · 11 %
B163: Gesamtertrag nach Steuern | C163: Betrag (€) | F163: Wasserfall (Diagramm) | G163: Start | H163: Ende | I163: Basis | J163: Zufl. + | K163: Zufl. − | L163: Abfl. + | M163: Abfl. − | N163: Erg. + | O163: Erg. − | P163: Oberkante | Q163: Beschriftung | R163: Lbl 1 | S163: Lbl 2 | T163: Lbl 3 | U163: Lbl 4
B164: Kumulierter Cashflow n. St. | C164: =Exit_CF_kum -> -32838.531 | F164: Cashflow kumuliert | G164: =0 -> 0 | H164: =G164+C164 -> -32838.531 | I164: =IF(MIN(G164,H164)>=0,MIN(G164,H164),IF(MAX(G164,H164)<=0,MAX(G164,H164),0)) -> 0 | J164: =IF(C164>=0,IF(MIN(G164,H164)>=0,MAX(G164,H164)-MIN(G164,H164),MAX(0,MAX(G164,H164))),0) -> 0 | K164: =IF(C164>=0,IF(MAX(G164,H164)<=0,MIN(G164,H164)-MAX(G164,H164),MIN(0,MIN(G164,H164))),0) -> 0 | L164: =IF(C164<0,IF(MIN(G164,H164)>=0,MAX(G164,H164)-MIN(G164,H164),MAX(0,MAX(G164,H164))),0) -> 0 | M164: =IF(C164<0,IF(MAX(G164,H164)<=0,MIN(G164,H164)-MAX(G164,H164),MIN(0,MIN(G164,H164))),0) -> -32838.531 | N164: =0 -> 0 | O164: =0 -> 0 | P164: =MAX(0,MAX(G164,H164)) -> 0 | Q164: =IF(C164<0,"−","+")&FIXED(ABS(C164)/1000,1)&" T€" -> −32.8 T€ | R164: =P164 -> 0 | S164: =0 -> 0 | T164: =0 -> 0 | U164: =0 -> 0 | AI164: ="Darlehen I · "&TEXT(IFERROR(MAX(0,Diagramme!$C$147)/SUM(Diagramme!$C$147:$C$149),0),"0 %") -> Darlehen I · 76 %
B165: Nettoerlös Verkauf | C165: =Exit_Netto -> 189109.9 | F165: Nettoerlös Verkauf | G165: =H164 -> -32838.531 | H165: =G165+C165 -> 156271.37 | I165: =IF(MIN(G165,H165)>=0,MIN(G165,H165),IF(MAX(G165,H165)<=0,MAX(G165,H165),0)) -> 0 | J165: =IF(C165>=0,IF(MIN(G165,H165)>=0,MAX(G165,H165)-MIN(G165,H165),MAX(0,MAX(G165,H165))),0) -> 156271.37 | K165: =IF(C165>=0,IF(MAX(G165,H165)<=0,MIN(G165,H165)-MAX(G165,H165),MIN(0,MIN(G165,H165))),0) -> -32838.531 | L165: =IF(C165<0,IF(MIN(G165,H165)>=0,MAX(G165,H165)-MIN(G165,H165),MAX(0,MAX(G165,H165))),0) -> 0 | M165: =IF(C165<0,IF(MAX(G165,H165)<=0,MIN(G165,H165)-MAX(G165,H165),MIN(0,MIN(G165,H165))),0) -> 0 | N165: =0 -> 0 | O165: =0 -> 0 | P165: =MAX(0,MAX(G165,H165)) -> 156271.37 | Q165: =IF(C165<0,"−","+")&FIXED(ABS(C165)/1000,1)&" T€" -> +189.1 T€ | R165: =0 -> 0 | S165: =P165 -> 156271.37 | T165: =0 -> 0 | U165: =0 -> 0 | AI165: ="Darlehen II · "&TEXT(IFERROR(MAX(0,Diagramme!$C$148)/SUM(Diagramme!$C$147:$C$149),0),"0 %") -> Darlehen II · 0 %
B166: – Eingesetztes Eigenkapital | C166: =-Eigenkapital -> -78974.5 | F166: Eigenkapital | G166: =H165 -> 156271.37 | H166: =G166+C166 -> 77296.866 | I166: =IF(MIN(G166,H166)>=0,MIN(G166,H166),IF(MAX(G166,H166)<=0,MAX(G166,H166),0)) -> 77296.866 | J166: =IF(C166>=0,IF(MIN(G166,H166)>=0,MAX(G166,H166)-MIN(G166,H166),MAX(0,MAX(G166,H166))),0) -> 0 | K166: =IF(C166>=0,IF(MAX(G166,H166)<=0,MIN(G166,H166)-MAX(G166,H166),MIN(0,MIN(G166,H166))),0) -> 0 | L166: =IF(C166<0,IF(MIN(G166,H166)>=0,MAX(G166,H166)-MIN(G166,H166),MAX(0,MAX(G166,H166))),0) -> 78974.5 | M166: =IF(C166<0,IF(MAX(G166,H166)<=0,MIN(G166,H166)-MAX(G166,H166),MIN(0,MIN(G166,H166))),0) -> 0 | N166: =0 -> 0 | O166: =0 -> 0 | P166: =MAX(0,MAX(G166,H166)) -> 156271.37 | Q166: =IF(C166<0,"−","+")&FIXED(ABS(C166)/1000,1)&" T€" -> −79.0 T€ | R166: =0 -> 0 | S166: =0 -> 0 | T166: =P166 -> 156271.37 | U166: =0 -> 0 | AI166: ="Eigenkapital · "&TEXT(IFERROR(MAX(0,Diagramme!$C$149)/SUM(Diagramme!$C$147:$C$149),0),"0 %") -> Eigenkapital · 24 %
B167: = Gesamtertrag | C167: =Gesamtertrag -> 77296.866 | F167: Gesamtertrag | G167: =0 -> 0 | H167: =C167 -> 77296.866 | I167: =IF(MIN(G167,H167)>=0,MIN(G167,H167),IF(MAX(G167,H167)<=0,MAX(G167,H167),0)) -> 0 | J167: =0 -> 0 | K167: =0 -> 0 | L167: =0 -> 0 | M167: =0 -> 0 | N167: =IF(MIN(G167,H167)>=0,MAX(G167,H167)-MIN(G167,H167),MAX(0,MAX(G167,H167))) -> 77296.866 | O167: =IF(MAX(G167,H167)<=0,MIN(G167,H167)-MAX(G167,H167),MIN(0,MIN(G167,H167))) -> 0 | P167: =MAX(0,MAX(G167,H167)) -> 77296.866 | Q167: =IF(C167<0,"−","")&FIXED(ABS(C167)/1000,1)&" T€" -> 77.3 T€ | R167: =0 -> 0 | S167: =0 -> 0 | T167: =0 -> 0 | U167: =P167 -> 77296.866
AI168: ="Verkaufskosten · "&TEXT(IFERROR(MAX(0,Diagramme!$C$158)/SUM(Diagramme!$C$158:$C$161),0),"0 %") -> Verkaufskosten · 2 %
B169: Jahr 1 pro Monat (€) | C169: Einnahmen | D169: Ausgaben | F169: Hilfsreihen Jahr 1 / Namen | G169: Einnahmen | H169: Ausgaben | AI169: ="Steuer · "&TEXT(IFERROR(MAX(0,Diagramme!$C$159)/SUM(Diagramme!$C$158:$C$161),0),"0 %") -> Steuer · 0 %
B170: Nettokaltmiete | C170: =INDEX(Projektion!$D$15:$AQ$15,1)/12 -> 921.5 | D170: =0 -> 0 | F170: =IF(D175>0,"Steuerzahlung","Steuererstattung") -> Steuererstattung | G170: =C171 -> 709.19971 | H170: =D175 -> 0 | AI170: ="Restschuld · "&TEXT(IFERROR(MAX(0,Diagramme!$C$160)/SUM(Diagramme!$C$158:$C$161),0),"0 %") -> Restschuld · 48 %
B171: Steuererstattung | C171: =MAX(0,-INDEX(Projektion!$D$35:$AQ$35,1)/12) -> 709.19971 | D171: =0 -> 0 | F171: Summe | G171: =SUM(C170:C175) -> 1630.6997 | H171: =SUM(D170:D175) -> 1374.1667 | AI171: ="Nettoerlös · "&TEXT(IFERROR(MAX(0,Diagramme!$C$161)/SUM(Diagramme!$C$158:$C$161),0),"0 %") -> Nettoerlös · 50 %
B172: Bewirtschaftungskosten | C172: =0 -> 0 | D172: =INDEX(Projektion!$D$26:$AQ$26,1)/12 -> 207.5 | F172: Summe vor Steuern | G172: =C170+C172+C173+C174 -> 921.5 | H172: =D170+D172+D173+D174 -> 1374.1667
B173: Zinsen | C173: =0 -> 0 | D173: =INDEX(Projektion!$D$30:$AQ$30,1)/12 -> 750 | F173: =IF(MAX(D181:AL181)>0,"Darlehen II","Darlehen II (keines)") -> Darlehen II (keines)
B174: Tilgung | C174: =0 -> 0 | D174: =INDEX(Projektion!$D$31:$AQ$31,1)/12 -> 416.66667
B175: Steuerzahlung | C175: =0 -> 0 | D175: =MAX(0,INDEX(Projektion!$D$35:$AQ$35,1)/12) -> 0
B177: Zeitreihen (Jahr 1–40) | C177: Einheit | D177: 1 | E177: 2 | F177: 3 | G177: 4 | H177: 5 | I177: 6 | J177: 7 | K177: 8 | L177: 9 | M177: 10 | N177: 11 | O177: 12 | P177: 13 | Q177: 14 | R177: 15 | S177: 16 | T177: 17 | U177: 18 | V177: 19 | W177: 20 | X177: 21 | Y177: 22 | Z177: 23 | AA177: 24 | AB177: 25 | AC177: 26 | AD177: 27 | AE177: 28 | AF177: 29 | AG177: 30 | AH177: 31 | AI177: 32 | AJ177: 33 | AK177: 34 | AL177: 35 | AM177: 36 | AN177: 37 | AO177: 38 | AP177: 39 | AQ177: 40
B178: Kalenderjahr | C178: Jahr | D178: =YEAR(Kaufdatum)+1-1 -> 2026 | E178: =YEAR(Kaufdatum)+2-1 -> 2027 | F178: =YEAR(Kaufdatum)+3-1 -> 2028 | G178: =YEAR(Kaufdatum)+4-1 -> 2029 | H178: =YEAR(Kaufdatum)+5-1 -> 2030 | I178: =YEAR(Kaufdatum)+6-1 -> 2031 | J178: =YEAR(Kaufdatum)+7-1 -> 2032 | K178: =YEAR(Kaufdatum)+8-1 -> 2033 | L178: =YEAR(Kaufdatum)+9-1 -> 2034 | M178: =YEAR(Kaufdatum)+10-1 -> 2035 | N178: =YEAR(Kaufdatum)+11-1 -> 2036 | O178: =YEAR(Kaufdatum)+12-1 -> 2037 | P178: =YEAR(Kaufdatum)+13-1 -> 2038 | Q178: =YEAR(Kaufdatum)+14-1 -> 2039 | R178: =YEAR(Kaufdatum)+15-1 -> 2040 | S178: =YEAR(Kaufdatum)+16-1 -> 2041 | T178: =YEAR(Kaufdatum)+17-1 -> 2042 | U178: =YEAR(Kaufdatum)+18-1 -> 2043 | V178: =YEAR(Kaufdatum)+19-1 -> 2044 | W178: =YEAR(Kaufdatum)+20-1 -> 2045 | X178: =YEAR(Kaufdatum)+21-1 -> 2046 | Y178: =YEAR(Kaufdatum)+22-1 -> 2047 | Z178: =YEAR(Kaufdatum)+23-1 -> 2048 | AA178: =YEAR(Kaufdatum)+24-1 -> 2049 | AB178: =YEAR(Kaufdatum)+25-1 -> 2050 | AC178: =YEAR(Kaufdatum)+26-1 -> 2051 | AD178: =YEAR(Kaufdatum)+27-1 -> 2052 | AE178: =YEAR(Kaufdatum)+28-1 -> 2053 | AF178: =YEAR(Kaufdatum)+29-1 -> 2054 | AG178: =YEAR(Kaufdatum)+30-1 -> 2055 | AH178: =YEAR(Kaufdatum)+31-1 -> 2056 | AI178: =YEAR(Kaufdatum)+32-1 -> 2057 | AJ178: =YEAR(Kaufdatum)+33-1 -> 2058 | AK178: =YEAR(Kaufdatum)+34-1 -> 2059 | AL178: =YEAR(Kaufdatum)+35-1 -> 2060 | AM178: =YEAR(Kaufdatum)+36-1 -> 2061 | AN178: =YEAR(Kaufdatum)+37-1 -> 2062 | AO178: =YEAR(Kaufdatum)+38-1 -> 2063 | AP178: =YEAR(Kaufdatum)+39-1 -> 2064 | AQ178: =YEAR(Kaufdatum)+40-1 -> 2065
B179: Immobilienwert | C179: € | D179: =Projektion!D41 -> 302940 | E179: =Projektion!E41 -> 308998.8 | F179: =Projektion!F41 -> 315178.78 | G179: =Projektion!G41 -> 321482.35 | H179: =Projektion!H41 -> 327912 | I179: =Projektion!I41 -> 334470.24 | J179: =Projektion!J41 -> 341159.64 | K179: =Projektion!K41 -> 347982.84 | ... AQ179: =Projektion!AQ41 -> 655787.78
B180: Restschuld Darlehen I | C180: € | D180: =Finanzierung!D19 -> 245000 | E180: =Finanzierung!E19 -> 239820 | F180: =Finanzierung!F19 -> 234453.52 | G180: =Finanzierung!G19 -> 228893.85 | H180: =Finanzierung!H19 -> 223134.03 | I180: =Finanzierung!I19 -> 217166.85 | J180: =Finanzierung!J19 -> 210984.86 | K180: =Finanzierung!K19 -> 204580.31 | ... AQ180: =Finanzierung!AQ19 -> 0
B181: Restschuld Darlehen II | C181: € | D181: =Finanzierung!D30 -> 0 | E181: =Finanzierung!E30 -> 0 | F181: =Finanzierung!F30 -> 0 | G181: =Finanzierung!G30 -> 0 | H181: =Finanzierung!H30 -> 0 | I181: =Finanzierung!I30 -> 0 | J181: =Finanzierung!J30 -> 0 | K181: =Finanzierung!K30 -> 0 | ... AQ181: =Finanzierung!AQ30 -> 0
B182: Restschuld gesamt | C182: € | D182: =Finanzierung!D38 -> 245000 | E182: =Finanzierung!E38 -> 239820 | F182: =Finanzierung!F38 -> 234453.52 | G182: =Finanzierung!G38 -> 228893.85 | H182: =Finanzierung!H38 -> 223134.03 | I182: =Finanzierung!I38 -> 217166.85 | J182: =Finanzierung!J38 -> 210984.86 | K182: =Finanzierung!K38 -> 204580.31 | ... AQ182: =Finanzierung!AQ38 -> 0
B183: Nettovermögen | C183: € | D183: =Projektion!D43 -> 57940 | E183: =Projektion!E43 -> 69178.8 | F183: =Projektion!F43 -> 80725.256 | G183: =Projektion!G43 -> 92588.505 | H183: =Projektion!H43 -> 104777.97 | I183: =Projektion!I43 -> 117303.39 | J183: =Projektion!J43 -> 130174.79 | K183: =Projektion!K43 -> 143402.52 | ... AQ183: =Projektion!AQ43 -> 655787.78
B184: Cashflow vor Steuern | C184: € | D184: =Projektion!D33 -> -5432 | E184: =Projektion!E33 -> -5260.64 | F184: =Projektion!F33 -> -5085.8528 | G184: =Projektion!G33 -> -4907.5699 | H184: =Projektion!H33 -> -4725.7213 | I184: =Projektion!I33 -> -4540.2357 | J184: =Projektion!J33 -> -4351.0404 | K184: =Projektion!K33 -> -4158.0612 | ... AQ184: =Projektion!AQ33 -> 18547.533
B185: Cashflow nach Steuern | C185: € | D185: =Projektion!D36 -> 3078.3965 | E185: =Projektion!E36 -> -3286.9635 | F185: =Projektion!F36 -> -3293.1662 | G185: =Projektion!G36 -> -3300.8732 | H185: =Projektion!H36 -> -3310.1643 | I185: =Projektion!I36 -> -3321.1226 | J185: =Projektion!J36 -> -3333.8347 | K185: =Projektion!K36 -> -3348.3911 | ... AQ185: =Projektion!AQ36 -> 10755.539
B186: Kumulierter Cashflow nach Steuern | C186: € | D186: =Projektion!D38 -> 3078.3965 | E186: =Projektion!E38 -> -208.56691 | F186: =Projektion!F38 -> -3501.7331 | G186: =Projektion!G38 -> -6802.6064 | H186: =Projektion!H38 -> -10112.771 | I186: =Projektion!I38 -> -13433.893 | J186: =Projektion!J38 -> -16767.728 | K186: =Projektion!K38 -> -20116.119 | ... AQ186: =Projektion!AQ38 -> -16195.544
B187: Zinsen | C187: € | D187: =Finanzierung!D35 -> 9000 | E187: =Finanzierung!E35 -> 8820 | F187: =Finanzierung!F35 -> 8633.52 | G187: =Finanzierung!G35 -> 8440.3267 | H187: =Finanzierung!H35 -> 8240.1785 | I187: =Finanzierung!I35 -> 8032.8249 | J187: =Finanzierung!J35 -> 7818.0066 | K187: =Finanzierung!K35 -> 7595.4548 | ... AQ187: =Finanzierung!AQ35 -> 0
B188: Tilgung | C188: € | D188: =Finanzierung!D36 -> 5000 | E188: =Finanzierung!E36 -> 5180 | F188: =Finanzierung!F36 -> 5366.48 | G188: =Finanzierung!G36 -> 5559.6733 | H188: =Finanzierung!H36 -> 5759.8215 | I188: =Finanzierung!I36 -> 5967.1751 | J188: =Finanzierung!J36 -> 6181.9934 | K188: =Finanzierung!K36 -> 6404.5452 | ... AQ188: =Finanzierung!AQ36 -> 0
B189: Kumulierte Zinsen | C189: € | D189: =D187 -> 9000 | E189: =D189+E187 -> 17820 | F189: =E189+F187 -> 26453.52 | G189: =F189+G187 -> 34893.847 | H189: =G189+H187 -> 43134.025 | I189: =H189+I187 -> 51166.85 | J189: =I189+J187 -> 58984.857 | K189: =J189+K187 -> 66580.312 | L189: =K189+L187 -> 73945.203 | ... AQ189: =AP189+AQ187 -> 192967.84
B190: Kumulierte Tilgung | C190: € | D190: =D188 -> 5000 | E190: =D190+E188 -> 10180 | F190: =E190+F188 -> 15546.48 | G190: =F190+G188 -> 21106.153 | H190: =G190+H188 -> 26865.975 | I190: =H190+I188 -> 32833.15 | J190: =I190+J188 -> 39015.143 | K190: =J190+K188 -> 45419.688 | L190: =K190+L188 -> 52054.797 | ... AQ190: =AP190+AQ188 -> 250000
B191: Kumulierte Steuer | C191: € | D191: =Steuern!D74 -> -8510.3965 | E191: =Steuern!E74 -> -10484.073 | F191: =Steuern!F74 -> -12276.76 | G191: =Steuern!G74 -> -13883.456 | H191: =Steuern!H74 -> -15299.013 | I191: =Steuern!I74 -> -16518.126 | J191: =Steuern!J74 -> -17535.332 | K191: =Steuern!K74 -> -18345.002 | ... AQ191: =Steuern!AQ74 -> 90751.898
B192: AfA regulär (Gebäude) | C192: € | D192: =Steuern!D49 -> 4885.3569 | E192: =Steuern!E49 -> 4885.3569 | F192: =Steuern!F49 -> 4885.3569 | G192: =Steuern!G49 -> 4885.3569 | H192: =Steuern!H49 -> 4885.3569 | I192: =Steuern!I49 -> 4885.3569 | J192: =Steuern!J49 -> 4885.3569 | K192: =Steuern!K49 -> 4885.3569 | ... AQ192: =Steuern!AQ49 -> 4885.3569
B193: Sonder-AfA § 7b | C193: € | D193: =Steuern!D50 -> 0 | E193: =Steuern!E50 -> 0 | F193: =Steuern!F50 -> 0 | G193: =Steuern!G50 -> 0 | H193: =Steuern!H50 -> 0 | I193: =Steuern!I50 -> 0 | J193: =Steuern!J50 -> 0 | K193: =Steuern!K50 -> 0 | ... AQ193: =Steuern!AQ50 -> 0
B194: Erhöhte Absetzungen § 7h/7i | C194: € | D194: =Steuern!D54 -> 0 | E194: =Steuern!E54 -> 0 | F194: =Steuern!F54 -> 0 | G194: =Steuern!G54 -> 0 | H194: =Steuern!H54 -> 0 | I194: =Steuern!I54 -> 0 | J194: =Steuern!J54 -> 0 | K194: =Steuern!K54 -> 0 | ... AQ194: =Steuern!AQ54 -> 0
B195: AfA bewegliche Gegenstände | C195: € | D195: =Steuern!D55 -> 800 | E195: =Steuern!E55 -> 800 | F195: =Steuern!F55 -> 800 | G195: =Steuern!G55 -> 800 | H195: =Steuern!H55 -> 800 | I195: =Steuern!I55 -> 800 | J195: =Steuern!J55 -> 800 | K195: =Steuern!K55 -> 800 | ... AQ195: =Steuern!AQ55 -> 0
B196: Steuerliches Ergebnis | C196: € | D196: =Steuern!D67 -> -18397.357 | E196: =Steuern!E67 -> -4266.5969 | F196: =Steuern!F67 -> -3875.3417 | G196: =Steuern!G67 -> -3473.2778 | H196: =Steuern!H67 -> -3060.0814 | I196: =Steuern!I67 -> -2635.4187 | J196: =Steuern!J67 -> -2198.9452 | K196: =Steuern!K67 -> -1750.305 | ... AQ196: =Steuern!AQ67 -> 16844.351
B197: Steuer (+ Zahlung / – Erstattung) | C197: € | D197: =Steuern!D73 -> -8510.3965 | E197: =Steuern!E73 -> -1973.6765 | F197: =Steuern!F73 -> -1792.6866 | G197: =Steuern!G73 -> -1606.6966 | H197: =Steuern!H73 -> -1415.5569 | I197: =Steuern!I73 -> -1219.1131 | J197: =Steuern!J73 -> -1017.2056 | K197: =Steuern!K73 -> -809.67011 | ... AQ197: =Steuern!AQ73 -> 7791.9947
B198: Nettokaltmiete Ist | C198: € | D198: =Projektion!D15 -> 11058 | E198: =Projektion!E15 -> 11279.16 | F198: =Projektion!F15 -> 11504.743 | G198: =Projektion!G15 -> 11734.838 | H198: =Projektion!H15 -> 11969.535 | I198: =Projektion!I15 -> 12208.926 | J198: =Projektion!J15 -> 12453.104 | K198: =Projektion!K15 -> 12702.166 | ... AQ198: =Projektion!AQ15 -> 23937.748
B199: Bewirtschaftungskosten | C199: € | D199: =Projektion!D26 -> 2490 | E199: =Projektion!E26 -> 2539.8 | F199: =Projektion!F26 -> 2590.596 | G199: =Projektion!G26 -> 2642.4079 | H199: =Projektion!H26 -> 2695.2561 | I199: =Projektion!I26 -> 2749.1612 | J199: =Projektion!J26 -> 2804.1444 | K199: =Projektion!K26 -> 2860.2273 | ... AQ199: =Projektion!AQ26 -> 5390.2145
B200: Kapitaldienst | C200: € | D200: =Projektion!D32 -> 14000 | E200: =Projektion!E32 -> 14000 | F200: =Projektion!F32 -> 14000 | G200: =Projektion!G32 -> 14000 | H200: =Projektion!H32 -> 14000 | I200: =Projektion!I32 -> 14000 | J200: =Projektion!J32 -> 14000 | K200: =Projektion!K32 -> 14000 | ... AQ200: =Projektion!AQ32 -> 0
B201: Eigenkapitalrendite im Jahr | C201: % | D201: =Projektion!D45 -> 0.17750535 | E201: =Projektion!E45 -> 0.10068866 | F201: =Projektion!F45 -> 0.10450576 | G201: =Projektion!G45 -> 0.1084195 | H201: =Projektion!H45 -> 0.11243255 | I201: =Projektion!I45 -> 0.11654765 | J201: =Projektion!J45 -> 0.12076763 | K201: =Projektion!K45 -> 0.1250954 | ... AQ201: =Projektion!AQ45 -> 0.29900946
B202: ="Verkaufspreis Jahr "&Haltedauer -> Verkaufspreis Jahr 12 | C202: € | D202: =IF(D$177=Haltedauer,D179,0) -> 0 | E202: =IF(E$177=Haltedauer,E179,0) -> 0 | F202: =IF(F$177=Haltedauer,F179,0) -> 0 | G202: =IF(G$177=Haltedauer,G179,0) -> 0 | H202: =IF(H$177=Haltedauer,H179,0) -> 0 | I202: =IF(I$177=Haltedauer,I179,0) -> 0 | J202: =IF(J$177=Haltedauer,J179,0) -> 0 | K202: =IF(K$177=Haltedauer,K179,0) -> 0 | ... AQ202: =IF(AQ$177=Haltedauer,AQ179,0) -> 0
B203: =IF(SUM(D203:W203)>0,"Sonder-AfA (§ 7b, § 7h/7i)","Sonder-AfA (keine)") -> Sonder-AfA (keine) | C203: € | D203: =D193+D194 -> 0 | E203: =E193+E194 -> 0 | F203: =F193+F194 -> 0 | G203: =G193+G194 -> 0 | H203: =H193+H194 -> 0 | I203: =I193+I194 -> 0 | J203: =J193+J194 -> 0 | K203: =K193+K194 -> 0 | ... AQ203: =AQ193+AQ194 -> 0
B205: AfA im Modell kumuliert (Diagramm) | C205: € | D205: ='AfA-Vergleich'!$D$26 -> 4885.3569 | E205: =D205+'AfA-Vergleich'!$E$26 -> 9770.7139 | F205: =E205+'AfA-Vergleich'!$F$26 -> 14656.071 | G205: =F205+'AfA-Vergleich'!$G$26 -> 19541.428 | H205: =G205+'AfA-Vergleich'!$H$26 -> 24426.785 | I205: =H205+'AfA-Vergleich'!$I$26 -> 29312.142 | J205: =I205+'AfA-Vergleich'!$J$26 -> 34197.499 | K205: =J205+'AfA-Vergleich'!$K$26 -> 39082.855 | L205: =K205+'AfA-Vergleich'!$L$26 -> 43968.212 | M205: =L205+'AfA-Vergleich'!$M$26 -> 48853.569
B206: Cashflow n. St. – Überschuss (Diagramm) | C206: € | D206: =MAX(0,D185) -> 3078.3965 | E206: =MAX(0,E185) -> 0 | F206: =MAX(0,F185) -> 0 | G206: =MAX(0,G185) -> 0 | H206: =MAX(0,H185) -> 0 | I206: =MAX(0,I185) -> 0 | J206: =MAX(0,J185) -> 0 | K206: =MAX(0,K185) -> 0 | ... AQ206: =MAX(0,AQ185) -> 10755.539
B207: Cashflow n. St. – Unterdeckung (Diagramm) | C207: € | D207: =MIN(0,D185) -> 0 | E207: =MIN(0,E185) -> -3286.9635 | F207: =MIN(0,F185) -> -3293.1662 | G207: =MIN(0,G185) -> -3300.8732 | H207: =MIN(0,H185) -> -3310.1643 | I207: =MIN(0,I185) -> -3321.1226 | J207: =MIN(0,J185) -> -3333.8347 | K207: =MIN(0,K185) -> -3348.3911 | ... AQ207: =MIN(0,AQ185) -> 0
B209: Keine Gewähr für die Richtigkeit der Angaben · ersetzt keine Rechts-, Steuer- oder Finanzberatung · Rechtsstand September 2026
B210: MM Holding GmbH · Kornhausgasse 4 · 88250 Weingarten · Amtsgericht Ulm HRB 750729

Sheet Eingaben
B5: EINGABEN › ALLE ANNAHMEN | L5: ‹ Start
B6: Eingaben | L6: =Obj_Name -> Beispiel: 3-Zimmer-Eigentumswohnung
B7: Alle Annahmen auf einen Blick – geändert wird im Leitfaden; direkt editierbar sind nur die Profi-Felder für Darlehen II. | L7: =IFERROR(IF(Erstellt_fuer="","","Erstellt für "&Erstellt_fuer),"") -> Erstellt für Max Mustermann
H8: ■ Eingabe hier ■ aus dem Leitfaden – dort ändern ■ berechnet
B9: 1 Objekt und Kaufpreis Stammdaten aus Schritt 01 und 02 | L9: ↑ Übersicht
B10: POSITION | C10: WERT | E10: EINHEIT | F10: QUELLE | G10: HINWEIS / STEUERLICHE EINORDNUNG
B11: Objektbezeichnung | C11: =Obj_Name -> Beispiel: 3-Zimmer-Eigentumswohnung | F11: S01 › | G11: Freitext – erscheint im Cockpit und im Bankgespräch
B12: Adresse | C12: =Obj_Adresse -> Musterstraße 1, 88250 Weingarten | F12: S01 ›
B13: Objektart | C13: =Objektart -> Eigentumswohnung | F13: S01 › | G13: Gewerbeeinheit: keine § 7b-Sonder-AfA, keine degressive AfA; im Betriebsvermögen 3 % linear
B14: Wohn-/Nutzfläche | C14: =Wohnflaeche -> 75 | F14: S01 › | G14: Basis für Miete/m², Instandhaltungsrücklage und die § 7b-Grenzen
B15: Grundstücksfläche bzw. Miteigentumsanteil | C15: =Grundstueck_qm -> 120 | F15: S01 › | G15: ETW: Miteigentumsanteil × Grundstücksfläche (lt. Teilungserklärung); nur Bodenrichtwert-Methode
B16: Baujahr (Jahr der Fertigstellung) | C16: =Baujahr -> 1996 | F16: S01 › | G16: Steuert AfA-Satz und die Prüfung von § 7b / degressiver AfA
B17: Kaufdatum (Übergang Nutzen & Lasten) | C17: =Kaufdatum -> 46357 | F17: S01 › | G17: Jahr 1 der Kalkulation = erste 12 Monate ab Kauf (keine zeitanteilige AfA im Modell)
B18: Bundesland (Belegenheit) | C18: =Bundesland -> Baden-Württemberg | F18: S01 › | G18: Steuert den Grunderwerbsteuersatz
B19: Kaufpreis (gesamt lt. Kaufvertrag) | C19: =Kaufpreis -> 285000 | F19: S02 › | G19: Inkl. mitverkaufter beweglicher Gegenstände und Rücklagenanteil
B20: davon bewegliche Gegenstände | C20: =KP_bewegl -> 8000 | F20: S02 › | G20: Einbauküche, Möbel: grunderwerbsteuerfrei (§ 2 GrEStG), gesondert linear abschreibbar
B21: Nutzungsdauer bewegliche Gegenstände | C21: =ND_bewegl -> 10 | F21: S02 › | G21: Einbauküche i. d. R. 10 Jahre (BFH IX R 14/15), Möbel 8–13 Jahre (AfA-Tabelle)
B22: davon Anteil an der Erhaltungsrücklage der WEG | C22: =Ruecklage_mitverkauft -> 3000 | F22: S02 › | G22: Gehört nicht zu den Gebäude-AK (nicht abschreibbar), unterliegt aber der GrESt (BFH II R 49/17)
B24: 2 Kaufnebenkosten Anschaffungsnebenkosten – anteilig mit dem Gebäude abgeschrieben | L24: ↑ Übersicht
B25: POSITION | C25: WERT | E25: EINHEIT | F25: QUELLE | G25: HINWEIS / STEUERLICHE EINORDNUNG
B26: Grunderwerbsteuersatz abweichend | C26: =GrESt_Override -> 0 | F26: S03 › | G26: Leer = automatisch nach Bundesland – nur ausfüllen, wenn ein abweichender Satz gelten soll
B27: Grunderwerbsteuersatz (angewendet) | C27: =IF(ISNUMBER(GrESt_Override),GrESt_Override,IFERROR(VLOOKUP(Bundesland,GrESt_Tab,2,FALSE()),0)) -> 0.05
B28: Grunderwerbsteuer | C28: =(Kaufpreis-KP_bewegl)*GrESt_Satz -> 13850 | G28: Bemessungsgrundlage ohne gesondert ausgewiesene bewegliche Gegenstände
B29: Notar (Kaufvertrag, Auflassung) | C29: =Notar_Pct -> 0.015 | F29: S03 › | G29: Üblich 1,0 – 1,5 % des Kaufpreises
B30: Grundbuchamt (Eigentumsumschreibung) | C30: =Grundbuch_Pct -> 0.005 | F30: S03 › | G30: Üblich ca. 0,5 %
B31: Maklerprovision (inkl. USt) | C31: =Makler_Pct -> 0.0357 | F31: S03 › | G31: Z. B. 3,57 % (3 % zzgl. 19 % USt)
B32: Sonstige Erwerbsnebenkosten | C32: =NK_Sonst -> 500 | F32: S03 › | G32: Gutachten, Fahrtkosten, Übersetzungen – Anschaffungsnebenkosten, sofern objektbezogen
B33: Notar – Betrag | C33: =Kaufpreis*Notar_Pct -> 4275
B34: Grundbuch – Betrag | C34: =Kaufpreis*Grundbuch_Pct -> 1425
B35: Makler – Betrag | C35: =Kaufpreis*Makler_Pct -> 10174.5
B36: Summe Kaufnebenkosten | C36: =GrESt_Betrag+Notar_Betrag+Grundbuch_Betrag+Makler_Betrag+NK_Sonst -> 30224.5
B37: Kaufnebenkostenquote | C37: =IF(Kaufpreis>0,NK_Summe/Kaufpreis,0) -> 0.10605088
B39: 3 Finanzierungsnebenkosten sofort abziehbare Werbungskosten bzw. Betriebsausgaben | L39: ↑ Übersicht
B40: POSITION | C40: WERT | E40: EINHEIT | F40: QUELLE | G40: HINWEIS / STEUERLICHE EINORDNUNG
B41: Grundschuldbestellung (Notar + Grundbuch) | C41: =Grundschuld_Pct -> 0.005 | E41: vom Darlehen | F41: S07 › | G41: Ca. 0,4 – 0,6 % der Darlehenssumme; Finanzierungskosten, sofort abziehbar
B42: Bearbeitungsgebühr / Wertermittlung / Vermittlung | C42: =Fin_NK_Sonst -> 500 | F42: S07 › | G42: Bank bzw. Vermittler – sofort abziehbar im Jahr der Zahlung
B43: Disagio Darlehen I | C43: =Disagio_Pct -> 0 | F43: S07 › | G43: Bis 5 % bei ≥ 5 Jahren Zinsbindung sofort abziehbar, sonst Verteilung über die Zinsbindung
B44: Grundschuldbestellung – Betrag | C44: =(Darlehen_I+Darlehen_II)*Grundschuld_Pct -> 1250
B45: Disagio – Betrag | C45: =Darlehen_I*Disagio_Pct -> 0 | G45: Erhöht den Kapitalbedarf (geringere Auszahlung)
B46: Summe Finanzierungsnebenkosten | C46: =Grundschuld_Betrag+Fin_NK_Sonst+Disagio_Betrag -> 1750
B48: 4 Kaufpreisaufteilung Grund und Boden / Gebäude · AfA-Bemessungsgrundlage | L48: ↑ Übersicht
B49: POSITION | C49: WERT | E49: EINHEIT | F49: QUELLE | G49: HINWEIS / STEUERLICHE EINORDNUNG
B50: Methode der Kaufpreisaufteilung | C50: =KPA_Methode -> Bodenrichtwert × Grundstücks-/Miteigentumsanteil | F50: S04 › | G50: BMF-Arbeitshilfe; abweichend per Gutachten oder plausibler Kaufvertragsaufteilung (BFH IX R 26/19)
B51: Bodenrichtwert | C51: =Bodenrichtwert -> 450 | E51: je m² | F51: S04 › | G51: Lt. Gutachterausschuss / BORIS des Bundeslandes (Methode 1)
B52: Bodenanteil in % des Kaufpreises | C52: =Bodenanteil_Pct -> 0.2 | F52: S04 › | G52: Nur Methode 2
B53: Gebäudewert lt. Gutachten / Kaufvertrag | C53: =Gebaeudewert_Gutachten -> 0 | F53: S04 › | G53: Nur Methode 3 (ohne bewegliche Gegenstände)
B54: Kaufpreis Immobilie (ohne Inventar und Rücklage) | C54: =Kaufpreis-KP_bewegl-Ruecklage_mitverkauft -> 274000
B55: Bodenwert (nicht abschreibbar) | C55: =IF(KPA_Idx=1,MIN(Bodenrichtwert*Grundstueck_qm,KP_Immobilie),IF(KPA_Idx=2,KP_Immobilie*Bodenanteil_Pct,MAX(KP_Immobilie-N(Gebaeudewert_Gutachten),0))) -> 54000
B56: Gebäudeanteil am Kaufpreis | C56: =IF(KP_Immobilie>0,(KP_Immobilie-Bodenwert)/KP_Immobilie,0) -> 0.80291971
B57: Anschaffungskosten Grund und Boden | C57: =Bodenwert+NK_Summe*(1-Gebaeudeanteil_Pct) -> 59956.653 | G57: Inkl. anteiliger Kaufnebenkosten; nicht abschreibbar
B58: Anschaffungskosten Gebäude = AfA-Basis | C58: =(KP_Immobilie-Bodenwert)+NK_Summe*Gebaeudeanteil_Pct -> 244267.85 | G58: Inkl. anteiliger Kaufnebenkosten
B59: Anschaffungskosten gesamt | C59: =Kaufpreis+NK_Summe -> 315224.5 | G59: Kaufpreis + Kaufnebenkosten
B61: 5 Maßnahmen nach Erwerb Renovierung, Sonderumlagen, Reserven | L61: ↑ Übersicht
B62: POSITION | C62: WERT | E62: EINHEIT | F62: QUELLE | G62: HINWEIS / STEUERLICHE EINORDNUNG
B63: Renovierung / Modernisierung im Jahr 1 (brutto) | C63: =Reno_J1 -> 12000 | F63: S05 › | G63: Teil des anfänglichen Kapitalbedarfs
B64: Renovierung / Modernisierung im Jahr 2 (brutto) | C64: =Reno_J2 -> 0 | F64: S05 › | G64: Aus laufendem Cashflow / Eigenkapital
B65: Renovierung / Modernisierung im Jahr 3 (brutto) | C65: =Reno_J3 -> 0 | F65: S05 › | G65: Jahre 1–3 zählen für die 15 %-Grenze (§ 6 Abs. 1 Nr. 1a EStG)
B66: Geplante Sonderumlagen der WEG im Jahr 1 | C66: =Sonderumlage -> 0 | F66: S05 › | G66: Instandsetzungs-Sonderumlagen: Erhaltungsaufwand, zählen ebenfalls zur 15 %-Grenze
B67: Steuerliche Behandlung der Maßnahmen | C67: =Reno_Behandlung -> Automatisch – 15 %-Grenze prüfen (§ 6 Abs. 1 Nr. 1a EStG) | F67: S05 › | G67: Automatik: netto > 15 % der Gebäude-AK in 3 Jahren → Herstellungskosten (AfA statt Sofortabzug)
B68: Verteilung Erhaltungsaufwand (§ 82b EStDV) | C68: =Verteilung_82b -> 1 | F68: S05 › | G68: 1 Jahr = Sofortabzug; 2–5 Jahre = gleichmäßige Verteilung (nur Privatvermögen, Wohngebäude)
B69: Wertsteigernder Anteil der Maßnahmen | C69: =Reno_Wertsteigerung_Pct -> 1 | F69: S05 › | G69: Anteil, um den der Objektwert steigt (Prognose)
B70: Liquiditätsreserve einmalig | C70: =Reserve_Einmalig -> 5000 | F70: S05 › | G70: Nicht steuerrelevant, z. B. Mieterwechsel – erhöht nur den Eigenkapitalbedarf
B71: Summe Maßnahmen (Jahre 1–3, brutto) | C71: =Reno_J1+Reno_J2+Reno_J3+Sonderumlage -> 12000
B72: Summe Maßnahmen netto (ohne USt) | C72: =Reno_Summe/(1+USt_Satz) -> 10084.034
B73: 15 %-Grenze (Anschaffungskosten Gebäude × 15 %) | C73: =AK_Gebaeude*Grenze_15_Satz -> 36640.177
B75: 6 Miete und Bewirtschaftung Monatswerte, Stand Kauf | L75: ↑ Übersicht
B76: POSITION | C76: WERT | E76: EINHEIT | F76: QUELLE | G76: HINWEIS / STEUERLICHE EINORDNUNG
B77: Nettokaltmiete | C77: =Miete_Monat -> 950 | E77: pro Monat | F77: S02 › | G77: Soll-Miete lt. Mietvertrag bzw. Marktmiete bei Neuvermietung
B78: Umlagefähige Betriebskosten | C78: =NK_umlagefaehig -> 220 | E78: pro Monat | F78: S02 › | G78: Vorauszahlung Mieter – Durchlaufposten (inkl. Grundsteuer); Information für Warmmiete
B79: Hausgeld gesamt (WEG) | C79: =Hausgeld -> 310 | E79: pro Monat | F79: S06 › | G79: Lt. Wirtschaftsplan
B80: davon nicht umlagefähig | C80: =Hausgeld_nicht_umlagefaehig -> 95 | E80: pro Monat | F80: S06 › | G80: Verwaltung WEG, Rücklage, Sonstiges – trägt der Eigentümer
B81: davon Zuführung zur Erhaltungsrücklage | C81: =Hausgeld_Ruecklage -> 60 | E81: pro Monat | F81: S06 › | G81: Im nicht umlagefähigen Hausgeld enthalten – steuerlich erst bei Verausgabung (BFH IX R 19/24)
B82: Mietverwaltung / Sondereigentumsverwaltung | C82: =Verwaltung_Monat -> 25 | E82: pro Monat | F82: S06 › | G82: Werbungskosten
B83: Eigene Instandhaltungsrücklage | C83: =IH_Ruecklage_qm -> 10 | E83: je m² p. a. | F83: S06 › | G83: Kalkulatorisch (Liquidität), nicht steuerwirksam bis zur Verausgabung; Faustwert 8–15 €/m²
B84: Mietausfallwagnis | C84: =Mietausfall_Pct -> 0.03 | E84: der Miete | F84: S06 › | G84: Kalkulatorisch 2–4 %
B85: Anfangsleerstand (Renovierung / Neuvermietung) | C85: =Leerstand_Monate -> 0 | F85: S06 › | G85: Reduziert die Miete im Jahr 1
B86: Sonstige Werbungskosten p. a. | C86: =Sonst_WK_pa -> 300 | E86: pro Jahr | F86: S06 › | G86: Steuerberatung, Kontoführung, Fahrten
B87: Mietsteigerung p. a. | C87: =Mietsteigerung -> 0.02 | F87: S11 › | G87: Prognose; Mietpreisbremse / Kappungsgrenze beachten
B88: Kostensteigerung p. a. | C88: =Kostensteigerung -> 0.02 | F88: S11 › | G88: Prognose
B89: Wertsteigerung p. a. | C89: =Wertsteigerung -> 0.02 | F89: S11 › | G89: Prognose; konservativ 0–2 %
B90: Jahresnettokaltmiete (Soll) | C90: =Miete_Monat*12 -> 11400
B91: Miete je m² | C91: =IF(Wohnflaeche>0,Miete_Monat/Wohnflaeche,0) -> 12.666667
B92: Bruttomietrendite (Jahresmiete / Kaufpreis) | C92: =IF(Kaufpreis>0,Jahresmiete/Kaufpreis,0) -> 0.04
B93: Kaufpreisfaktor (Kaufpreis / Jahresmiete) | C93: =IF(Jahresmiete>0,Kaufpreis/Jahresmiete,0) -> 25
B95: 7 Finanzierung Darlehen II nur hier eingeben | L95: ↑ Übersicht
B96: POSITION | C96: WERT | E96: EINHEIT | F96: QUELLE | G96: HINWEIS / STEUERLICHE EINORDNUNG
B97: Darlehen I – Betrag | C97: =Darlehen_I -> 250000 | F97: S07 › | G97: Bankdarlehen (Annuität)
B98: Darlehen I – Sollzins p. a. | C98: =Zins_I -> 0.036 | F98: S07 ›
B99: Darlehen I – anfängliche Tilgung p. a. | C99: =Tilgung_I -> 0.02 | F99: S07 › | G99: Annuität = (Zins + Tilgung) × Darlehen, konstant
B100: Darlehen I – Zinsbindung | C100: =Zinsbindung_I -> 10 | F100: S07 ›
B101: Darlehen I – Anschlusszins (Annahme) | C101: =Anschlusszins_I -> 0.045 | F101: S07 › | G101: Nach Ablauf der Zinsbindung – Zinsänderungsrisiko; Annuität bleibt konstant
B102: Darlehen I – Sondertilgung p. a. | C102: =Sondertilgung_I -> 0 | E102: pro Jahr | F102: S07 ›
B103: Darlehen I – tilgungsfreie Anlaufjahre | C103: =Tilgungsfrei_I -> 0 | F103: S07 ›
B104: Darlehen II (z. B. KfW) – Betrag | C104: 0 | G104: KfW 261/297/298 oder Nachrangdarlehen
B105: Darlehen II – Sollzins p. a. | C105: 0.025
B106: Darlehen II – anfängliche Tilgung p. a. | C106: 0.03
B107: Darlehen II – Zinsbindung | C107: 10
B108: Darlehen II – Anschlusszins (Annahme) | C108: 0.04
B109: Darlehen II – Sondertilgung p. a. | C109: 0 | E109: pro Jahr
B110: Darlehen II – tilgungsfreie Anlaufjahre | C110: 0 | G110: KfW: i. d. R. 1–5 Jahre
...

Sheet Projektion
B5: BERECHNUNG › PROJEKTION
B6: Projektion | D6: Eingaben dazu: S11 Prognose & Exit ›
B7: Miete, Kosten, Cashflow und Vermögen über 40 Jahre · Beträge in € pro Jahr | D7: ■ Verkaufsjahr · ● negatives Ergebnis · Steuer: + Zahlung / – Erstattung · Jahr 1 = erste 12 Monate ab Kauf
B8: Jahr der Kalkulation | C8: Jahr 0 | D8: 1 | E8: 2 | F8: 3 | G8: 4 | H8: 5 | I8: 6 | J8: 7 | K8: 8 | L8: 9 | M8: 10 | N8: 11 | O8: 12 | P8: 13 | Q8: 14 | R8: 15 | S8: 16 | T8: 17 | U8: 18 | V8: 19 | W8: 20 | X8: 21 | Y8: 22 | Z8: 23 | AA8: 24 | AB8: 25 | AC8: 26 | AD8: 27 | AE8: 28 | AF8: 29 | AG8: 30 | AH8: 31 | AI8: 32 | AJ8: 33 | AK8: 34 | AL8: 35 | AM8: 36 | AN8: 37 | AO8: 38 | AP8: 39 | AQ8: 40
B9: Jahr der Kalkulation | D9: 1 | E9: 2 | F9: 3 | G9: 4 | H9: 5 | I9: 6 | J9: 7 | K9: 8 | L9: 9 | M9: 10 | N9: 11 | O9: 12 | P9: 13 | Q9: 14 | R9: 15 | S9: 16 | T9: 17 | U9: 18 | V9: 19 | W9: 20 | X9: 21 | Y9: 22 | Z9: 23 | AA9: 24 | AB9: 25 | AC9: 26 | AD9: 27 | AE9: 28 | AF9: 29 | AG9: 30 | AH9: 31 | AI9: 32 | AJ9: 33 | AK9: 34 | AL9: 35 | AM9: 36 | AN9: 37 | AO9: 38 | AP9: 39 | AQ9: 40
B10: Kalenderjahr | C10: Kauf | D10: =YEAR(Kaufdatum)+D9-1 -> 2026 | E10: =YEAR(Kaufdatum)+E9-1 -> 2027 | F10: =YEAR(Kaufdatum)+F9-1 -> 2028 | G10: =YEAR(Kaufdatum)+G9-1 -> 2029 | H10: =YEAR(Kaufdatum)+H9-1 -> 2030 | I10: =YEAR(Kaufdatum)+I9-1 -> 2031 | J10: =YEAR(Kaufdatum)+J9-1 -> 2032 | K10: =YEAR(Kaufdatum)+K9-1 -> 2033 | ... AQ10: =YEAR(Kaufdatum)+AQ9-1 -> 2065
B12: Mieteinnahmen | C12: ↑ Übersicht
B13: Nettokaltmiete Soll | C13: € | D13: =Miete_Monat*12*(1+Mietsteigerung)^(D9-1) -> 11400 | E13: =Miete_Monat*12*(1+Mietsteigerung)^(E9-1) -> 11628 | F13: =Miete_Monat*12*(1+Mietsteigerung)^(F9-1) -> 11860.56 | G13: =Miete_Monat*12*(1+Mietsteigerung)^(G9-1) -> 12097.771 | H13: =Miete_Monat*12*(1+Mietsteigerung)^(H9-1) -> 12339.727 | I13: =Miete_Monat*12*(1+Mietsteigerung)^(I9-1) -> 12586.521 | J13: =Miete_Monat*12*(1+Mietsteigerung)^(J9-1) -> 12838.252 | K13: =Miete_Monat*12*(1+Mietsteigerung)^(K9-1) -> 13095.017 | ... AQ13: =Miete_Monat*12*(1+Mietsteigerung)^(AQ9-1) -> 24678.09
B14: – Leerstand / Mietausfallwagnis | C14: € | D14: =D13*(IF(D9=1,MIN(N(Leerstand_Monate),12)/12,0)+Mietausfall_Pct*(1-IF(D9=1,MIN(N(Leerstand_Monate),12)/12,0))) -> 342 | E14: =E13*(IF(E9=1,MIN(N(Leerstand_Monate),12)/12,0)+Mietausfall_Pct*(1-IF(E9=1,MIN(N(Leerstand_Monate),12)/12,0))) -> 348.84 | F14: =F13*(IF(F9=1,MIN(N(Leerstand_Monate),12)/12,0)+Mietausfall_Pct*(1-IF(F9=1,MIN(N(Leerstand_Monate),12)/12,0))) -> 355.8168 | G14: =G13*(IF(G9=1,MIN(N(Leerstand_Monate),12)/12,0)+Mietausfall_Pct*(1-IF(G9=1,MIN(N(Leerstand_Monate),12)/12,0))) -> 362.93314 | H14: =H13*(IF(H9=1,MIN(N(Leerstand_Monate),12)/12,0)+Mietausfall_Pct*(1-IF(H9=1,MIN(N(Leerstand_Monate),12)/12,0))) -> 370.1918 | I14: =I13*(IF(I9=1,MIN(N(Leerstand_Monate),12)/12,0)+Mietausfall_Pct*(1-IF(I9=1,MIN(N(Leerstand_Monate),12)/12,0))) -> 377.59563 | J14: =J13*(IF(J9=1,MIN(N(Leerstand_Monate),12)/12,0)+Mietausfall_Pct*(1-IF(J9=1,MIN(N(Leerstand_Monate),12)/12,0))) -> 385.14755 | K14: =K13*(IF(K9=1,MIN(N(Leerstand_Monate),12)/12,0)+Mietausfall_Pct*(1-IF(K9=1,MIN(N(Leerstand_Monate),12)/12,0))) -> 392.8505 | ... AQ14: =AQ13*(IF(AQ9=1,MIN(N(Leerstand_Monate),12)/12,0)+Mietausfall_Pct*(1-IF(AQ9=1,MIN(N(Leerstand_Monate),12)/12,0))) -> 740.34271
B15: = Nettokaltmiete Ist | C15: € | D15: =D13-D14 -> 11058 | E15: =E13-E14 -> 11279.16 | F15: =F13-F14 -> 11504.743 | G15: =G13-G14 -> 11734.838 | H15: =H13-H14 -> 11969.535 | I15: =I13-I14 -> 12208.926 | J15: =J13-J14 -> 12453.104 | K15: =K13-K14 -> 12702.166 | ... AQ15: =AQ13-AQ14 -> 23937.748
B16: Umlagefähige Betriebskosten (Durchlaufposten) | C16: € | D16: =NK_umlagefaehig*12*(1+Kostensteigerung)^(D9-1) -> 2640 | E16: =NK_umlagefaehig*12*(1+Kostensteigerung)^(E9-1) -> 2692.8 | F16: =NK_umlagefaehig*12*(1+Kostensteigerung)^(F9-1) -> 2746.656 | G16: =NK_umlagefaehig*12*(1+Kostensteigerung)^(G9-1) -> 2801.5891 | H16: =NK_umlagefaehig*12*(1+Kostensteigerung)^(H9-1) -> 2857.6209 | I16: =NK_umlagefaehig*12*(1+Kostensteigerung)^(I9-1) -> 2914.7733 | J16: =NK_umlagefaehig*12*(1+Kostensteigerung)^(J9-1) -> 2973.0688 | K16: =NK_umlagefaehig*12*(1+Kostensteigerung)^(K9-1) -> 3032.5302 | ... AQ16: =NK_umlagefaehig*12*(1+Kostensteigerung)^(AQ9-1) -> 5714.9262
B17: Warmmiete | C17: € | D17: =D15+D16 -> 13698 | E17: =E15+E16 -> 13971.96 | F17: =F15+F16 -> 14251.399 | G17: =G15+G16 -> 14536.427 | H17: =H15+H16 -> 14827.156 | I17: =I15+I16 -> 15123.699 | J17: =J15+J16 -> 15426.173 | K17: =K15+K16 -> 15734.696 | ... AQ17: =AQ15+AQ16 -> 29652.674
B19: Bewirtschaftungskosten · nicht umlagefähig, Zahlungsabfluss | C19: ↑ Übersicht
B20: Hausgeld nicht umlagefähig (ohne Rücklagenzuführung) | C20: € | D20: =MAX(0,Hausgeld_nicht_umlagefaehig-Hausgeld_Ruecklage)*12*(1+Kostensteigerung)^(D9-1) -> 420 | E20: =MAX(0,Hausgeld_nicht_umlagefaehig-Hausgeld_Ruecklage)*12*(1+Kostensteigerung)^(E9-1) -> 428.4 | F20: =MAX(0,Hausgeld_nicht_umlagefaehig-Hausgeld_Ruecklage)*12*(1+Kostensteigerung)^(F9-1) -> 436.968 | G20: =MAX(0,Hausgeld_nicht_umlagefaehig-Hausgeld_Ruecklage)*12*(1+Kostensteigerung)^(G9-1) -> 445.70736 | H20: =MAX(0,Hausgeld_nicht_umlagefaehig-Hausgeld_Ruecklage)*12*(1+Kostensteigerung)^(H9-1) -> 454.62151 | I20: =MAX(0,Hausgeld_nicht_umlagefaehig-Hausgeld_Ruecklage)*12*(1+Kostensteigerung)^(I9-1) -> 463.71394 | J20: =MAX(0,Hausgeld_nicht_umlagefaehig-Hausgeld_Ruecklage)*12*(1+Kostensteigerung)^(J9-1) -> 472.98822 | K20: =MAX(0,Hausgeld_nicht_umlagefaehig-Hausgeld_Ruecklage)*12*(1+Kostensteigerung)^(K9-1) -> 482.44798 | ... AQ20: =MAX(0,Hausgeld_nicht_umlagefaehig-Hausgeld_Ruecklage)*12*(1+Kostensteigerung)^(AQ9-1) -> 909.1928
B21: Zuführung Erhaltungsrücklage WEG | C21: € | D21: =Hausgeld_Ruecklage*12*(1+Kostensteigerung)^(D9-1) -> 720 | E21: =Hausgeld_Ruecklage*12*(1+Kostensteigerung)^(E9-1) -> 734.4 | F21: =Hausgeld_Ruecklage*12*(1+Kostensteigerung)^(F9-1) -> 749.088 | G21: =Hausgeld_Ruecklage*12*(1+Kostensteigerung)^(G9-1) -> 764.06976 | H21: =Hausgeld_Ruecklage*12*(1+Kostensteigerung)^(H9-1) -> 779.35116 | I21: =Hausgeld_Ruecklage*12*(1+Kostensteigerung)^(I9-1) -> 794.93818 | J21: =Hausgeld_Ruecklage*12*(1+Kostensteigerung)^(J9-1) -> 810.83694 | K21: =Hausgeld_Ruecklage*12*(1+Kostensteigerung)^(K9-1) -> 827.05368 | ... AQ21: =Hausgeld_Ruecklage*12*(1+Kostensteigerung)^(AQ9-1) -> 1558.6162
B22: Mietverwaltung / SEV | C22: € | D22: =Verwaltung_Monat*12*(1+Kostensteigerung)^(D9-1) -> 300 | E22: =Verwaltung_Monat*12*(1+Kostensteigerung)^(E9-1) -> 306 | F22: =Verwaltung_Monat*12*(1+Kostensteigerung)^(F9-1) -> 312.12 | G22: =Verwaltung_Monat*12*(1+Kostensteigerung)^(G9-1) -> 318.3624 | H22: =Verwaltung_Monat*12*(1+Kostensteigerung)^(H9-1) -> 324.72965 | I22: =Verwaltung_Monat*12*(1+Kostensteigerung)^(I9-1) -> 331.22424 | J22: =Verwaltung_Monat*12*(1+Kostensteigerung)^(J9-1) -> 337.84873 | K22: =Verwaltung_Monat*12*(1+Kostensteigerung)^(K9-1) -> 344.6057 | ... AQ22: =Verwaltung_Monat*12*(1+Kostensteigerung)^(AQ9-1) -> 649.42343
B23: Sonstige Werbungskosten | C23: € | D23: =Sonst_WK_pa*(1+Kostensteigerung)^(D9-1) -> 300 | E23: =Sonst_WK_pa*(1+Kostensteigerung)^(E9-1) -> 306 | F23: =Sonst_WK_pa*(1+Kostensteigerung)^(F9-1) -> 312.12 | G23: =Sonst_WK_pa*(1+Kostensteigerung)^(G9-1) -> 318.3624 | H23: =Sonst_WK_pa*(1+Kostensteigerung)^(H9-1) -> 324.72965 | I23: =Sonst_WK_pa*(1+Kostensteigerung)^(I9-1) -> 331.22424 | J23: =Sonst_WK_pa*(1+Kostensteigerung)^(J9-1) -> 337.84873 | K23: =Sonst_WK_pa*(1+Kostensteigerung)^(K9-1) -> 344.6057 | ... AQ23: =Sonst_WK_pa*(1+Kostensteigerung)^(AQ9-1) -> 649.42343
B24: Eigene Instandhaltungsrücklage (kalkulatorisch) | C24: € | D24: =IH_Ruecklage_qm*Wohnflaeche*(1+Kostensteigerung)^(D9-1) -> 750 | E24: =IH_Ruecklage_qm*Wohnflaeche*(1+Kostensteigerung)^(E9-1) -> 765 | F24: =IH_Ruecklage_qm*Wohnflaeche*(1+Kostensteigerung)^(F9-1) -> 780.3 | G24: =IH_Ruecklage_qm*Wohnflaeche*(1+Kostensteigerung)^(G9-1) -> 795.906 | H24: =IH_Ruecklage_qm*Wohnflaeche*(1+Kostensteigerung)^(H9-1) -> 811.82412 | I24: =IH_Ruecklage_qm*Wohnflaeche*(1+Kostensteigerung)^(I9-1) -> 828.0606 | J24: =IH_Ruecklage_qm*Wohnflaeche*(1+Kostensteigerung)^(J9-1) -> 844.62181 | K24: =IH_Ruecklage_qm*Wohnflaeche*(1+Kostensteigerung)^(K9-1) -> 861.51425 | ... AQ24: =IH_Ruecklage_qm*Wohnflaeche*(1+Kostensteigerung)^(AQ9-1) -> 1623.5586
B25: Renovierung Jahre 2–3 (Jahr 1 in der Investition enthalten) | C25: € | D25: =IF(D9=2,Reno_J2,IF(D9=3,Reno_J3,0)) -> 0 | E25: =IF(E9=2,Reno_J2,IF(E9=3,Reno_J3,0)) -> 0 | F25: =IF(F9=2,Reno_J2,IF(F9=3,Reno_J3,0)) -> 0 | G25: =IF(G9=2,Reno_J2,IF(G9=3,Reno_J3,0)) -> 0 | H25: =IF(H9=2,Reno_J2,IF(H9=3,Reno_J3,0)) -> 0 | I25: =IF(I9=2,Reno_J2,IF(I9=3,Reno_J3,0)) -> 0 | J25: =IF(J9=2,Reno_J2,IF(J9=3,Reno_J3,0)) -> 0 | K25: =IF(K9=2,Reno_J2,IF(K9=3,Reno_J3,0)) -> 0 | ... AQ25: =IF(AQ9=2,Reno_J2,IF(AQ9=3,Reno_J3,0)) -> 0
B26: = Bewirtschaftungskosten gesamt | C26: € | D26: =SUM(D20:D25) -> 2490 | E26: =SUM(E20:E25) -> 2539.8 | F26: =SUM(F20:F25) -> 2590.596 | G26: =SUM(G20:G25) -> 2642.4079 | H26: =SUM(H20:H25) -> 2695.2561 | I26: =SUM(I20:I25) -> 2749.1612 | J26: =SUM(J20:J25) -> 2804.1444 | K26: =SUM(K20:K25) -> 2860.2273 | ... AQ26: =SUM(AQ20:AQ25) -> 5390.2145
B28: Cashflow | C28: ↑ Übersicht
B29: = Einnahmenüberschuss vor Finanzierung (NOI) | C29: € | D29: =D15-D26 -> 8568 | E29: =E15-E26 -> 8739.36 | F29: =F15-F26 -> 8914.1472 | G29: =G15-G26 -> 9092.4301 | H29: =H15-H26 -> 9274.2787 | I29: =I15-I26 -> 9459.7643 | J29: =J15-J26 -> 9648.9596 | K29: =K15-K26 -> 9841.9388 | ... AQ29: =AQ15-AQ26 -> 18547.533
B30: Zinsen | C30: € | D30: =Finanzierung!D35 -> 9000 | E30: =Finanzierung!E35 -> 8820 | F30: =Finanzierung!F35 -> 8633.52 | G30: =Finanzierung!G35 -> 8440.3267 | H30: =Finanzierung!H35 -> 8240.1785 | I30: =Finanzierung!I35 -> 8032.8249 | J30: =Finanzierung!J35 -> 7818.0066 | K30: =Finanzierung!K35 -> 7595.4548 | ... AQ30: =Finanzierung!AQ35 -> 0
B31: Tilgung (inkl. Sondertilgung) | C31: € | D31: =Finanzierung!D36 -> 5000 | E31: =Finanzierung!E36 -> 5180 | F31: =Finanzierung!F36 -> 5366.48 | G31: =Finanzierung!G36 -> 5559.6733 | H31: =Finanzierung!H36 -> 5759.8215 | I31: =Finanzierung!I36 -> 5967.1751 | J31: =Finanzierung!J36 -> 6181.9934 | K31: =Finanzierung!K36 -> 6404.5452 | ... AQ31: =Finanzierung!AQ36 -> 0
B32: – Kapitaldienst (Zinsen + Tilgung inkl. Sondertilgung) | C32: € | D32: =D30+D31 -> 14000 | E32: =E30+E31 -> 14000 | F32: =F30+F31 -> 14000 | G32: =G30+G31 -> 14000 | H32: =H30+H31 -> 14000 | I32: =I30+I31 -> 14000 | J32: =J30+J31 -> 14000 | K32: =K30+K31 -> 14000 | ... AQ32: =AQ30+AQ31 -> 0
B33: = Cashflow vor Steuern | C33: € | D33: =D29-D32 -> -5432 | E33: =E29-E32 -> -5260.64 | F33: =F29-F32 -> -5085.8528 | G33: =G29-G32 -> -4907.5699 | H33: =H29-H32 -> -4725.7213 | I33: =I29-I32 -> -4540.2357 | J33: =J29-J32 -> -4351.0404 | K33: =K29-K32 -> -4158.0612 | ... AQ33: =AQ29-AQ32 -> 18547.533
B34: Info: Steuerliches Ergebnis | C34: € | D34: =Steuern!D67 -> -18397.357 | E34: =Steuern!E67 -> -4266.5969 | F34: =Steuern!F67 -> -3875.3417 | G34: =Steuern!G67 -> -3473.2778 | H34: =Steuern!H67 -> -3060.0814 | I34: =Steuern!I67 -> -2635.4187 | J34: =Steuern!J67 -> -2198.9452 | K34: =Steuern!K67 -> -1750.305 | ... AQ34: =Steuern!AQ67 -> 16844.351
B35: – Steuer (+ Zahlung / – Erstattung) | C35: € | D35: =Steuern!D73 -> -8510.3965 | E35: =Steuern!E73 -> -1973.6765 | F35: =Steuern!F73 -> -1792.6866 | G35: =Steuern!G73 -> -1606.6966 | H35: =Steuern!H73 -> -1415.5569 | I35: =Steuern!I73 -> -1219.1131 | J35: =Steuern!J73 -> -1017.2056 | K35: =Steuern!K73 -> -809.67011 | ... AQ35: =Steuern!AQ73 -> 7791.9947
B36: = Cashflow nach Steuern | C36: € | D36: =D33-D35 -> 3078.3965 | E36: =E33-E35 -> -3286.9635 | F36: =F33-F35 -> -3293.1662 | G36: =G33-G35 -> -3300.8732 | H36: =H33-H35 -> -3310.1643 | I36: =I33-I35 -> -3321.1226 | J36: =J33-J35 -> -3333.8347 | K36: =K33-K35 -> -3348.3911 | ... AQ36: =AQ33-AQ35 -> 10755.539
B37: Cashflow nach Steuern pro Monat | C37: € | D37: =D36/12 -> 256.53305 | E37: =E36/12 -> -273.91362 | F37: =F36/12 -> -274.43052 | G37: =G36/12 -> -275.07277 | H37: =H36/12 -> -275.84703 | I37: =I36/12 -> -276.76022 | J37: =J36/12 -> -277.81956 | K37: =K36/12 -> -279.03259 | ... AQ37: =AQ36/12 -> 896.29488
B38: Kumulierter Cashflow nach Steuern | C38: € | D38: =D36 -> 3078.3965 | E38: =D38+E36 -> -208.56691 | F38: =E38+F36 -> -3501.7331 | G38: =F38+G36 -> -6802.6064 | H38: =G38+H36 -> -10112.771 | I38: =H38+I36 -> -13433.893 | J38: =I38+J36 -> -16767.728 | K38: =J38+K36 -> -20116.119 | L38: =K38+L36 -> -23481.005 | ... AQ38: =AP38+AQ36 -> -16195.544
B40: Vermögensentwicklung | C40: ↑ Übersicht
B41: Immobilienwert Jahresende (Prognose) | C41: € | D41: =(Kaufpreis+Investition_J1*Reno_Wertsteigerung_Pct)*(1+Wertsteigerung) -> 302940 | E41: =D41*(1+Wertsteigerung)+E25*Reno_Wertsteigerung_Pct -> 308998.8 | F41: =E41*(1+Wertsteigerung)+F25*Reno_Wertsteigerung_Pct -> 315178.78 | G41: =F41*(1+Wertsteigerung)+G25*Reno_Wertsteigerung_Pct -> 321482.35 | H41: =G41*(1+Wertsteigerung)+H25*Reno_Wertsteigerung_Pct -> 327912 | I41: =H41*(1+Wertsteigerung)+I25*Reno_Wertsteigerung_Pct -> 334470.24 | J41: =I41*(1+Wertsteigerung)+J25*Reno_Wertsteigerung_Pct -> 341159.64 | K41: =J41*(1+Wertsteigerung)+K25*Reno_Wertsteigerung_Pct -> 347982.84 | L41: =K41*(1+Wertsteigerung)+L25*Reno_Wertsteigerung_Pct -> 354942.49 | ... AQ41: =AP41*(1+Wertsteigerung)+AQ25*Reno_Wertsteigerung_Pct -> 655787.78
B42: – Restschuld Jahresende | C42: € | D42: =Finanzierung!D38 -> 245000 | E42: =Finanzierung!E38 -> 239820 | F42: =Finanzierung!F38 -> 234453.52 | G42: =Finanzierung!G38 -> 228893.85 | H42: =Finanzierung!H38 -> 223134.03 | I42: =Finanzierung!I38 -> 217166.85 | J42: =Finanzierung!J38 -> 210984.86 | K42: =Finanzierung!K38 -> 204580.31 | ... AQ42: =Finanzierung!AQ38 -> 0
B43: = Nettovermögen | C43: € | D43: =D41-D42 -> 57940 | E43: =E41-E42 -> 69178.8 | F43: =F41-F42 -> 80725.256 | G43: =G41-G42 -> 92588.505 | H43: =H41-H42 -> 104777.97 | I43: =I41-I42 -> 117303.39 | J43: =J41-J42 -> 130174.79 | K43: =K41-K42 -> 143402.52 | ... AQ43: =AQ41-AQ42 -> 655787.78
B44: Vermögenszuwachs im Jahr | C44: € | D44: =D36+(Darlehen_Summe-D42)+(D41-(Kaufpreis+Investition_J1*Reno_Wertsteigerung_Pct)) -> 14018.397 | E44: =E36+(D42-E42)+(E41-D41) -> 7951.8365 | F44: =F36+(E42-F42)+(F41-E41) -> 8253.2898 | G44: =G36+(F42-G42)+(G41-F41) -> 8562.3756 | H44: =H36+(G42-H42)+(H41-G41) -> 8879.3042 | I44: =I36+(H42-I42)+(I41-H41) -> 9204.2925 | J44: =J36+(I42-J42)+(J41-I41) -> 9537.5634 | K44: =K36+(J42-K42)+(K41-J41) -> 9879.3469 | L44: =L36+(K42-L42)+(L41-K41) -> 10229.88 | ... AQ44: =AQ36+(AP42-AQ42)+(AQ41-AP41) -> 23614.122
B45: Eigenkapitalrendite (Vermögenszuwachs / Eigenkapital) | C45: % | D45: =IF(Eigenkapital>0,D44/Eigenkapital,0) -> 0.17750535 | E45: =IF(Eigenkapital>0,E44/Eigenkapital,0) -> 0.10068866 | F45: =IF(Eigenkapital>0,F44/Eigenkapital,0) -> 0.10450576 | G45: =IF(Eigenkapital>0,G44/Eigenkapital,0) -> 0.1084195 | H45: =IF(Eigenkapital>0,H44/Eigenkapital,0) -> 0.11243255 | I45: =IF(Eigenkapital>0,I44/Eigenkapital,0) -> 0.11654765 | J45: =IF(Eigenkapital>0,J44/Eigenkapital,0) -> 0.12076763 | K45: =IF(Eigenkapital>0,K44/Eigenkapital,0) -> 0.1250954 | ... AQ45: =IF(Eigenkapital>0,AQ44/Eigenkapital,0) -> 0.29900946
B46: Kumulierte Steuer | C46: € | D46: =Steuern!D74 -> -8510.3965 | E46: =Steuern!E74 -> -10484.073 | F46: =Steuern!F74 -> -12276.76 | G46: =Steuern!G74 -> -13883.456 | H46: =Steuern!H74 -> -15299.013 | I46: =Steuern!I74 -> -16518.126 | J46: =Steuern!J74 -> -17535.332 | K46: =Steuern!K74 -> -18345.002 | ... AQ46: =Steuern!AQ74 -> 90751.898
B48: Exit-Cashflow · Basis für die Eigenkapitalrendite (IRR) | C48: ↑ Übersicht
B49: = Exit-Cashflow (Jahr 0 = Eigenkapitaleinsatz) | C49: =-Eigenkapital -> -78974.5 | D49: =IF(D9<Haltedauer,D36,IF(D9=Haltedauer,D36+Exit_Netto,0)) -> 3078.3965 | E49: =IF(E9<Haltedauer,E36,IF(E9=Haltedauer,E36+Exit_Netto,0)) -> -3286.9635 | F49: =IF(F9<Haltedauer,F36,IF(F9=Haltedauer,F36+Exit_Netto,0)) -> -3293.1662 | G49: =IF(G9<Haltedauer,G36,IF(G9=Haltedauer,G36+Exit_Netto,0)) -> -3300.8732 | H49: =IF(H9<Haltedauer,H36,IF(H9=Haltedauer,H36+Exit_Netto,0)) -> -3310.1643 | I49: =IF(I9<Haltedauer,I36,IF(I9=Haltedauer,I36+Exit_Netto,0)) -> -3321.1226 | J49: =IF(J9<Haltedauer,J36,IF(J9=Haltedauer,J36+Exit_Netto,0)) -> -3333.8347 | K49: =IF(K9<Haltedauer,K36,IF(K9=Haltedauer,K36+Exit_Netto,0)) -> -3348.3911 | ... AQ49: =IF(AQ9<Haltedauer,AQ36,IF(AQ9=Haltedauer,AQ36+Exit_Netto,0)) -> 0
B51: Keine Gewähr für die Richtigkeit der Angaben · ersetzt keine Rechts-, Steuer- oder Finanzberatung · Rechtsstand September 2026
B52: MM Holding GmbH · Kornhausgasse 4 · 88250 Weingarten · Amtsgericht Ulm HRB 750729

Sheet Steuern
B5: STEUERN › STEUER-TABELLE
B6: Steuer-Tabelle | D6: Eingaben dazu: S09 Steuern ›
B7: Abgeleitete Parameter, AfA-Verlauf und steuerliches Ergebnis über 40 Jahre | D7: ■ Verkaufsjahr · ● negatives Ergebnis · Steuer: + Zahlung / – Erstattung (Verrechnung mit anderen Einkünften)
B8: Abgeleitete steuerliche Parameter · über die Gliederung links einklappbar | I8: ↓ Jahrestabelle | L8: ↓ Verkaufsszenario
B9: Index Objektart (technisch) | C9: =IFERROR(MATCH(Objektart,L_Objektart,0),1) -> 1
B10: Index Methode Kaufpreisaufteilung (technisch) | C10: =IFERROR(MATCH(KPA_Methode,L_KPA,0),1) -> 1
B11: Index Behandlung Renovierung (technisch) | C11: =IFERROR(MATCH(Reno_Behandlung,L_Reno,0),1) -> 1
B12: Index Rechtsform (technisch) | C12: =IFERROR(MATCH(Rechtsform,L_Rechtsform,0),1) -> 1 | E12: 1 = Privat, 2 = vvGmbH, 3 = GmbH gewerblich
B13: Index Veranlagung (technisch) | C13: =IFERROR(MATCH(Veranlagung,L_Veranlagung,0),1) -> 1
B14: Index Kirchensteuer (technisch) | C14: =IFERROR(MATCH(KiSt,L_KiSt,0),1) -> 2
B15: Index AfA-Methode (gewählt) | C15: =IFERROR(MATCH(AfA_Methode,L_AfA,0),1) -> 1
B16: Index Verlustverrechnung (technisch) | C16: =IFERROR(MATCH(Verlustverrechnung,L_Verlust,0),1) -> 1
B17: Wohngebäude | C17: =IF(Objektart_Idx=4,0,1) -> 1 | E17: Gewerbeeinheit: keine § 7b / keine degressive AfA
B18: Solidaritätszuschlag effektiv | C18: =IF(AND(Rechtsform_Idx=1,Soli="Ja"),Soli_Konst,0) -> 0.055 | E18: auf die ESt (Privat); GmbH: separat auf die KSt
B19: Kirchensteuersatz effektiv | C19: =IF(Rechtsform_Idx=1,CHOOSE(KiSt_Idx,0,KiSt_8,KiSt_9),0) -> 0.08
B20: Gewerbesteuersatz effektiv (Messzahl × Hebesatz) | C20: =IF(Rechtsform_Idx=3,GewSt_Messzahl*Hebesatz,0) -> 0 | E20: 0 bei Privatperson und bei erweiterter Kürzung
B21: Sofortige Verlustverrechnung | C21: =IF(AND(Rechtsform_Idx=1,Verlust_Idx=1),1,0) -> 1 | E21: sonst Verlustvortrag
B22: Verteilungszeitraum Erhaltungsaufwand (angewendet) | C22: =IF(Rechtsform_Idx=1,MAX(1,MIN(Max_82b,N(Verteilung_82b))),1) -> 1 | E22: § 82b EStDV nur im Privatvermögen
B23: Disagio sofort abziehbar | C23: =IF(AND(Disagio_Pct<=Disagio_Grenze,Zinsbindung_I>=Disagio_Jahre),1,0) -> 1 | E23: sonst Verteilung über die Zinsbindung
B24: AfA-Methode angewendet (Index) | C24: =IF(AND(AfA_Idx=5,OR(Baujahr<2023,Wohngebaeude=0)),1,IF(AND(AfA_Idx=6,N(RND_Gutachten)<=0),1,AfA_Idx)) -> 1 | E24: Fallback auf „Automatisch“, wenn Voraussetzungen fehlen (siehe Prüfhinweise im Cockpit)
B25: Linearer AfA-Satz nach Baujahr (Standard) | C25: =IF(AND(Wohngebaeude=0,Rechtsform_Idx>1),0.03,IF(Baujahr<1925,IF(Baujahr>0,0.025,0.02),IF(Baujahr>=2023,0.03,0.02))) -> 0.02 | E25: § 7 Abs. 4 S. 1 EStG
B26: Linearer AfA-Satz angewendet | C26: =IF(Methode_eff=6,1/MAX(N(RND_Gutachten),1),CHOOSE(Methode_eff,AfA_Satz_auto,0.02,0.025,0.03,0.03,0)) -> 0.02 | E26: bei degressiver Methode: Satz für den späteren Wechsel (3 %)
B27: Typisierte Nutzungsdauer | C27: =1/AfA_Satz_linear -> 50 | E27: Basis für Restwert-AfA nach § 7a Abs. 9 / § 7 Abs. 5a S. 4 EStG
B28: Degressive AfA aktiv | C28: =IF(Methode_eff=5,1,0) -> 0
B29: Begünstigte Sanierungskosten § 7h/7i (angewendet) | C29: =IF(AND(Denkmal="Ja",N(Sanierungskosten_7i)>0),MIN(Sanierungskosten_7i,AK_Gebaeude),0) -> 0
B30: AfA-Bemessungsgrundlage Gebäude (ohne Sanierungsanteil) | C30: =AK_Gebaeude-Sanierung_eff -> 244267.85 | E30: zzgl. später aktivierter Herstellungskosten
B31: Anschaffungskosten Gebäude je m² Wohnfläche | C31: =IF(Wohnflaeche>0,AK_Gebaeude/Wohnflaeche,0) -> 3256.9046 | E31: Prüfgröße § 7b (Obergrenze 5.200 €/m²)
B32: Sonder-AfA § 7b aktiv | C32: =IF(AND(SonderAfA_7b="Ja",Wohngebaeude=1,Baujahr>=2023,Baukosten_qm<=Grenze_7b_Baukosten),1,0) -> 0 | E32: Neubau ab 2023, Wohnzwecke, Baukostenobergrenze eingehalten
B33: Sonder-AfA § 7b – Bemessungsgrundlage | C33: =IF(SonderAfA_aktiv=1,MIN(BMG_Regel_Basis,Grenze_7b_BMG*Wohnflaeche),0) -> 0 | E33: max. 4.000 €/m²
B34: Sonder-AfA § 7b p. a. (Jahre 1–4) | C34: =SonderAfA_BMG*SonderAfA_Satz -> 0
B35: Renovierung als Herstellungskosten aktivieren | C35: =IF(Reno_Idx=3,1,IF(Reno_Idx=2,0,IF(Reno_Netto>Grenze_15,1,0))) -> 0 | E35: § 6 Abs. 1 Nr. 1a EStG
B36: Maßnahmen Jahr 1 (Renovierung + Sonderumlage) | C36: =Reno_J1+Sonderumlage -> 12000
B37: Standard-AfA Jahr 1 (linear nach Baujahr, ohne Sonder-AfA) | C37: =AfA_Satz_auto*BMG_Regel_Basis -> 4885.3569 | E37: Vergleichsmaßstab
B40: Jahr der Kalkulation | D40: 1 | E40: 2 | F40: 3 | G40: 4 | H40: 5 | I40: 6 | J40: 7 | K40: 8 | L40: 9 | M40: 10 | N40: 11 | O40: 12 | P40: 13 | Q40: 14 | R40: 15 | S40: 16 | T40: 17 | U40: 18 | V40: 19 | W40: 20 | X40: 21 | Y40: 22 | Z40: 23 | AA40: 24 | AB40: 25 | AC40: 26 | AD40: 27 | AE40: 28 | AF40: 29 | AG40: 30 | AH40: 31 | AI40: 32 | AJ40: 33 | AK40: 34 | AL40: 35 | AM40: 36 | AN40: 37 | AO40: 38 | AP40: 39 | AQ40: 40
B41: Jahr der Kalkulation | D41: 1 | E41: 2 | F41: 3 | G41: 4 | H41: 5 | I41: 6 | J41: 7 | K41: 8 | L41: 9 | M41: 10 | N41: 11 | O41: 12 | P41: 13 | Q41: 14 | R41: 15 | S41: 16 | T41: 17 | U41: 18 | V41: 19 | W41: 20 | X41: 21 | Y41: 22 | Z41: 23 | AA41: 24 | AB41: 25 | AC41: 26 | AD41: 27 | AE41: 28 | AF41: 29 | AG41: 30 | AH41: 31 | AI41: 32 | AJ41: 33 | AK41: 34 | AL41: 35 | AM41: 36 | AN41: 37 | AO41: 38 | AP41: 39 | AQ41: 40
B42: Kalenderjahr | D42: =YEAR(Kaufdatum)+D41-1 -> 2026 | E42: =YEAR(Kaufdatum)+E41-1 -> 2027 | F42: =YEAR(Kaufdatum)+F41-1 -> 2028 | G42: =YEAR(Kaufdatum)+G41-1 -> 2029 | H42: =YEAR(Kaufdatum)+H41-1 -> 2030 | I42: =YEAR(Kaufdatum)+I41-1 -> 2031 | J42: =YEAR(Kaufdatum)+J41-1 -> 2032 | K42: =YEAR(Kaufdatum)+K41-1 -> 2033 | ... AQ42: =YEAR(Kaufdatum)+AQ41-1 -> 2065
B44: Abschreibung (AfA) | C44: ↑ Übersicht | D44: =D$42 -> 2026 | E44: =E$42 -> 2027 | F44: =F$42 -> 2028 | G44: =G$42 -> 2029 | H44: =H$42 -> 2030 | I44: =I$42 -> 2031 | J44: =J$42 -> 2032 | K44: =K$42 -> 2033 | ... AQ44: =AQ$42 -> 2065
B45: Nachträgliche Herstellungskosten (aktivierte Maßnahmen) | C45: € | D45: =IF(HK_Flag=1,IF(D41=1,Investition_J1,IF(D41=2,Reno_J2,IF(D41=3,Reno_J3,0))),0) -> 0 | E45: =IF(HK_Flag=1,IF(E41=1,Investition_J1,IF(E41=2,Reno_J2,IF(E41=3,Reno_J3,0))),0) -> 0 | F45: =IF(HK_Flag=1,IF(F41=1,Investition_J1,IF(F41=2,Reno_J2,IF(F41=3,Reno_J3,0))),0) -> 0 | G45: =IF(HK_Flag=1,IF(G41=1,Investition_J1,IF(G41=2,Reno_J2,IF(G41=3,Reno_J3,0))),0) -> 0 | H45: =IF(HK_Flag=1,IF(H41=1,Investition_J1,IF(H41=2,Reno_J2,IF(H41=3,Reno_J3,0))),0) -> 0 | I45: =IF(HK_Flag=1,IF(I41=1,Investition_J1,IF(I41=2,Reno_J2,IF(I41=3,Reno_J3,0))),0) -> 0 | J45: =IF(HK_Flag=1,IF(J41=1,Investition_J1,IF(J41=2,Reno_J2,IF(J41=3,Reno_J3,0))),0) -> 0 | K45: =IF(HK_Flag=1,IF(K41=1,Investition_J1,IF(K41=2,Reno_J2,IF(K41=3,Reno_J3,0))),0) -> 0 | ... AQ45: =IF(HK_Flag=1,IF(AQ41=1,Investition_J1,IF(AQ41=2,Reno_J2,IF(AQ41=3,Reno_J3,0))),0) -> 0
B46: Kumulierte nachträgliche Herstellungskosten | C46: € | D46: =D45 -> 0 | E46: =D46+E45 -> 0 | F46: =E46+F45 -> 0 | G46: =F46+G45 -> 0 | H46: =G46+H45 -> 0 | I46: =H46+I45 -> 0 | J46: =I46+J45 -> 0 | K46: =J46+K45 -> 0 | L46: =K46+L45 -> 0 | ... AQ46: =AP46+AQ45 -> 0
B47: AfA-Bemessungsgrundlage Gebäude (kumuliert) | C47: € | D47: =BMG_Regel_Basis+D46 -> 244267.85 | E47: =BMG_Regel_Basis+E46 -> 244267.85 | F47: =BMG_Regel_Basis+F46 -> 244267.85 | G47: =BMG_Regel_Basis+G46 -> 244267.85 | H47: =BMG_Regel_Basis+H46 -> 244267.85 | I47: =BMG_Regel_Basis+I46 -> 244267.85 | J47: =BMG_Regel_Basis+J46 -> 244267.85 | K47: =BMG_Regel_Basis+K46 -> 244267.85 | ... AQ47: =BMG_Regel_Basis+AQ46 -> 244267.85
B48: Restwert Gebäude Jahresbeginn | C48: € | D48: =D47 -> 244267.85 | E48: =E47-D52 -> 239382.49 | F48: =F47-E52 -> 234497.13 | G48: =G47-F52 -> 229611.78 | H48: =H47-G52 -> 224726.42 | I48: =I47-H52 -> 219841.06 | J48: =J47-I52 -> 214955.71 | K48: =K47-J52 -> 210070.35 | L48: =L47-K52 -> 205184.99 | ... AQ48: =AQ47-AP52 -> 53738.926
B49: Reguläre Gebäude-AfA (gewählte Methode) | C49: € | D49: =IF(Is_Degressiv=1,MIN(D48,MAX(Degressiv_Satz*D48,IF(Wechsel_linear="Ja",D48/MAX(ND_lin-(D41-1),1),0))),MIN(D48,IF(AND(SonderAfA_aktiv=1,D41>SonderAfA_Jahre),$G$53/MAX(ND_lin-SonderAfA_Jahre,1),AfA_Satz_linear*D47))) -> 4885.3569 | E49: =IF(Is_Degressiv=1,MIN(E48,MAX(Degressiv_Satz*E48,IF(Wechsel_linear="Ja",E48/MAX(ND_lin-(E41-1),1),0))),MIN(E48,IF(AND(SonderAfA_aktiv=1,E41>SonderAfA_Jahre),$G$53/MAX(ND_lin-SonderAfA_Jahre,1),AfA_Satz_linear*E47))) -> 4885.3569 | F49: =IF(Is_Degressiv=1,MIN(F48,MAX(Degressiv_Satz*F48,IF(Wechsel_linear="Ja",F48/MAX(ND_lin-(F41-1),1),0))),MIN(F48,IF(AND(SonderAfA_aktiv=1,F41>SonderAfA_Jahre),$G$53/MAX(ND_lin-SonderAfA_Jahre,1),AfA_Satz_linear*F47))) -> 4885.3569 | G49: =IF(Is_Degressiv=1,MIN(G48,MAX(Degressiv_Satz*G48,IF(Wechsel_linear="Ja",G48/MAX(ND_lin-(G41-1),1),0))),MIN(G48,IF(AND(SonderAfA_aktiv=1,G41>SonderAfA_Jahre),$G$53/MAX(ND_lin-SonderAfA_Jahre,1),AfA_Satz_linear*G47))) -> 4885.3569 | H49: =IF(Is_Degressiv=1,MIN(H48,MAX(Degressiv_Satz*H48,IF(Wechsel_linear="Ja",H48/MAX(ND_lin-(H41-1),1),0))),MIN(H48,IF(AND(SonderAfA_aktiv=1,H41>SonderAfA_Jahre),$G$53/MAX(ND_lin-SonderAfA_Jahre,1),AfA_Satz_linear*H47))) -> 4885.3569 | I49: =IF(Is_Degressiv=1,MIN(I48,MAX(Degressiv_Satz*I48,IF(Wechsel_linear="Ja",I48/MAX(ND_lin-(I41-1),1),0))),MIN(I48,IF(AND(SonderAfA_aktiv=1,I41>SonderAfA_Jahre),$G$53/MAX(ND_lin-SonderAfA_Jahre,1),AfA_Satz_linear*I47))) -> 4885.3569 | J49: =IF(Is_Degressiv=1,MIN(J48,MAX(Degressiv_Satz*J48,IF(Wechsel_linear="Ja",J48/MAX(ND_lin-(J41-1),1),0))),MIN(J48,IF(AND(SonderAfA_aktiv=1,J41>SonderAfA_Jahre),$G$53/MAX(ND_lin-SonderAfA_Jahre,1),AfA_Satz_linear*J47))) -> 4885.3569 | K49: =IF(Is_Degressiv=1,MIN(K48,MAX(Degressiv_Satz*K48,IF(Wechsel_linear="Ja",K48/MAX(ND_lin-(K41-1),1),0))),MIN(K48,IF(AND(SonderAfA_aktiv=1,K41>SonderAfA_Jahre),$G$53/MAX(ND_lin-SonderAfA_Jahre,1),AfA_Satz_linear*K47))) -> 4885.3569 | ... AQ49: =IF(Is_Degressiv=1,MIN(AQ48,MAX(Degressiv_Satz*AQ48,IF(Wechsel_linear="Ja",AQ48/MAX(ND_lin-(AQ41-1),1),0))),MIN(AQ48,IF(AND(SonderAfA_aktiv=1,AQ41>SonderAfA_Jahre),$G$53/MAX(ND_lin-SonderAfA_Jahre,1),AfA_Satz_linear*AQ47))) -> 4885.3569
B50: Sonder-AfA § 7b EStG | C50: € | D50: =IF(AND(SonderAfA_aktiv=1,D41<=SonderAfA_Jahre),MIN(SonderAfA_Betrag_pa,MAX(0,D48-D49)),0) -> 0 | E50: =IF(AND(SonderAfA_aktiv=1,E41<=SonderAfA_Jahre),MIN(SonderAfA_Betrag_pa,MAX(0,E48-E49)),0) -> 0 | F50: =IF(AND(SonderAfA_aktiv=1,F41<=SonderAfA_Jahre),MIN(SonderAfA_Betrag_pa,MAX(0,F48-F49)),0) -> 0 | G50: =IF(AND(SonderAfA_aktiv=1,G41<=SonderAfA_Jahre),MIN(SonderAfA_Betrag_pa,MAX(0,G48-G49)),0) -> 0 | H50: =IF(AND(SonderAfA_aktiv=1,H41<=SonderAfA_Jahre),MIN(SonderAfA_Betrag_pa,MAX(0,H48-H49)),0) -> 0 | I50: =IF(AND(SonderAfA_aktiv=1,I41<=SonderAfA_Jahre),MIN(SonderAfA_Betrag_pa,MAX(0,I48-I49)),0) -> 0 | J50: =IF(AND(SonderAfA_aktiv=1,J41<=SonderAfA_Jahre),MIN(SonderAfA_Betrag_pa,MAX(0,J48-J49)),0) -> 0 | K50: =IF(AND(SonderAfA_aktiv=1,K41<=SonderAfA_Jahre),MIN(SonderAfA_Betrag_pa,MAX(0,K48-K49)),0) -> 0 | ... AQ50: =IF(AND(SonderAfA_aktiv=1,AQ41<=SonderAfA_Jahre),MIN(SonderAfA_Betrag_pa,MAX(0,AQ48-AQ49)),0) -> 0
B51: = AfA Gebäude (regulär + Sonder-AfA) | C51: € | D51: =D49+D50 -> 4885.3569 | E51: =E49+E50 -> 4885.3569 | F51: =F49+F50 -> 4885.3569 | G51: =G49+G50 -> 4885.3569 | H51: =H49+H50 -> 4885.3569 | I51: =I49+I50 -> 4885.3569 | J51: =J49+J50 -> 4885.3569 | K51: =K49+K50 -> 4885.3569 | ... AQ51: =AQ49+AQ50 -> 4885.3569
B52: Kumulierte AfA Gebäude | C52: € | D52: =D51 -> 4885.3569 | E52: =D52+E51 -> 9770.7139 | F52: =E52+F51 -> 14656.071 | G52: =F52+G51 -> 19541.428 | H52: =G52+H51 -> 24426.785 | I52: =H52+I51 -> 29312.142 | J52: =I52+J51 -> 34197.499 | K52: =J52+K51 -> 39082.855 | L52: =K52+L51 -> 43968.212 | ... AQ52: =AP52+AQ51 -> 195414.28
B53: Restwert Gebäude Jahresende | C53: € | D53: =D47-D52 -> 239382.49 | E53: =E47-E52 -> 234497.13 | F53: =F47-F52 -> 229611.78 | G53: =G47-G52 -> 224726.42 | H53: =H47-H52 -> 219841.06 | I53: =I47-I52 -> 214955.71 | J53: =J47-J52 -> 210070.35 | K53: =K47-K52 -> 205184.99 | ... AQ53: =AQ47-AQ52 -> 48853.569
B54: Erhöhte Absetzungen § 7h / § 7i (Sanierungsanteil) | C54: € | D54: =IF(Sanierung_eff>0,IF(D41<=8,Satz_7i_1,IF(D41<=12,Satz_7i_2,0))*Sanierung_eff,0) -> 0 | E54: =IF(Sanierung_eff>0,IF(E41<=8,Satz_7i_1,IF(E41<=12,Satz_7i_2,0))*Sanierung_eff,0) -> 0 | F54: =IF(Sanierung_eff>0,IF(F41<=8,Satz_7i_1,IF(F41<=12,Satz_7i_2,0))*Sanierung_eff,0) -> 0 | G54: =IF(Sanierung_eff>0,IF(G41<=8,Satz_7i_1,IF(G41<=12,Satz_7i_2,0))*Sanierung_eff,0) -> 0 | H54: =IF(Sanierung_eff>0,IF(H41<=8,Satz_7i_1,IF(H41<=12,Satz_7i_2,0))*Sanierung_eff,0) -> 0 | I54: =IF(Sanierung_eff>0,IF(I41<=8,Satz_7i_1,IF(I41<=12,Satz_7i_2,0))*Sanierung_eff,0) -> 0 | J54: =IF(Sanierung_eff>0,IF(J41<=8,Satz_7i_1,IF(J41<=12,Satz_7i_2,0))*Sanierung_eff,0) -> 0 | K54: =IF(Sanierung_eff>0,IF(K41<=8,Satz_7i_1,IF(K41<=12,Satz_7i_2,0))*Sanierung_eff,0) -> 0 | ... AQ54: =IF(Sanierung_eff>0,IF(AQ41<=8,Satz_7i_1,IF(AQ41<=12,Satz_7i_2,0))*Sanierung_eff,0) -> 0
B55: AfA bewegliche Gegenstände (Einbauküche etc.) | C55: € | D55: =IF(AND(N(ND_bewegl)>0,D41<=N(ND_bewegl)),KP_bewegl/N(ND_bewegl),0) -> 800 | E55: =IF(AND(N(ND_bewegl)>0,E41<=N(ND_bewegl)),KP_bewegl/N(ND_bewegl),0) -> 800 | F55: =IF(AND(N(ND_bewegl)>0,F41<=N(ND_bewegl)),KP_bewegl/N(ND_bewegl),0) -> 800 | G55: =IF(AND(N(ND_bewegl)>0,G41<=N(ND_bewegl)),KP_bewegl/N(ND_bewegl),0) -> 800 | H55: =IF(AND(N(ND_bewegl)>0,H41<=N(ND_bewegl)),KP_bewegl/N(ND_bewegl),0) -> 800 | I55: =IF(AND(N(ND_bewegl)>0,I41<=N(ND_bewegl)),KP_bewegl/N(ND_bewegl),0) -> 800 | J55: =IF(AND(N(ND_bewegl)>0,J41<=N(ND_bewegl)),KP_bewegl/N(ND_bewegl),0) -> 800 | K55: =IF(AND(N(ND_bewegl)>0,K41<=N(ND_bewegl)),KP_bewegl/N(ND_bewegl),0) -> 800 | ... AQ55: =IF(AND(N(ND_bewegl)>0,AQ41<=N(ND_bewegl)),KP_bewegl/N(ND_bewegl),0) -> 0
B56: = Abschreibungen gesamt | C56: € | D56: =D51+D54+D55 -> 5685.3569 | E56: =E51+E54+E55 -> 5685.3569 | F56: =F51+F54+F55 -> 5685.3569 | G56: =G51+G54+G55 -> 5685.3569 | H56: =H51+H54+H55 -> 5685.3569 | I56: =I51+I54+I55 -> 5685.3569 | J56: =J51+J54+J55 -> 5685.3569 | K56: =K51+K54+K55 -> 5685.3569 | ... AQ56: =AQ51+AQ54+AQ55 -> 4885.3569
B57: Kumulierte Abschreibungen gesamt | C57: € | D57: =D56 -> 5685.3569 | E57: =D57+E56 -> 11370.714 | F57: =E57+F56 -> 17056.071 | G57: =F57+G56 -> 22741.428 | H57: =G57+H56 -> 28426.785 | I57: =H57+I56 -> 34112.142 | J57: =I57+J56 -> 39797.499 | K57: =J57+K56 -> 45482.855 | L57: =K57+L56 -> 51168.212 | ... AQ57: =AP57+AQ56 -> 203414.28
B59: Steuerliches Ergebnis aus dem Objekt | C59: ↑ Übersicht | D59: =D$42 -> 2026 | E59: =E$42 -> 2027 | F59: =F$42 -> 2028 | G59: =G$42 -> 2029 | H59: =H$42 -> 2030 | I59: =I$42 -> 2031 | J59: =J$42 -> 2032 | K59: =K$42 -> 2033 | ... AQ59: =AQ$42 -> 2065
B60: Einnahmen: Nettokaltmiete Ist | C60: € | D60: =Projektion!D15 -> 11058 | E60: =Projektion!E15 -> 11279.16 | F60: =Projektion!F15 -> 11504.743 | G60: =Projektion!G15 -> 11734.838 | H60: =Projektion!H15 -> 11969.535 | I60: =Projektion!I15 -> 12208.926 | J60: =Projektion!J15 -> 12453.104 | K60: =Projektion!K15 -> 12702.166 | ... AQ60: =Projektion!AQ15 -> 23937.748
B61: Bewirtschaftungskosten (steuerlich) | C61: € | D61: =Projektion!D20+Projektion!D22+Projektion!D23 -> 1020 | E61: =Projektion!E20+Projektion!E22+Projektion!E23 -> 1040.4 | F61: =Projektion!F20+Projektion!F22+Projektion!F23 -> 1061.208 | G61: =Projektion!G20+Projektion!G22+Projektion!G23 -> 1082.4322 | H61: =Projektion!H20+Projektion!H22+Projektion!H23 -> 1104.0808 | I61: =Projektion!I20+Projektion!I22+Projektion!I23 -> 1126.1624 | J61: =Projektion!J20+Projektion!J22+Projektion!J23 -> 1148.6857 | K61: =Projektion!K20+Projektion!K22+Projektion!K23 -> 1171.6594 | ... AQ61: =Projektion!AQ20+Projektion!AQ22+Projektion!AQ23 -> 2208.0397
B62: Schuldzinsen | C62: € | D62: =Finanzierung!D35 -> 9000 | E62: =Finanzierung!E35 -> 8820 | F62: =Finanzierung!F35 -> 8633.52 | G62: =Finanzierung!G35 -> 8440.3267 | H62: =Finanzierung!H35 -> 8240.1785 | I62: =Finanzierung!I35 -> 8032.8249 | J62: =Finanzierung!J35 -> 7818.0066 | K62: =Finanzierung!K35 -> 7595.4548 | ... AQ62: =Finanzierung!AQ35 -> 0
